Workbook
Name clCompletado: #REF!
Name clConRetraso: #REF!
Name clEnCurso: #REF!
Name clPersonalizado1: #REF!
Name clPersonalizado2: #REF!
Name clPersonalizado4: #REF!
Name clSinComenzar: #REF!
Name S: #REF!
Name SegmentaciónDeDatos_EMPRESA: #N/A
Name txtPersonalizado1: #REF!
Name txtPersonalizado2: #REF!
Name txtPersonalizado3: #REF!
Name txtPersonalizado4: #REF!

Sheet Colaboradores
A1: Cod_colab | B1: Id | C1: Nombre | D1: Pasaporte | E1: Movil | F1: StatusSeguridad | G1: FechaAlta | H1: FechaBaja | I1: FechaInicio | J1: FechaFinPedido | K1: FechaSalidaTrabajador | L1: Contratante
A2: E1172 | B2: 1172 | C2: ABDALLAH SAMMAR | E2: +351 964 185 751 | F2: Baja | G2: 45581.917 | H2: 45645.958 | K2: 45645.958 | L2: KOTRIK INDUSTRIAL
A3: E0530 | B3: 530 | C3: ABDELFAHAM OUBOUZID | D3: 166231325 | E3: +351 927 245 833 | F3: Baja | G3: 45778.917 | K3: 45889.917 | L3: KOTRIK ROSAS
A4: E1365 | B4: 1365 | C4: ABDELHAQ GUEHOUANE | E4: 34 602 49 64 70 | F4: Baja | G4: 45438.917 | H4: 45476.917 | K4: 45456.917 | L4: KOTRIK INDUSTRIAL
A5: E1855 | B5: 1855 | C5: ABDRUBAL FONSECA RINCON | D5: BG974479 | E5: +57 311 686 4894
A6: E0663 | B6: 663 | C6: ABEL ANTONIO CUESTA CIFUENTES | E6: +39 366 142 9913 | F6: Baja | G6: 45643.958 | K6: 45666.958 | L6: KOTRIK ROSAS
A7: E0513 | B7: 513 | C7: ABRAHAM DAVID HOYOS ALVAREZ | D7: BE508253 | E7: +57 301 7613079 | F7: alta | G7: 45705.958 | L7: STOCCO
A8: E0432 | B8: 432 | C8: ADALBERTO ARAGON GOMEZ | E8: +57 310 4676699 | F8: Alta | G8: 45761.917 | L8: KOTRIK INDUSTRIAL
A9: E0687 | B9: 687 | C9: ADILSON ESCOBAR OREJUELA | D9: BE550492 | E9: +34 616 68 47 21 | F9: Baja | G9: 45760.917 | H9: 45773.917 | K9: 45773.917 | L9: KOTRIK ROSAS
A10: E1050 | B10: 1050 | C10: ADRIAN BERNAL GOMEZ | E10: +34 654 47 87 56 | F10: anulado | G10: 45553.917 | L10: KOTRIK ROSAS
A11: E0570 | B11: 570 | C11: ADRIAN CAMILO PINILLA AGUIRRE | E11: +57 311 5096970 | F11: Pendiente Alta | L11: KOTRIK INDUSTRIAL
A12: E0452 | B12: 452 | C12: ADRIAN CARLOSAMA CHAVEZ | E12: +34 604 21 21 79 | F12: pendiente alta | L12: STOCCO
A13: E1221 | B13: 1221 | C13: ADRIAN RICARDO BAQUERO GONZALEZ | E13: 57 320 4650287 | F13: Baja | G13: 45524.917 | H13: 45649.958 | K13: 45649.958 | L13: KOTRIK INDUSTRIAL
A14: E0764 | B14: 764 | C14: ADRIANO DOS SANTOS DE CARVALHO | E14: 351 910 384 813 | F14: Baja | G14: 45070.917 | K14: 45482.917 | L14: KOTRIK INDUSTRIAL
A15: E0516 | B15: 516 | C15: AGNER MARTINEZ CARREAZO | E15: +34 603 22 41 86 | F15: pendiente alta | L15: STOCCO
A16: E0814 | B16: 814 | C16: AGUINALDO JOSE DA SILVA SOUZA | D16: FR290366 | E16: 351 960 190 974 | F16: Anulado
A17: E0194 | B17: 194 | C17: ALAN FRANCISCO NAVAS DIAZ | D17: BD749809 | E17: +57 323 4616593 | F17: Alta | G17: 45760.917 | L17: KOTRIK ROSAS
A18: E0406 | B18: 406 | C18: ALAN GERSON RAMIREZ ACARO | D18: 120655378 | E18: +51 947 371 486 | F18: pendiente alta | L18: KOTRIK ROSAS
A19: E1402 | B19: 1402 | C19: ALBEIRO CARDOZO HEREDIA | D19: AY405605 | E19: +57 310 418 7853 | F19: Pendiente Alta | I19: 45804.917 | J19: 45835.917 | L19: KOTRIK ROSAS
A20: E0347 | B20: 347 | C20: ALBEIRO ENRIQUE AMOR AGUILAR | D20: AQ894821 | E20: +57 321 2579013 | F20: Pendiente Alta | G20: 45760.917 | L20: Kotrik & Rosas
A21: E0272 | B21: 272 | C21: ALBEIRO OBANDO MICOLTA | D21: BD593560 | E21: +34 637 08 87 33 | F21: Alta | G21: 45776.917 | L21: KOTRIK INDUSTRIAL
A22: E0853 | B22: 853 | C22: ALBERT IGO SILVA LIMA DE CERQUEIRA | E22: 351 926 101 401 | F22: Anulado | L22: KOTRIK INDUSTRIAL
A23: E0189 | B23: 189 | C23: ALBERTO CCENHUA MICHCA | E23: +51 956 343 384 | F23: Pendiente Alta | L23: KOTRIK INDUSTRIAL
A24: E0208 | B24: 208 | C24: ALBERTO DURAN | D24: AV989255 | E24: +48 790 797 494 | F24: Alta | G24: 45760.917 | L24: KOTRIK ROSAS
A25: E0134 | B25: 134 | C25: ALBERTO ENRIQUE MACIAS TEHERAN | E25: 57 324 5729666 | F25: Alta | G25: 45761.917 | L25: KOTRIK INDUSTRIAL
A26: E0449 | B26: 449 | C26: ALBERTO ISMAEL MENDIETA CACERES | D26: 122134064 | E26: +51 983 738 942 | F26: pendiente alta | L26: KOTRIK ROSAS
A27: E1448 | B27: 1448 | C27: ALBERTO LUIS MALDONADO BARRERA | D27: AY305422 | E27: 57 323 2914686 | F27: Pendiente Alta | L27: STOCCO
A28: E2135 | B28: 2135 | C28: ALBERTO RICHELLI DA SILVA | D28: GE293997 | E28: +351 932 828 968
A29: E1356 | B29: 1356 | C29: ALDAIR GABRIEL LARA RAMIREZ | E29: +34 611 376 106 | F29: Anulado | L29: KOTRIK ROSAS
A30: E2114 | B30: 2114 | C30: ALDEMAR DOMINGUEZ CERCADO | D30: BG720416 | E30: +34 604 10 75 05
A31: E0460 | B31: 460 | C31: ALDO IVAN AILIO LABBE | D31: AAI878342 | E31: +54 911 265 34702 | F31: Pendiente Alta | L31: KOTRIK INDUSTRIAL
A32: E1382 | B32: 1382 | C32: ALDO LUIS CHACON BALAREZO | D32: 223302581 | E32: +51 915 332 957 | F32: Baja | K32: 45719.958 | L32: KOTRIK ROSAS
A33: E1449 | B33: 1449 | C33: ALDRINIS EDWARDS MENDOZA NIETO | E33: +57 301 782 4463 | F33: Pendiente Alta | L33: STOCCO
A34: E0648 | B34: 648 | C34: ALDRUMAR CABALLERO MARTINEZ | D34: AT606726 | E34: +57 316 299 0121 | F34: Baja | K34: 45781.917 | L34: KOTRIK ROSAS
A35: E0243 | B35: 243 | C35: ALEEX IVAN LOPEZ CUBILLOS | D35: BE054818 | E35: +34 641 56 11 84 | F35: Alta | G35: 45761.917 | L35: KOTRIK INDUSTRIAL
A36: E1770 | B36: 1770 | C36: ALEJANDRO ERWIN ZAMBRANO AGUILERA | D36: P13933983 | E36: +46 767 098 768 | F36: Pendiente Alta | L36: WISEOWE, UNIPESSOAL LDA
A37: E0662 | B37: 662 | C37: ALEJANDRO GONZALO URIBE | E37: +57 320 7160004 | F37: Baja | G37: 45536.917 | H37: 45555.917 | K37: 45555.917 | L37: KOTRIK ROSAS
A38: E0009 | B38: 9 | C38: ALEJANDRO HERNANDEZ PIMIENTA | D38: AS996395 | E38: +57 313 7806680 | F38: Alta | G38: 45784.917 | K38: 45804.917 | L38: KOTRIK INDUSTRIAL
A39: E0128 | B39: 128 | C39: ALEJANDRO JOSE BORJA MANGA | E39: +34647527268 | F39: Alta | G39: 45784.917 | H39: 45747.917 | L39: KOTRIK INDUSTRIAL
A40: E0960 | B40: 960 | C40: ALEJANDRO QUINCENO ROA | E40: 34 674 42 17 82 | F40: Baja | G40: 45470.917 | H40: 45566.917 | K40: 45566.917 | L40: KOTRIK ROSAS
A41: E1352 | B41: 1352 | C41: ALESSANDRO FERREIRA | F41: Anulado
A42: E1253 | B42: 1253 | C42: ALESSANDRO SANTANA DE JESUS | E42: +351 915 857 016 | F42: Anulado | L42: KOTRIK ROSAS
A43: E1380 | B43: 1380 | C43: ALEX ALTAMAR CARMONA | E43: +57 350 6415820 | F43: baja | K43: 45715.958 | L43: KOTRIK ROSAS
A44: E0388 | B44: 388 | C44: ALEX DAVID GOMEZ VILLADA | D44: AW558954 | E44: +34 633 10 59 23 | F44: Alta | G44: 45761.917 | L44: KOTRIK INDUSTRIAL
A45: E1921 | B45: 1921 | C45: ALEX JAVIER LEONEL OTAVO | D45: BD414292 | E45: +34 602 592 928
A46: E1319 | B46: 1319 | C46: ALEX LUCAS SCHOROEDER | E46: +351 912 814 148 | F46: Baja | G46: 45700.958 | L46: KOTRIK INDUSTRIAL
A47: E0593 | B47: 593 | C47: ALEX MAURICIO CARDONA RAMIREZ | D47: BE848923 | E47: +34 643 67 45 89 | F47: pendiente alta | L47: KOTRIK ROSAS
A48: E0302 | B48: 302 | C48: ALEX MENDOZA ALCAZAR | E48: +351 922 243 701 | F48: Alta | G48: 45799.917 | L48: KOTRIK INDUSTRIAL
A49: E1056 | B49: 1056 | C49: ALEX SANDRO VALENGA | E49: 351 932 585 168 | F49: Baja | G49: 45401.917 | H49: 45432.917 | L49: KOTRIK INDUSTRIAL
A50: E1400 | B50: 1400 | C50: ALEXANDER ALONSO ROMERO | D50: BG171257 | E50: +57 311 544 3382 | F50: Pendiente Alta
A51: E0362 | B51: 362 | C51: ALEXANDER ANTHONY ZAMORA ALMENDARIZ | D51: 124688504 | E51: +34 645 01 84 52 | F51: Pendiente Alta | L51: KOTRIK INDUSTRIAL
A52: E0456 | B52: 456 | C52: ALEXANDER DE LA OSSA VEGA | E52: +57 300 6171364 | F52: Alta | G52: 45761.917 | L52: KOTRIK INDUSTRIAL
A53: E1936 | B53: 1936 | C53: ALEXANDER GUTIERREZ MONTANEZ | D53: AZ841752 | E53: +34 603 190 229
A54: E1450 | B54: 1450 | C54: ALEXANDER GUTIERREZ MONTAÑEZ | E54: +57 320 6977132 | F54: Pendiente Alta | L54: STOCCO
A55: E2098 | B55: 2098 | C55: ALEXANDER GUZMAN | D55: AS735626 | E55: +57 316 4247180
A56: E0831 | B56: 831 | C56: ALEXANDER JAVIER ALBINO JIMENEZ | E56: +48 783 056 361 | F56: Anulado | L56: KOTRIK INDUSTRIAL
A57: E0386 | B57: 386 | C57: ALEXANDER MANUEL LOPEZ ROJAS | D57: AV692233 | E57: +48 731 013 497 | F57: Alta | G57: 45761.917 | L57: KOTRIK INDUSTRIAL
A58: E1684 | B58: 1684 | C58: ALEXANDER PEREIRA HERNANDEZ | D58: BD874725 | E58: +48 515 733 428 | L58: Stocco LDA
A59: E1451 | B59: 1451 | C59: ALEXANDER SUAREZ PULGAR | D59: BD467127 | E59: 57 321 720 7178 | F59: Pendiente Alta | L59: Kotrik Industrial, LDA
A60: E1313 | B60: 1313 | C60: ALEXANDRE BEZERRA DE OLIVEIRA | E60: +351 929 070 753 | F60: baja | G60: 45728.958 | H60: 45763.917 | K60: 45763.917 | L60: KOTRIK INDUSTRIAL
A61: E1984 | B61: 1984 | C61: ALEXEI MOLINA CHICA | E61: +58 4146978916
A62: E1876 | B62: 1876 | C62: ALEXIS DIAGO ZUNIGA | D62: BF904145 | E62: +34 610 72 21 22
A63: E2074 | B63: 2074 | C63: ALEXIS ENRIQUE MORENO ARRIETA | D63: BG732756 | E63: +57 314 5412524
A64: E1273 | B64: 1273 | C64: ALEXIS HAIR GALEANO BOTELLO | E64: +34 600 77 33 42 | F64: Baja | G64: 45464.917 | H64: 45531.917 | K64: 45531.917 | L64: KOTRIK INDUSTRIAL
A65: E1355 | B65: 1355 | C65: ALEXIS JESUS SUAREZ GONZALEZ | D65: BC575429 | E65: +57 312 630 5315 | F65: Baja | K65: 45799.917 | L65: KOTRIK INDUSTRIAL
A66: E1277 | B66: 1277 | C66: ALEXIS ORTIZ | E66: +57 311 2797029 | F66: anulado | L66: STOCCO
A67: E1051 | B67: 1051 | C67: ALFONSO DE JESUS YANES CABARCAS | E67: +57 323 5868503 | F67: anulado | L67: KOTRIK INDUSTRIAL
A68: E1973 | B68: 1973 | C68: ALFREDO ANTONIO OSPINO RANGEL | D68: BD903027 | E68: +57 301 607 8912
A69: E1128 | B69: 1128 | C69: ALFREDO ENRIQUE RODRIGUEZ NOGUERA | E69: +57 314 4890387 | F69: baja | L69: KOTRIK INDUSTRIAL
A70: E2018 | B70: 2018 | C70: ALIRIO ACEROS AGUILAR | E70: +57 314 30 44143
A71: E0254 | B71: 254 | C71: ALIRIO ORTIZ MOLINA | D71: BE286208 | E71: +34 642 60 05 16 | F71: Alta | G71: 45760.917 | L71: KOTRIK ROSAS
A72: E0934 | B72: 934 | C72: ALISSON ANTONIO SOUSA DOS SANTOS | E72: +351 964 686 820 | F72: Pendiente Baja | G72: 45669.958 | K72: 45708.958 | L72: KOTRIK ROSAS
A73: E0783 | B73: 783 | C73: ALONSO PRADA | E73: 34 624 09 61 14 | F73: Anulado | L73: KOTRIK INDUSTRIAL
A74: E1236 | B74: 1236 | C74: ALONSO SIERRA GAFARO | E74: 57 314 3506000 | F74: Anulado | L74: KOTRIK ROSAS
A75: E1244 | B75: 1244 | C75: ALONSO SOLANO GOMEZ | E75: +34 647 50 93 68 | F75: Baja | L75: KOTRIK ROSAS
A76: E1232 | B76: 1232 | C76: ALVARO ADRIAN GOMEZ CASTRO | E76: +34 640 79 60 80 | F76: Baja | K76: 45735.958 | L76: KOTRIK ROSAS
A77: E0888 | B77: 888 | C77: ALVARO ANDRES ARBELAEZ | E77: +57 317-4121683 | F77: Baja | K77: 45533.917 | L77: KOTRIK ROSAS
A78: E0769 | B78: 769 | C78: ALVARO ANDRES QUIÑONES ZUÑIGA | E78: 34 674 04 37 18 | F78: Baja | G78: 45438.917 | H78: 45534.917 | K78: 45534.917 | L78: KOTRIK INDUSTRIAL
A79: E1707 | B79: 1707 | C79: ALVARO ARIZA CONTRERAS | D79: BE168542 | E79: +57 320 6915049 | F79: Pendiente Alta | L79: Kotrik Industrial, LDA
A80: E0677 | B80: 677 | C80: ALVARO DAZA MESA | E80: +57 321 3414128 | F80: Baja | G80: 45669.958 | K80: 45725.958 | L80: KOTRIK INDUSTRIAL
A81: E0815 | B81: 815 | C81: ALVARO DIAZ GARCIA | E81: 48 731 176 989 | F81: Anulado | L81: KOTRIK INDUSTRIAL
A82: E0166 | B82: 166 | C82: ALVARO ENRIQUE ROJAS DE LA OSSA | D82: AQ520819 | E82: +34 672 20 36 15 | F82: Alta | G82: 45761.917 | L82: KOTRIK INDUSTRIAL
A83: E0651 | B83: 651 | C83: ALVARO ESPINOSA ALCALDE | E83: +34 672 97 80 14 | F83: Baja | G83: 45634.958 | K83: 45706.958 | L83: KOTRIK ROSAS
A84: E0565 | B84: 565 | C84: ALVARO FIGUEROA ARANGO | D84: BF806838 | E84: +57 313 436 0999 | F84: Pendiente Alta | L84: Wiseowe LDA
A85: E2079 | B85: 2079 | C85: ALVARO JAVIER NARVAEZ MUÑOZ | D85: BD516455 | E85: 34607275082 | F85: Alta | G85: 45826.917
A86: E0247 | B86: 247 | C86: ALVARO JOSE NAVARRETE GAMBOA | E86: +34 662 48 33 12 | F86: Alta | G86: 45799.917 | L86: KOTRIK ROSAS
A87: E0442 | B87: 442 | C87: ALVARO JUNIOR CERVANTES MELENDEZ | E87: +57 310 738 2860 | F87: Pendiente Alta | L87: KOTRIK INDUSTRIAL
A88: E1061 | B88: 1061 | C88: ALVARO NAVARRO CONTRERAS | E88: 34 673917276 | F88: Anulado | L88: KOTRIK INDUSTRIAL
A89: E1404 | B89: 1404 | C89: ALVARO PUERTA ESPITIA | D89: BC803810 | E89: +48 505 734 353 | F89: Pendiente Alta | I89: 45810.917 | L89: Wiseowe LDA
A90: E1882 | B90: 1882 | C90: ALVARO SEGOVIA TORRES | D90: AV605518 | E90: +57 320 489 0425
A91: E1192 | B91: 1192 | C91: ALVARO SOLARTE VARON | E91: +34 600 47 04 14 | F91: Baja | G91: 45600.958 | K91: 45730.958 | L91: KOTRIK ROSAS
A92: E1330 | B92: 1330 | C92: ALYSON HENRIQUE SILVA NASCIMENTO | E92: +351 926 787 364 | F92: Baja | G92: 45705.958 | K92: 45729.958 | L92: KOTRIK INDUSTRIAL
A93: E1878 | B93: 1878 | C93: AMADOR JOSE JIMENEZ | D93: 196828893 | E93: +57 315 490 5421
A94: E1703 | B94: 1703 | C94: ANDERSON CHELUVAY GONZALEZ TRUJILLO | D94: AY076491 | E94: +57 313 813 3854 | F94: Pendiente Alta | L94: Kotrik & Rosas
A95: E1186 | B95: 1186 | C95: ANDERSON CORREA FLORES | E95: +34 640 93 28 44 | F95: Anulado | L95: KOTRIK ROSAS
A96: E0175 | B96: 175 | C96: ANDERSSON CANAVAL NUÑEZ | E96: +57 333 2625846 | F96: alta | G96: 45678.958 | L96: STOCCO
A97: E0536 | B97: 536 | C97: ANDERSSON DENILSON GOMEZ ASCENSIO | E97: +51 912 683 395 | F97: Pendiente Alta | L97: KOTRIK INDUSTRIAL
A98: E1331 | B98: 1331 | C98: ANDRE DA SILVA ARAUJO | E98: +351 933 835 552 | F98: Baja | G98: 45705.958 | L98: KOTRIK INDUSTRIAL
A99: E2067 | B99: 2067 | C99: ANDRES AGREDO ARBOLEDA | D99: AX610947 | E99: +57 316 6743908
A100: E1891 | B100: 1891 | C100: ANDRES ALEXANDER BEJARANO PEREZ | D100: BG383525 | E100: +34 624 36 99 54
...

Sheet Analises
W6: Janeiro | X6: Fevereiro | Y6: Março | Z6: Abril | AA6: Maio | AB6: Junho | AC6: Julho | AD6: Agosto
V7: Wiseowe | AA7: 18720.63 | AB7: 43132.986 | AC7: 47111.644 | AD7: 130651.03
V8: Kotrik Industrial | AA8: 877075.91 | AB8: 836098.04 | AC8: 614968.95 | AD8: 458754.58
V9: Kotrik Rosas | AA9: 673295.74 | AB9: 554018.72 | AC9: 532254.25 | AD9: 404359.84

Sheet Declaração salário
D1: VENCIMENTOS JANEIRO
B2: EMPRESA | C2: COD | D2: TRABALHADOR | E2: INICIO VINCULO | F2: FIM VINCULO | G2: HORAS TRABALHADAS | H2: TARIFA | I2: ALOJAMENTO | J2: DIAS DE ALTA | K2: IMPOSTO | L2: CARRO | M2: OUTROS DEScontos | N2: VALOR | O2: SALDO PENDENTE | P2: Columna1
B3: KR | C3: =IF(D3="", "", INDEX(Colaboradores!A:A, MATCH(D3,Colaboradores!C:C, 0))) -> E0194 | D3: ALAN FRANCISCO NAVAS DIAZ | E3: 45761 | F3: 46053 | G3: =IFERROR(VLOOKUP(Tabla10[[#This Row],[COD]],'TotalHorasAjustadas (2)'!D:L,8,FALSE),"") -> 144 | H3: =IFERROR(VLOOKUP(Tabla10[[#This Row],[COD]],Tabla15[],4,FALSE),"") -> 13 | I3: =IFERROR(VLOOKUP(Tabla10[[#This Row],[COD]],Alojamentos!B:P,11,FALSE),"") -> 300 | J3: =IF(ISBLANK(Tabla10[[#This Row],[INICIO VINCULO]]), 0, MAX(0, MIN(IF(ISBLANK(Tabla10[[#This Row],[FIM VINCULO]]), DATE(2026,1,31), Tabla10[[#This Row],[FIM VINCULO]]), DATE(2026,1,31)) - MAX(Tabla10[[#This Row],[INICIO VINCULO]], DATE(2026,1,1)) + 1)) -> 31 | K3: =7.05806*Tabla10[[#This Row],[DIAS DE ALTA]] -> 218.79986 | L3: =IFERROR(VLOOKUP(Tabla10[[#This Row],[COD]],Carro!B:D,3,FALSE),"") | M3: =IFERROR(VLOOKUP(Tabla10[[#This Row],[COD]],'Outros descontos'!B:P,15,FALSE),"") | N3: =(Tabla10[[#This Row],[HORAS TRABALHADAS]]*Tabla10[[#This Row],[TARIFA]]) - SUM(Tabla10[[#This Row],[ALOJAMENTO]], Tabla10[[#This Row],[IMPOSTO]], Tabla10[[#This Row],[CARRO]]) -> 1353.2001
B4: WS | C4: =IF(D4="", "", INDEX(Colaboradores!A:A, MATCH(D4,Colaboradores!C:C, 0))) -> E0272 | D4: ALBEIRO OBANDO MICOLTA | E4: 45945 | G4: =IFERROR(VLOOKUP(Tabla10[[#This Row],[COD]],'TotalHorasAjustadas (2)'!D:L,8,FALSE),"") -> 179 | H4: =IFERROR(VLOOKUP(Tabla10[[#This Row],[COD]],Tabla15[],4,FALSE),"") -> 17 | I4: =IFERROR(VLOOKUP(Tabla10[[#This Row],[COD]],Alojamentos!B:P,11,FALSE),"") -> 300 | J4: =IF(ISBLANK(Tabla10[[#This Row],[INICIO VINCULO]]), 0, MAX(0, MIN(IF(ISBLANK(Tabla10[[#This Row],[FIM VINCULO]]), DATE(2026,1,31), Tabla10[[#This Row],[FIM VINCULO]]), DATE(2026,1,31)) - MAX(Tabla10[[#This Row],[INICIO VINCULO]], DATE(2026,1,1)) + 1)) -> 31 | K4: =7.05806*Tabla10[[#This Row],[DIAS DE ALTA]] -> 218.79986 | L4: =IFERROR(VLOOKUP(Tabla10[[#This Row],[COD]],Carro!B:D,3,FALSE),"") | M4: =IFERROR(VLOOKUP(Tabla10[[#This Row],[COD]],'Outros descontos'!B:P,15,FALSE),"") | N4: =(Tabla10[[#This Row],[HORAS TRABALHADAS]]*Tabla10[[#This Row],[TARIFA]]) - SUM(Tabla10[[#This Row],[ALOJAMENTO]], Tabla10[[#This Row],[IMPOSTO]], Tabla10[[#This Row],[CARRO]]) -> 2524.2001
B5: KI | C5: =IF(D5="", "", INDEX(Colaboradores!A:A, MATCH(D5,Colaboradores!C:C, 0))) -> E0388 | D5: ALEX DAVID GOMEZ VILLADA | E5: 45762 | F5: 46052 | G5: =IFERROR(VLOOKUP(Tabla10[[#This Row],[COD]],'TotalHorasAjustadas (2)'!D:L,8,FALSE),"") -> 181 | H5: =IFERROR(VLOOKUP(Tabla10[[#This Row],[COD]],Tabla15[],4,FALSE),"") -> 15 | I5: =IFERROR(VLOOKUP(Tabla10[[#This Row],[COD]],Alojamentos!B:P,11,FALSE),"") | J5: =IF(ISBLANK(Tabla10[[#This Row],[INICIO VINCULO]]), 0, MAX(0, MIN(IF(ISBLANK(Tabla10[[#This Row],[FIM VINCULO]]), DATE(2026,1,31), Tabla10[[#This Row],[FIM VINCULO]]), DATE(2026,1,31)) - MAX(Tabla10[[#This Row],[INICIO VINCULO]], DATE(2026,1,1)) + 1)) -> 30 | K5: =7.05806*Tabla10[[#This Row],[DIAS DE ALTA]] -> 211.7418 | L5: =IFERROR(VLOOKUP(Tabla10[[#This Row],[COD]],Carro!B:D,3,FALSE),"") | M5: =IFERROR(VLOOKUP(Tabla10[[#This Row],[COD]],'Outros descontos'!B:P,15,FALSE),"") | N5: =(Tabla10[[#This Row],[HORAS TRABALHADAS]]*Tabla10[[#This Row],[TARIFA]]) - SUM(Tabla10[[#This Row],[ALOJAMENTO]], Tabla10[[#This Row],[IMPOSTO]], Tabla10[[#This Row],[CARRO]]) -> 2503.2582
B6: LM | C6: =IF(D6="", "", INDEX(Colaboradores!A:A, MATCH(D6,Colaboradores!C:C, 0))) -> E2098 | D6: ALEXANDER GUZMAN | E6: 46051 | G6: =IFERROR(VLOOKUP(Tabla10[[#This Row],[COD]],'TotalHorasAjustadas (2)'!D:L,8,FALSE),"") -> 23 | H6: 15 | I6: =IFERROR(VLOOKUP(Tabla10[[#This Row],[COD]],Alojamentos!B:P,11,FALSE),"") | J6: =IF(ISBLANK(Tabla10[[#This Row],[INICIO VINCULO]]), 0, MAX(0, MIN(IF(ISBLANK(Tabla10[[#This Row],[FIM VINCULO]]), DATE(2026,1,31), Tabla10[[#This Row],[FIM VINCULO]]), DATE(2026,1,31)) - MAX(Tabla10[[#This Row],[INICIO VINCULO]], DATE(2026,1,1)) + 1)) -> 3 | K6: =7.05806*Tabla10[[#This Row],[DIAS DE ALTA]] -> 21.17418 | L6: =IFERROR(VLOOKUP(Tabla10[[#This Row],[COD]],Carro!B:D,3,FALSE),"") -> 10 | M6: =IFERROR(VLOOKUP(Tabla10[[#This Row],[COD]],'Outros descontos'!B:P,15,FALSE),"") | N6: =(Tabla10[[#This Row],[HORAS TRABALHADAS]]*Tabla10[[#This Row],[TARIFA]]) - SUM(Tabla10[[#This Row],[ALOJAMENTO]], Tabla10[[#This Row],[IMPOSTO]], Tabla10[[#This Row],[CARRO]]) -> 313.82582
B7: WS | C7: =IF(D7="", "", INDEX(Colaboradores!A:A, MATCH(D7,Colaboradores!C:C, 0))) -> E0386 | D7: ALEXANDER MANUEL LOPEZ ROJAS | E7: 45939 | G7: =IFERROR(VLOOKUP(Tabla10[[#This Row],[COD]],'TotalHorasAjustadas (2)'!D:L,8,FALSE),"") -> 188.5 | H7: =IFERROR(VLOOKUP(Tabla10[[#This Row],[COD]],Tabla15[],4,FALSE),"") -> 12 | I7: =IFERROR(VLOOKUP(Tabla10[[#This Row],[COD]],Alojamentos!B:P,11,FALSE),"") | J7: =IF(ISBLANK(Tabla10[[#This Row],[INICIO VINCULO]]), 0, MAX(0, MIN(IF(ISBLANK(Tabla10[[#This Row],[FIM VINCULO]]), DATE(2026,1,31), Tabla10[[#This Row],[FIM VINCULO]]), DATE(2026,1,31)) - MAX(Tabla10[[#This Row],[INICIO VINCULO]], DATE(2026,1,1)) + 1)) -> 31 | K7: =7.05806*Tabla10[[#This Row],[DIAS DE ALTA]] -> 218.79986 | L7: =IFERROR(VLOOKUP(Tabla10[[#This Row],[COD]],Carro!B:D,3,FALSE),"") | M7: =IFERROR(VLOOKUP(Tabla10[[#This Row],[COD]],'Outros descontos'!B:P,15,FALSE),"") | N7: =(Tabla10[[#This Row],[HORAS TRABALHADAS]]*Tabla10[[#This Row],[TARIFA]]) - SUM(Tabla10[[#This Row],[ALOJAMENTO]], Tabla10[[#This Row],[IMPOSTO]], Tabla10[[#This Row],[CARRO]]) -> 2043.2001
B8: LM | C8: =IF(D8="", "", INDEX(Colaboradores!A:A, MATCH(D8,Colaboradores!C:C, 0))) -> E0254 | D8: ALIRIO ORTIZ MOLINA | E8: 46030 | G8: =IFERROR(VLOOKUP(Tabla10[[#This Row],[COD]],'TotalHorasAjustadas (2)'!D:L,8,FALSE),"") -> 171 | H8: 15 | I8: =IFERROR(VLOOKUP(Tabla10[[#This Row],[COD]],Alojamentos!B:P,11,FALSE),"") -> 240 | J8: =IF(ISBLANK(Tabla10[[#This Row],[INICIO VINCULO]]), 0, MAX(0, MIN(IF(ISBLANK(Tabla10[[#This Row],[FIM VINCULO]]), DATE(2026,1,31), Tabla10[[#This Row],[FIM VINCULO]]), DATE(2026,1,31)) - MAX(Tabla10[[#This Row],[INICIO VINCULO]], DATE(2026,1,1)) + 1)) -> 24 | K8: =7.05806*Tabla10[[#This Row],[DIAS DE ALTA]] -> 169.39344 | L8: =IFERROR(VLOOKUP(Tabla10[[#This Row],[COD]],Carro!B:D,3,FALSE),"") | M8: =IFERROR(VLOOKUP(Tabla10[[#This Row],[COD]],'Outros descontos'!B:P,15,FALSE),"") | N8: =(Tabla10[[#This Row],[HORAS TRABALHADAS]]*Tabla10[[#This Row],[TARIFA]]) - SUM(Tabla10[[#This Row],[ALOJAMENTO]], Tabla10[[#This Row],[IMPOSTO]], Tabla10[[#This Row],[CARRO]]) -> 2155.6066
B9: KI | C9: =IF(D9="", "", INDEX(Colaboradores!A:A, MATCH(D9,Colaboradores!C:C, 0))) -> E0166 | D9: ALVARO ENRIQUE ROJAS DE LA OSSA | E9: 45762 | F9: 46053 | G9: =IFERROR(VLOOKUP(Tabla10[[#This Row],[COD]],'TotalHorasAjustadas (2)'!D:L,8,FALSE),"") -> 144 | H9: =IFERROR(VLOOKUP(Tabla10[[#This Row],[COD]],Tabla15[],4,FALSE),"") -> 17 | I9: =IFERROR(VLOOKUP(Tabla10[[#This Row],[COD]],Alojamentos!B:P,11,FALSE),"") | J9: =IF(ISBLANK(Tabla10[[#This Row],[INICIO VINCULO]]), 0, MAX(0, MIN(IF(ISBLANK(Tabla10[[#This Row],[FIM VINCULO]]), DATE(2026,1,31), Tabla10[[#This Row],[FIM VINCULO]]), DATE(2026,1,31)) - MAX(Tabla10[[#This Row],[INICIO VINCULO]], DATE(2026,1,1)) + 1)) -> 31 | K9: =7.05806*Tabla10[[#This Row],[DIAS DE ALTA]] -> 218.79986 | L9: =IFERROR(VLOOKUP(Tabla10[[#This Row],[COD]],Carro!B:D,3,FALSE),"") | M9: =IFERROR(VLOOKUP(Tabla10[[#This Row],[COD]],'Outros descontos'!B:P,15,FALSE),"") | N9: =(Tabla10[[#This Row],[HORAS TRABALHADAS]]*Tabla10[[#This Row],[TARIFA]]) - SUM(Tabla10[[#This Row],[ALOJAMENTO]], Tabla10[[#This Row],[IMPOSTO]], Tabla10[[#This Row],[CARRO]]) -> 2229.2001
B10: KR | C10: =IF(D10="", "", INDEX(Colaboradores!A:A, MATCH(D10,Colaboradores!C:C, 0))) -> E2079 | D10: ALVARO JAVIER NARVAEZ MUÑOZ | E10: 45827 | F10: 46052 | G10: =IFERROR(VLOOKUP(Tabla10[[#This Row],[COD]],'TotalHorasAjustadas (2)'!D:L,8,FALSE),"") -> 144 | H10: 15 | I10: =IFERROR(VLOOKUP(Tabla10[[#This Row],[COD]],Alojamentos!B:P,11,FALSE),"") -> 300 | J10: =IF(ISBLANK(Tabla10[[#This Row],[INICIO VINCULO]]), 0, MAX(0, MIN(IF(ISBLANK(Tabla10[[#This Row],[FIM VINCULO]]), DATE(2026,1,31), Tabla10[[#This Row],[FIM VINCULO]]), DATE(2026,1,31)) - MAX(Tabla10[[#This Row],[INICIO VINCULO]], DATE(2026,1,1)) + 1)) -> 30 | K10: =7.05806*Tabla10[[#This Row],[DIAS DE ALTA]] -> 211.7418 | L10: =IFERROR(VLOOKUP(Tabla10[[#This Row],[COD]],Carro!B:D,3,FALSE),"") | M10: =IFERROR(VLOOKUP(Tabla10[[#This Row],[COD]],'Outros descontos'!B:P,15,FALSE),"") | N10: =(Tabla10[[#This Row],[HORAS TRABALHADAS]]*Tabla10[[#This Row],[TARIFA]]) - SUM(Tabla10[[#This Row],[ALOJAMENTO]], Tabla10[[#This Row],[IMPOSTO]], Tabla10[[#This Row],[CARRO]]) -> 1648.2582
B11: WS | D11: ANA LUIZA TAVARES LARA | E11: 45819 | G11: 160 | H11: 0 | I11: =IFERROR(VLOOKUP(Tabla10[[#This Row],[COD]],Alojamentos!B:P,11,FALSE),"") | J11: =IF(ISBLANK(Tabla10[[#This Row],[INICIO VINCULO]]), 0, MAX(0, MIN(IF(ISBLANK(Tabla10[[#This Row],[FIM VINCULO]]), DATE(2026,1,31), Tabla10[[#This Row],[FIM VINCULO]]), DATE(2026,1,31)) - MAX(Tabla10[[#This Row],[INICIO VINCULO]], DATE(2026,1,1)) + 1)) -> 31 | K11: 0 | L11: =IFERROR(VLOOKUP(Tabla10[[#This Row],[COD]],Carro!B:D,3,FALSE),"") | M11: =IFERROR(VLOOKUP(Tabla10[[#This Row],[COD]],'Outros descontos'!B:P,15,FALSE),"") | N11: 1528.13
B12: WS | C12: =IF(D12="", "", INDEX(Colaboradores!A:A, MATCH(D12,Colaboradores!C:C, 0))) -> E0500 | D12: ANDRES CAMILO ALVAREZ CUERVO | E12: 45896 | G12: 208.5 | H12: =IFERROR(VLOOKUP(Tabla10[[#This Row],[COD]],Tabla15[],4,FALSE),"") -> 15 | I12: =IFERROR(VLOOKUP(Tabla10[[#This Row],[COD]],Alojamentos!B:P,11,FALSE),"") | J12: =IF(ISBLANK(Tabla10[[#This Row],[INICIO VINCULO]]), 0, MAX(0, MIN(IF(ISBLANK(Tabla10[[#This Row],[FIM VINCULO]]), DATE(2026,1,31), Tabla10[[#This Row],[FIM VINCULO]]), DATE(2026,1,31)) - MAX(Tabla10[[#This Row],[INICIO VINCULO]], DATE(2026,1,1)) + 1)) -> 31 | K12: =7.05806*Tabla10[[#This Row],[DIAS DE ALTA]] -> 218.79986 | L12: =IFERROR(VLOOKUP(Tabla10[[#This Row],[COD]],Carro!B:D,3,FALSE),"") -> 140 | M12: =IFERROR(VLOOKUP(Tabla10[[#This Row],[COD]],'Outros descontos'!B:P,15,FALSE),"") | N12: =(Tabla10[[#This Row],[HORAS TRABALHADAS]]*Tabla10[[#This Row],[TARIFA]]) - SUM(Tabla10[[#This Row],[ALOJAMENTO]], Tabla10[[#This Row],[IMPOSTO]], Tabla10[[#This Row],[CARRO]]) -> 2768.7001
B13: KR | C13: =IF(D13="", "", INDEX(Colaboradores!A:A, MATCH(D13,Colaboradores!C:C, 0))) -> E0359 | D13: ANDRES FELIPE GOMEZ PUERTA | E13: 45852 | F13: 46052 | G13: =IFERROR(VLOOKUP(Tabla10[[#This Row],[COD]],'TotalHorasAjustadas (2)'!D:L,8,FALSE),"") -> 133 | H13: =IFERROR(VLOOKUP(Tabla10[[#This Row],[COD]],Tabla15[],4,FALSE),"") -> 15 | I13: =IFERROR(VLOOKUP(Tabla10[[#This Row],[COD]],Alojamentos!B:P,11,FALSE),"") -> 300 | J13: =IF(ISBLANK(Tabla10[[#This Row],[INICIO VINCULO]]), 0, MAX(0, MIN(IF(ISBLANK(Tabla10[[#This Row],[FIM VINCULO]]), DATE(2026,1,31), Tabla10[[#This Row],[FIM VINCULO]]), DATE(2026,1,31)) - MAX(Tabla10[[#This Row],[INICIO VINCULO]], DATE(2026,1,1)) + 1)) -> 30 | K13: =7.05806*Tabla10[[#This Row],[DIAS DE ALTA]] -> 211.7418 | L13: =IFERROR(VLOOKUP(Tabla10[[#This Row],[COD]],Carro!B:D,3,FALSE),"") | M13: =IFERROR(VLOOKUP(Tabla10[[#This Row],[COD]],'Outros descontos'!B:P,15,FALSE),"") | N13: =(Tabla10[[#This Row],[HORAS TRABALHADAS]]*Tabla10[[#This Row],[TARIFA]]) - SUM(Tabla10[[#This Row],[ALOJAMENTO]], Tabla10[[#This Row],[IMPOSTO]], Tabla10[[#This Row],[CARRO]]) -> 1483.2582
B14: WS | C14: =IF(D14="", "", INDEX(Colaboradores!A:A, MATCH(D14,Colaboradores!C:C, 0))) -> E0617 | D14: ANDRES FELIPE MARULANDA ARAQUE | E14: 45945 | G14: =IFERROR(VLOOKUP(Tabla10[[#This Row],[COD]],'TotalHorasAjustadas (2)'!D:L,8,FALSE),"") -> 268 | H14: =IFERROR(VLOOKUP(Tabla10[[#This Row],[COD]],Tabla15[],4,FALSE),"") -> 15 | I14: =IFERROR(VLOOKUP(Tabla10[[#This Row],[COD]],Alojamentos!B:P,11,FALSE),"") | J14: =IF(ISBLANK(Tabla10[[#This Row],[INICIO VINCULO]]), 0, MAX(0, MIN(IF(ISBLANK(Tabla10[[#This Row],[FIM VINCULO]]), DATE(2026,1,31), Tabla10[[#This Row],[FIM VINCULO]]), DATE(2026,1,31)) - MAX(Tabla10[[#This Row],[INICIO VINCULO]], DATE(2026,1,1)) + 1)) -> 31 | K14: =7.05806*Tabla10[[#This Row],[DIAS DE ALTA]] -> 218.79986 | L14: =IFERROR(VLOOKUP(Tabla10[[#This Row],[COD]],Carro!B:D,3,FALSE),"") -> 66.666667 | M14: =IFERROR(VLOOKUP(Tabla10[[#This Row],[COD]],'Outros descontos'!B:P,15,FALSE),"") -> 148.97 | N14: =(Tabla10[[#This Row],[HORAS TRABALHADAS]]*Tabla10[[#This Row],[TARIFA]]) - SUM(Tabla10[[#This Row],[ALOJAMENTO]], Tabla10[[#This Row],[IMPOSTO]], Tabla10[[#This Row],[CARRO]],Tabla10[[#This Row],[OUTROS DEScontos]]) -> 3585.5635
B15: KR | C15: =IF(D15="", "", INDEX(Colaboradores!A:A, MATCH(D15,Colaboradores!C:C, 0))) -> E0195 | D15: BLADIMIRO DIAZ MARTINEZ | E15: 45761 | F15: 46053 | G15: =IFERROR(VLOOKUP(Tabla10[[#This Row],[COD]],'TotalHorasAjustadas (2)'!D:L,8,FALSE),"") -> 144 | H15: =IFERROR(VLOOKUP(Tabla10[[#This Row],[COD]],Tabla15[],4,FALSE),"") -> 13 | I15: =IFERROR(VLOOKUP(Tabla10[[#This Row],[COD]],Alojamentos!B:P,11,FALSE),"") -> 300 | J15: =IF(ISBLANK(Tabla10[[#This Row],[INICIO VINCULO]]), 0, MAX(0, MIN(IF(ISBLANK(Tabla10[[#This Row],[FIM VINCULO]]), DATE(2026,1,31), Tabla10[[#This Row],[FIM VINCULO]]), DATE(2026,1,31)) - MAX(Tabla10[[#This Row],[INICIO VINCULO]], DATE(2026,1,1)) + 1)) -> 31 | K15: =7.05806*Tabla10[[#This Row],[DIAS DE ALTA]] -> 218.79986 | L15: =IFERROR(VLOOKUP(Tabla10[[#This Row],[COD]],Carro!B:D,3,FALSE),"") | M15: =IFERROR(VLOOKUP(Tabla10[[#This Row],[COD]],'Outros descontos'!B:P,15,FALSE),"") | N15: =(Tabla10[[#This Row],[HORAS TRABALHADAS]]*Tabla10[[#This Row],[TARIFA]]) - SUM(Tabla10[[#This Row],[ALOJAMENTO]], Tabla10[[#This Row],[IMPOSTO]], Tabla10[[#This Row],[CARRO]]) -> 1353.2001
B16: WS | C16: =IF(D16="", "", INDEX(Colaboradores!A:A, MATCH(D16,Colaboradores!C:C, 0))) -> E1668 | D16: BRAYAN JOSE SALINAS MARTINEZ | E16: 45945 | G16: 165 | H16: =IFERROR(VLOOKUP(Tabla10[[#This Row],[COD]],Tabla15[],4,FALSE),"") -> 15 | I16: =IFERROR(VLOOKUP(Tabla10[[#This Row],[COD]],Alojamentos!B:P,11,FALSE),"") | J16: =IF(ISBLANK(Tabla10[[#This Row],[INICIO VINCULO]]), 0, MAX(0, MIN(IF(ISBLANK(Tabla10[[#This Row],[FIM VINCULO]]), DATE(2026,1,31), Tabla10[[#This Row],[FIM VINCULO]]), DATE(2026,1,31)) - MAX(Tabla10[[#This Row],[INICIO VINCULO]], DATE(2026,1,1)) + 1)) -> 31 | K16: =7.05806*Tabla10[[#This Row],[DIAS DE ALTA]] -> 218.79986 | L16: =IFERROR(VLOOKUP(Tabla10[[#This Row],[COD]],Carro!B:D,3,FALSE),"") | M16: =IFERROR(VLOOKUP(Tabla10[[#This Row],[COD]],'Outros descontos'!B:P,15,FALSE),"") | N16: =(Tabla10[[#This Row],[HORAS TRABALHADAS]]*Tabla10[[#This Row],[TARIFA]]) - SUM(Tabla10[[#This Row],[ALOJAMENTO]], Tabla10[[#This Row],[IMPOSTO]], Tabla10[[#This Row],[CARRO]]) -> 2256.2001
B17: KR | C17: =IF(D17="", "", INDEX(Colaboradores!A:A, MATCH(D17,Colaboradores!C:C, 0))) -> E0558 | D17: BREIDIS JOSE CARDOZO GALUE | E17: 45761 | G17: =IFERROR(VLOOKUP(Tabla10[[#This Row],[COD]],'TotalHorasAjustadas (2)'!D:L,8,FALSE),"") -> 194 | H17: =IFERROR(VLOOKUP(Tabla10[[#This Row],[COD]],Tabla15[],4,FALSE),"") -> 15 | I17: =IFERROR(VLOOKUP(Tabla10[[#This Row],[COD]],Alojamentos!B:P,11,FALSE),"") | J17: =IF(ISBLANK(Tabla10[[#This Row],[INICIO VINCULO]]), 0, MAX(0, MIN(IF(ISBLANK(Tabla10[[#This Row],[FIM VINCULO]]), DATE(2026,1,31), Tabla10[[#This Row],[FIM VINCULO]]), DATE(2026,1,31)) - MAX(Tabla10[[#This Row],[INICIO VINCULO]], DATE(2026,1,1)) + 1)) -> 31 | K17: =7.05806*Tabla10[[#This Row],[DIAS DE ALTA]] -> 218.79986 | L17: =IFERROR(VLOOKUP(Tabla10[[#This Row],[COD]],Carro!B:D,3,FALSE),"") | M17: =IFERROR(VLOOKUP(Tabla10[[#This Row],[COD]],'Outros descontos'!B:P,15,FALSE),"") | N17: =(Tabla10[[#This Row],[HORAS TRABALHADAS]]*Tabla10[[#This Row],[TARIFA]]) - SUM(Tabla10[[#This Row],[ALOJAMENTO]], Tabla10[[#This Row],[IMPOSTO]], Tabla10[[#This Row],[CARRO]]) -> 2691.2001
B18: LM | C18: =IF(D18="", "", INDEX(Colaboradores!A:A, MATCH(D18,Colaboradores!C:C, 0))) -> E0622 | D18: BREINER MOLINA PELAEZ | E18: 45942 | G18: =IFERROR(VLOOKUP(Tabla10[[#This Row],[COD]],'TotalHorasAjustadas (2)'!D:L,8,FALSE),"") -> 210 | H18: =IFERROR(VLOOKUP(Tabla10[[#This Row],[COD]],Tabla15[],4,FALSE),"") -> 15 | I18: =IFERROR(VLOOKUP(Tabla10[[#This Row],[COD]],Alojamentos!B:P,11,FALSE),"") | J18: =IF(ISBLANK(Tabla10[[#This Row],[INICIO VINCULO]]), 0, MAX(0, MIN(IF(ISBLANK(Tabla10[[#This Row],[FIM VINCULO]]), DATE(2026,1,31), Tabla10[[#This Row],[FIM VINCULO]]), DATE(2026,1,31)) - MAX(Tabla10[[#This Row],[INICIO VINCULO]], DATE(2026,1,1)) + 1)) -> 31 | K18: =7.05806*Tabla10[[#This Row],[DIAS DE ALTA]] -> 218.79986 | L18: =IFERROR(VLOOKUP(Tabla10[[#This Row],[COD]],Carro!B:D,3,FALSE),"") -> 102.66 | M18: =IFERROR(VLOOKUP(Tabla10[[#This Row],[COD]],'Outros descontos'!B:P,15,FALSE),"") -> 53.16 | N18: =(Tabla10[[#This Row],[HORAS TRABALHADAS]]*Tabla10[[#This Row],[TARIFA]]) - SUM(Tabla10[[#This Row],[ALOJAMENTO]], Tabla10[[#This Row],[IMPOSTO]], Tabla10[[#This Row],[CARRO]],Tabla10[[#This Row],[OUTROS DEScontos]]) -> 2775.3801
B19: WS | D19: BRENDA JAVORSKI NECKEL | E19: 45819 | G19: 160 | H19: 0 | I19: =IFERROR(VLOOKUP(Tabla10[[#This Row],[COD]],Alojamentos!B:P,11,FALSE),"") | J19: =IF(ISBLANK(Tabla10[[#This Row],[INICIO VINCULO]]), 0, MAX(0, MIN(IF(ISBLANK(Tabla10[[#This Row],[FIM VINCULO]]), DATE(2026,1,31), Tabla10[[#This Row],[FIM VINCULO]]), DATE(2026,1,31)) - MAX(Tabla10[[#This Row],[INICIO VINCULO]], DATE(2026,1,1)) + 1)) -> 31 | K19: 0 | L19: =IFERROR(VLOOKUP(Tabla10[[#This Row],[COD]],Carro!B:D,3,FALSE),"") | M19: =IFERROR(VLOOKUP(Tabla10[[#This Row],[COD]],'Outros descontos'!B:P,15,FALSE),"") | N19: 2337.5
B20: KI | C20: =IF(D20="", "", INDEX(Colaboradores!A:A, MATCH(D20,Colaboradores!C:C, 0))) -> E0277 | D20: CAMILO ANDRES VALERO PEREZ | E20: 45762 | F20: 46053 | G20: =IFERROR(VLOOKUP(Tabla10[[#This Row],[COD]],'TotalHorasAjustadas (2)'!D:L,8,FALSE),"") -> 201 | H20: =IFERROR(VLOOKUP(Tabla10[[#This Row],[COD]],Tabla15[],4,FALSE),"") -> 15 | I20: =IFERROR(VLOOKUP(Tabla10[[#This Row],[COD]],Alojamentos!B:P,11,FALSE),"") | J20: =IF(ISBLANK(Tabla10[[#This Row],[INICIO VINCULO]]), 0, MAX(0, MIN(IF(ISBLANK(Tabla10[[#This Row],[FIM VINCULO]]), DATE(2026,1,31), Tabla10[[#This Row],[FIM VINCULO]]), DATE(2026,1,31)) - MAX(Tabla10[[#This Row],[INICIO VINCULO]], DATE(2026,1,1)) + 1)) -> 31 | K20: =7.05806*Tabla10[[#This Row],[DIAS DE ALTA]] -> 218.79986 | L20: =IFERROR(VLOOKUP(Tabla10[[#This Row],[COD]],Carro!B:D,3,FALSE),"") -> 145 | M20: =IFERROR(VLOOKUP(Tabla10[[#This Row],[COD]],'Outros descontos'!B:P,15,FALSE),"") | N20: =(Tabla10[[#This Row],[HORAS TRABALHADAS]]*Tabla10[[#This Row],[TARIFA]]) - SUM(Tabla10[[#This Row],[ALOJAMENTO]], Tabla10[[#This Row],[IMPOSTO]], Tabla10[[#This Row],[CARRO]]) -> 2651.2001
B21: KR | C21: =IF(D21="", "", INDEX(Colaboradores!A:A, MATCH(D21,Colaboradores!C:C, 0))) -> E0396 | D21: CARLOS ANDRES JIMENEZ RAMIREZ | E21: 45880 | F21: 46052 | G21: =IFERROR(VLOOKUP(Tabla10[[#This Row],[COD]],'TotalHorasAjustadas (2)'!D:L,8,FALSE),"") -> 143 | H21: =IFERROR(VLOOKUP(Tabla10[[#This Row],[COD]],Tabla15[],4,FALSE),"") -> 15 | I21: =IFERROR(VLOOKUP(Tabla10[[#This Row],[COD]],Alojamentos!B:P,11,FALSE),"") -> 300 | J21: =IF(ISBLANK(Tabla10[[#This Row],[INICIO VINCULO]]), 0, MAX(0, MIN(IF(ISBLANK(Tabla10[[#This Row],[FIM VINCULO]]), DATE(2026,1,31), Tabla10[[#This Row],[FIM VINCULO]]), DATE(2026,1,31)) - MAX(Tabla10[[#This Row],[INICIO VINCULO]], DATE(2026,1,1)) + 1)) -> 30 | K21: =7.05806*Tabla10[[#This Row],[DIAS DE ALTA]] -> 211.7418 | L21: =IFERROR(VLOOKUP(Tabla10[[#This Row],[COD]],Carro!B:D,3,FALSE),"") | M21: =IFERROR(VLOOKUP(Tabla10[[#This Row],[COD]],'Outros descontos'!B:P,15,FALSE),"") | N21: =(Tabla10[[#This Row],[HORAS TRABALHADAS]]*Tabla10[[#This Row],[TARIFA]]) - SUM(Tabla10[[#This Row],[ALOJAMENTO]], Tabla10[[#This Row],[IMPOSTO]], Tabla10[[#This Row],[CARRO]]) -> 1633.2582
B22: LM | C22: =IF(D22="", "", INDEX(Colaboradores!A:A, MATCH(D22,Colaboradores!C:C, 0))) -> E1976 | D22: CARLOS DANIEL RODRIGUEZ PENA | E22: 46048 | G22: =IFERROR(VLOOKUP(Tabla10[[#This Row],[COD]],'TotalHorasAjustadas (2)'!D:L,8,FALSE),"") -> 62 | H22: 15 | I22: =IFERROR(VLOOKUP(Tabla10[[#This Row],[COD]],Alojamentos!B:P,11,FALSE),"") | J22: =IF(ISBLANK(Tabla10[[#This Row],[INICIO VINCULO]]), 0, MAX(0, MIN(IF(ISBLANK(Tabla10[[#This Row],[FIM VINCULO]]), DATE(2026,1,31), Tabla10[[#This Row],[FIM VINCULO]]), DATE(2026,1,31)) - MAX(Tabla10[[#This Row],[INICIO VINCULO]], DATE(2026,1,1)) + 1)) -> 6 | K22: =7.05806*Tabla10[[#This Row],[DIAS DE ALTA]] -> 42.34836 | L22: =IFERROR(VLOOKUP(Tabla10[[#This Row],[COD]],Carro!B:D,3,FALSE),"") -> 45 | M22: =IFERROR(VLOOKUP(Tabla10[[#This Row],[COD]],'Outros descontos'!B:P,15,FALSE),"") | N22: =(Tabla10[[#This Row],[HORAS TRABALHADAS]]*Tabla10[[#This Row],[TARIFA]]) - SUM(Tabla10[[#This Row],[ALOJAMENTO]], Tabla10[[#This Row],[IMPOSTO]], Tabla10[[#This Row],[CARRO]]) -> 842.65164
B23: LM | D23: CARLOS DE MARINS MENINO JUNIOR | E23: 45895 | G23: 160 | H23: 0 | I23: =IFERROR(VLOOKUP(Tabla10[[#This Row],[COD]],Alojamentos!B:P,11,FALSE),"") | J23: =IF(ISBLANK(Tabla10[[#This Row],[INICIO VINCULO]]), 0, MAX(0, MIN(IF(ISBLANK(Tabla10[[#This Row],[FIM VINCULO]]), DATE(2026,1,31), Tabla10[[#This Row],[FIM VINCULO]]), DATE(2026,1,31)) - MAX(Tabla10[[#This Row],[INICIO VINCULO]], DATE(2026,1,1)) + 1)) -> 31 | K23: 0 | L23: =IFERROR(VLOOKUP(Tabla10[[#This Row],[COD]],Carro!B:D,3,FALSE),"") | M23: =IFERROR(VLOOKUP(Tabla10[[#This Row],[COD]],'Outros descontos'!B:P,15,FALSE),"") | N23: 1420
B24: LM | C24: =IF(D24="", "", INDEX(Colaboradores!A:A, MATCH(D24,Colaboradores!C:C, 0))) -> E0144 | D24: CARLOS EDUARDO CARDENAS ESPINOSA | E24: 45943 | G24: =IFERROR(VLOOKUP(Tabla10[[#This Row],[COD]],'TotalHorasAjustadas (2)'!D:L,8,FALSE),"") -> 204.5 | H24: =IFERROR(VLOOKUP(Tabla10[[#This Row],[COD]],Tabla15[],4,FALSE),"") -> 15 | I24: =IFERROR(VLOOKUP(Tabla10[[#This Row],[COD]],Alojamentos!B:P,11,FALSE),"") -> 300 | J24: =IF(ISBLANK(Tabla10[[#This Row],[INICIO VINCULO]]), 0, MAX(0, MIN(IF(ISBLANK(Tabla10[[#This Row],[FIM VINCULO]]), DATE(2026,1,31), Tabla10[[#This Row],[FIM VINCULO]]), DATE(2026,1,31)) - MAX(Tabla10[[#This Row],[INICIO VINCULO]], DATE(2026,1,1)) + 1)) -> 31 | K24: =7.05806*Tabla10[[#This Row],[DIAS DE ALTA]] -> 218.79986 | L24: =IFERROR(VLOOKUP(Tabla10[[#This Row],[COD]],Carro!B:D,3,FALSE),"") | M24: =IFERROR(VLOOKUP(Tabla10[[#This Row],[COD]],'Outros descontos'!B:P,15,FALSE),"") | N24: =(Tabla10[[#This Row],[HORAS TRABALHADAS]]*Tabla10[[#This Row],[TARIFA]]) - SUM(Tabla10[[#This Row],[ALOJAMENTO]], Tabla10[[#This Row],[IMPOSTO]], Tabla10[[#This Row],[CARRO]]) -> 2548.7001
B25: KR | C25: =IF(D25="", "", INDEX(Colaboradores!A:A, MATCH(D25,Colaboradores!C:C, 0))) -> E0553 | D25: CARLOS JULIO ACOSTA CAMACHO | E25: 45779 | F25: 46052 | G25: =IFERROR(VLOOKUP(Tabla10[[#This Row],[COD]],'TotalHorasAjustadas (2)'!D:L,8,FALSE),"") -> 170 | H25: =IFERROR(VLOOKUP(Tabla10[[#This Row],[COD]],Tabla15[],4,FALSE),"") -> 15 | I25: =IFERROR(VLOOKUP(Tabla10[[#This Row],[COD]],Alojamentos!B:P,11,FALSE),"") | J25: =IF(ISBLANK(Tabla10[[#This Row],[INICIO VINCULO]]), 0, MAX(0, MIN(IF(ISBLANK(Tabla10[[#This Row],[FIM VINCULO]]), DATE(2026,1,31), Tabla10[[#This Row],[FIM VINCULO]]), DATE(2026,1,31)) - MAX(Tabla10[[#This Row],[INICIO VINCULO]], DATE(2026,1,1)) + 1)) -> 30 | K25: =7.05806*Tabla10[[#This Row],[DIAS DE ALTA]] -> 211.7418 | L25: =IFERROR(VLOOKUP(Tabla10[[#This Row],[COD]],Carro!B:D,3,FALSE),"") -> 120 | M25: =IFERROR(VLOOKUP(Tabla10[[#This Row],[COD]],'Outros descontos'!B:P,15,FALSE),"") | N25: =(Tabla10[[#This Row],[HORAS TRABALHADAS]]*Tabla10[[#This Row],[TARIFA]]) - SUM(Tabla10[[#This Row],[ALOJAMENTO]], Tabla10[[#This Row],[IMPOSTO]], Tabla10[[#This Row],[CARRO]]) -> 2218.2582
B26: WS | C26: =IF(D26="", "", INDEX(Colaboradores!A:A, MATCH(D26,Colaboradores!C:C, 0))) -> E0801 | D26: CARLOS MITCHELL SANTOS RODRIGUEZ | E26: 45945 | G26: =IFERROR(VLOOKUP(Tabla10[[#This Row],[COD]],'TotalHorasAjustadas (2)'!D:L,8,FALSE),"") -> 268 | H26: =IFERROR(VLOOKUP(Tabla10[[#This Row],[COD]],Tabla15[],4,FALSE),"") -> 15 | I26: =IFERROR(VLOOKUP(Tabla10[[#This Row],[COD]],Alojamentos!B:P,11,FALSE),"") | J26: =IF(ISBLANK(Tabla10[[#This Row],[INICIO VINCULO]]), 0, MAX(0, MIN(IF(ISBLANK(Tabla10[[#This Row],[FIM VINCULO]]), DATE(2026,1,31), Tabla10[[#This Row],[FIM VINCULO]]), DATE(2026,1,31)) - MAX(Tabla10[[#This Row],[INICIO VINCULO]], DATE(2026,1,1)) + 1)) -> 31 | K26: =7.05806*Tabla10[[#This Row],[DIAS DE ALTA]] -> 218.79986 | L26: =IFERROR(VLOOKUP(Tabla10[[#This Row],[COD]],Carro!B:D,3,FALSE),"") -> 66.666667 | M26: =IFERROR(VLOOKUP(Tabla10[[#This Row],[COD]],'Outros descontos'!B:P,15,FALSE),"") -> 148.97 | N26: =(Tabla10[[#This Row],[HORAS TRABALHADAS]]*Tabla10[[#This Row],[TARIFA]]) - SUM(Tabla10[[#This Row],[ALOJAMENTO]], Tabla10[[#This Row],[IMPOSTO]], Tabla10[[#This Row],[CARRO]],Tabla10[[#This Row],[OUTROS DEScontos]]) -> 3585.5635
B27: WS | C27: =IF(D27="", "", INDEX(Colaboradores!A:A, MATCH(D27,Colaboradores!C:C, 0))) -> E1129 | D27: CICERO LIMA BATISTA | E27: 45931 | G27: =IFERROR(VLOOKUP(Tabla10[[#This Row],[COD]],'TotalHorasAjustadas (2)'!D:L,8,FALSE),"") -> 160 | H27: =IFERROR(VLOOKUP(Tabla10[[#This Row],[COD]],Tabla15[],4,FALSE),"") -> 16 | I27: =IFERROR(VLOOKUP(Tabla10[[#This Row],[COD]],Alojamentos!B:P,11,FALSE),"") | J27: =IF(ISBLANK(Tabla10[[#This Row],[INICIO VINCULO]]), 0, MAX(0, MIN(IF(ISBLANK(Tabla10[[#This Row],[FIM VINCULO]]), DATE(2026,1,31), Tabla10[[#This Row],[FIM VINCULO]]), DATE(2026,1,31)) - MAX(Tabla10[[#This Row],[INICIO VINCULO]], DATE(2026,1,1)) + 1)) -> 31 | K27: =7.05806*Tabla10[[#This Row],[DIAS DE ALTA]] -> 218.79986 | L27: =IFERROR(VLOOKUP(Tabla10[[#This Row],[COD]],Carro!B:D,3,FALSE),"") | M27: =IFERROR(VLOOKUP(Tabla10[[#This Row],[COD]],'Outros descontos'!B:P,15,FALSE),"") | N27: =(Tabla10[[#This Row],[HORAS TRABALHADAS]]*Tabla10[[#This Row],[TARIFA]]) - SUM(Tabla10[[#This Row],[ALOJAMENTO]], Tabla10[[#This Row],[IMPOSTO]], Tabla10[[#This Row],[CARRO]]) -> 2341.2001
B28: LM | C28: =IF(D28="", "", INDEX(Colaboradores!A:A, MATCH(D28,Colaboradores!C:C, 0))) -> E1918 | D28: CRISTIAN CAMILO BORRE SILVA | E28: 46041 | G28: =IFERROR(VLOOKUP(Tabla10[[#This Row],[COD]],'TotalHorasAjustadas (2)'!D:L,8,FALSE),"") -> 103 | H28: 15 | I28: =IFERROR(VLOOKUP(Tabla10[[#This Row],[COD]],Alojamentos!B:P,11,FALSE),"") | J28: =IF(ISBLANK(Tabla10[[#This Row],[INICIO VINCULO]]), 0, MAX(0, MIN(IF(ISBLANK(Tabla10[[#This Row],[FIM VINCULO]]), DATE(2026,1,31), Tabla10[[#This Row],[FIM VINCULO]]), DATE(2026,1,31)) - MAX(Tabla10[[#This Row],[INICIO VINCULO]], DATE(2026,1,1)) + 1)) -> 13 | K28: =7.05806*Tabla10[[#This Row],[DIAS DE ALTA]] -> 91.75478 | L28: =IFERROR(VLOOKUP(Tabla10[[#This Row],[COD]],Carro!B:D,3,FALSE),"") | M28: =IFERROR(VLOOKUP(Tabla10[[#This Row],[COD]],'Outros descontos'!B:P,15,FALSE),"") | N28: =(Tabla10[[#This Row],[HORAS TRABALHADAS]]*Tabla10[[#This Row],[TARIFA]]) - SUM(Tabla10[[#This Row],[ALOJAMENTO]], Tabla10[[#This Row],[IMPOSTO]], Tabla10[[#This Row],[CARRO]]) -> 1453.2452
B29: KI | C29: =IF(D29="", "", INDEX(Colaboradores!A:A, MATCH(D29,Colaboradores!C:C, 0))) -> E1895 | D29: DAMIAN ZAMBRANO TULANDE | E29: 45762 | F29: 46052 | G29: =IFERROR(VLOOKUP(Tabla10[[#This Row],[COD]],'TotalHorasAjustadas (2)'!D:L,8,FALSE),"") -> 142 | H29: =IFERROR(VLOOKUP(Tabla10[[#This Row],[COD]],Tabla15[],4,FALSE),"") -> 15 | I29: =IFERROR(VLOOKUP(Tabla10[[#This Row],[COD]],Alojamentos!B:P,11,FALSE),"") | J29: =IF(ISBLANK(Tabla10[[#This Row],[INICIO VINCULO]]), 0, MAX(0, MIN(IF(ISBLANK(Tabla10[[#This Row],[FIM VINCULO]]), DATE(2026,1,31), Tabla10[[#This Row],[FIM VINCULO]]), DATE(2026,1,31)) - MAX(Tabla10[[#This Row],[INICIO VINCULO]], DATE(2026,1,1)) + 1)) -> 30 | K29: =7.05806*Tabla10[[#This Row],[DIAS DE ALTA]] -> 211.7418 | L29: =IFERROR(VLOOKUP(Tabla10[[#This Row],[COD]],Carro!B:D,3,FALSE),"") -> 66.666667 | M29: =IFERROR(VLOOKUP(Tabla10[[#This Row],[COD]],'Outros descontos'!B:P,15,FALSE),"") | N29: =(Tabla10[[#This Row],[HORAS TRABALHADAS]]*Tabla10[[#This Row],[TARIFA]]) - SUM(Tabla10[[#This Row],[ALOJAMENTO]], Tabla10[[#This Row],[IMPOSTO]], Tabla10[[#This Row],[CARRO]]) -> 1851.5915
B30: KI | C30: =IF(D30="", "", INDEX(Colaboradores!A:A, MATCH(D30,Colaboradores!C:C, 0))) -> E0534 | D30: DANILO RAMIREZ SARATE | E30: 45762 | F30: 46027 | G30: 0 | H30: =IFERROR(VLOOKUP(Tabla10[[#This Row],[COD]],Tabla15[],4,FALSE),"") -> 15 | I30: =IFERROR(VLOOKUP(Tabla10[[#This Row],[COD]],Alojamentos!B:P,11,FALSE),"") | J30: =IF(ISBLANK(Tabla10[[#This Row],[INICIO VINCULO]]), 0, MAX(0, MIN(IF(ISBLANK(Tabla10[[#This Row],[FIM VINCULO]]), DATE(2026,1,31), Tabla10[[#This Row],[FIM VINCULO]]), DATE(2026,1,31)) - MAX(Tabla10[[#This Row],[INICIO VINCULO]], DATE(2026,1,1)) + 1)) -> 5 | K30: =7.05806*Tabla10[[#This Row],[DIAS DE ALTA]] -> 35.2903 | L30: =IFERROR(VLOOKUP(Tabla10[[#This Row],[COD]],Carro!B:D,3,FALSE),"") | M30: =IFERROR(VLOOKUP(Tabla10[[#This Row],[COD]],'Outros descontos'!B:P,15,FALSE),"") | N30: 0
B31: WS | C31: =IF(D31="", "", INDEX(Colaboradores!A:A, MATCH(D31,Colaboradores!C:C, 0))) -> E1663 | D31: DARIO CARLOS MANUEL PEREIRA | E31: 45945 | G31: =IFERROR(VLOOKUP(Tabla10[[#This Row],[COD]],'TotalHorasAjustadas (2)'!D:L,8,FALSE),"") -> 102 | H31: =IFERROR(VLOOKUP(Tabla10[[#This Row],[COD]],Tabla15[],4,FALSE),"") -> 15 | I31: =IFERROR(VLOOKUP(Tabla10[[#This Row],[COD]],Alojamentos!B:P,11,FALSE),"") | J31: =IF(ISBLANK(Tabla10[[#This Row],[INICIO VINCULO]]), 0, MAX(0, MIN(IF(ISBLANK(Tabla10[[#This Row],[FIM VINCULO]]), DATE(2026,1,31), Tabla10[[#This Row],[FIM VINCULO]]), DATE(2026,1,31)) - MAX(Tabla10[[#This Row],[INICIO VINCULO]], DATE(2026,1,1)) + 1)) -> 31 | K31: =7.05806*Tabla10[[#This Row],[DIAS DE ALTA]] -> 218.79986 | L31: =IFERROR(VLOOKUP(Tabla10[[#This Row],[COD]],Carro!B:D,3,FALSE),"") | M31: =IFERROR(VLOOKUP(Tabla10[[#This Row],[COD]],'Outros descontos'!B:P,15,FALSE),"") | N31: =(Tabla10[[#This Row],[HORAS TRABALHADAS]]*Tabla10[[#This Row],[TARIFA]]) - SUM(Tabla10[[#This Row],[ALOJAMENTO]], Tabla10[[#This Row],[IMPOSTO]], Tabla10[[#This Row],[CARRO]]) -> 1311.2001
B32: WS | C32: =IF(D32="", "", INDEX(Colaboradores!A:A, MATCH(D32,Colaboradores!C:C, 0))) -> E0578 | D32: DIEGO ROBERTO SOUZA SCAVACINI | E32: 45873 | G32: =IFERROR(VLOOKUP(Tabla10[[#This Row],[COD]],'TotalHorasAjustadas (2)'!D:L,8,FALSE),"") -> 76 | H32: =IFERROR(VLOOKUP(Tabla10[[#This Row],[COD]],Tabla15[],4,FALSE),"") -> 17 | I32: =IFERROR(VLOOKUP(Tabla10[[#This Row],[COD]],Alojamentos!B:P,11,FALSE),"") | J32: =IF(ISBLANK(Tabla10[[#This Row],[INICIO VINCULO]]), 0, MAX(0, MIN(IF(ISBLANK(Tabla10[[#This Row],[FIM VINCULO]]), DATE(2026,1,31), Tabla10[[#This Row],[FIM VINCULO]]), DATE(2026,1,31)) - MAX(Tabla10[[#This Row],[INICIO VINCULO]], DATE(2026,1,1)) + 1)) -> 31 | K32: =7.05806*Tabla10[[#This Row],[DIAS DE ALTA]] -> 218.79986 | L32: =IFERROR(VLOOKUP(Tabla10[[#This Row],[COD]],Carro!B:D,3,FALSE),"") | M32: =IFERROR(VLOOKUP(Tabla10[[#This Row],[COD]],'Outros descontos'!B:P,15,FALSE),"") | N32: =(Tabla10[[#This Row],[HORAS TRABALHADAS]]*Tabla10[[#This Row],[TARIFA]]) - SUM(Tabla10[[#This Row],[ALOJAMENTO]], Tabla10[[#This Row],[IMPOSTO]], Tabla10[[#This Row],[CARRO]]) -> 1073.2001
B33: WS | C33: =IF(D33="", "", INDEX(Colaboradores!A:A, MATCH(D33,Colaboradores!C:C, 0))) -> E1826 | D33: DOMINGO RAMON VEGA HUMANEZ | E33: 46052 | G33: =IFERROR(VLOOKUP(Tabla10[[#This Row],[COD]],'TotalHorasAjustadas (2)'!D:L,8,FALSE),"") -> 172.5 | H33: =IFERROR(VLOOKUP(Tabla10[[#This Row],[COD]],Tabla15[],4,FALSE),"") -> 15 | I33: =IFERROR(VLOOKUP(Tabla10[[#This Row],[COD]],Alojamentos!B:P,11,FALSE),"") | J33: =IF(ISBLANK(Tabla10[[#This Row],[INICIO VINCULO]]), 0, MAX(0, MIN(IF(ISBLANK(Tabla10[[#This Row],[FIM VINCULO]]), DATE(2026,1,31), Tabla10[[#This Row],[FIM VINCULO]]), DATE(2026,1,31)) - MAX(Tabla10[[#This Row],[INICIO VINCULO]], DATE(2026,1,1)) + 1)) -> 2 | K33: =7.05806*Tabla10[[#This Row],[DIAS DE ALTA]] -> 14.11612 | L33: =IFERROR(VLOOKUP(Tabla10[[#This Row],[COD]],Carro!B:D,3,FALSE),"") | M33: =IFERROR(VLOOKUP(Tabla10[[#This Row],[COD]],'Outros descontos'!B:P,15,FALSE),"") | N33: 580.88 | O33: 2000
B34: WS | C34: =IF(D34="", "", INDEX(Colaboradores!A:A, MATCH(D34,Colaboradores!C:C, 0))) -> E1970 | D34: EDDIE DE JESUS ZARATE IGUARAN | E34: 46041 | G34: 48 | H34: =IFERROR(VLOOKUP(Tabla10[[#This Row],[COD]],Tabla15[],4,FALSE),"") -> 15 | I34: =IFERROR(VLOOKUP(Tabla10[[#This Row],[COD]],Alojamentos!B:P,11,FALSE),"") | J34: =IF(ISBLANK(Tabla10[[#This Row],[INICIO VINCULO]]), 0, MAX(0, MIN(IF(ISBLANK(Tabla10[[#This Row],[FIM VINCULO]]), DATE(2026,1,31), Tabla10[[#This Row],[FIM VINCULO]]), DATE(2026,1,31)) - MAX(Tabla10[[#This Row],[INICIO VINCULO]], DATE(2026,1,1)) + 1)) -> 13 | K34: =7.05806*Tabla10[[#This Row],[DIAS DE ALTA]] -> 91.75478 | L34: =IFERROR(VLOOKUP(Tabla10[[#This Row],[COD]],Carro!B:D,3,FALSE),"") -> 40 | M34: =IFERROR(VLOOKUP(Tabla10[[#This Row],[COD]],'Outros descontos'!B:P,15,FALSE),"") -> 112.93 | N34: =(Tabla10[[#This Row],[HORAS TRABALHADAS]]*Tabla10[[#This Row],[TARIFA]]) - SUM(Tabla10[[#This Row],[ALOJAMENTO]], Tabla10[[#This Row],[IMPOSTO]], Tabla10[[#This Row],[CARRO]]) -> 588.24522
B35: LM | C35: =IF(D35="", "", INDEX(Colaboradores!A:A, MATCH(D35,Colaboradores!C:C, 0))) -> E1970 | D35: EDDIE DE JESUS ZARATE IGUARAN | E35: 45951 | F35: 46034 | G35: 48 | H35: =IFERROR(VLOOKUP(Tabla10[[#This Row],[COD]],Tabla15[],4,FALSE),"") -> 15 | I35: =IFERROR(VLOOKUP(Tabla10[[#This Row],[COD]],Alojamentos!B:P,11,FALSE),"") | J35: =IF(ISBLANK(Tabla10[[#This Row],[INICIO VINCULO]]), 0, MAX(0, MIN(IF(ISBLANK(Tabla10[[#This Row],[FIM VINCULO]]), DATE(2026,1,31), Tabla10[[#This Row],[FIM VINCULO]]), DATE(2026,1,31)) - MAX(Tabla10[[#This Row],[INICIO VINCULO]], DATE(2026,1,1)) + 1)) -> 12 | K35: =7.05806*Tabla10[[#This Row],[DIAS DE ALTA]] -> 84.69672 | M35: =IFERROR(VLOOKUP(Tabla10[[#This Row],[COD]],'Outros descontos'!B:P,15,FALSE),"") -> 112.93 | N35: =(Tabla10[[#This Row],[HORAS TRABALHADAS]]*Tabla10[[#This Row],[TARIFA]]) - SUM(Tabla10[[#This Row],[ALOJAMENTO]], Tabla10[[#This Row],[IMPOSTO]], Tabla10[[#This Row],[CARRO]]) -> 635.30328
B36: LM | C36: =IF(D36="", "", INDEX(Colaboradores!A:A, MATCH(D36,Colaboradores!C:C, 0))) -> E2090 | D36: EDGAR CORRALES HOYOS | E36: 46041 | G36: =IFERROR(VLOOKUP(Tabla10[[#This Row],[COD]],'TotalHorasAjustadas (2)'!D:L,8,FALSE),"") -> 74 | H36: 15 | I36: =IFERROR(VLOOKUP(Tabla10[[#This Row],[COD]],Alojamentos!B:P,11,FALSE),"") | J36: =IF(ISBLANK(Tabla10[[#This Row],[INICIO VINCULO]]), 0, MAX(0, MIN(IF(ISBLANK(Tabla10[[#This Row],[FIM VINCULO]]), DATE(2026,1,31), Tabla10[[#This Row],[FIM VINCULO]]), DATE(2026,1,31)) - MAX(Tabla10[[#This Row],[INICIO VINCULO]], DATE(2026,1,1)) + 1)) -> 13 | K36: =7.05806*Tabla10[[#This Row],[DIAS DE ALTA]] -> 91.75478 | L36: =IFERROR(VLOOKUP(Tabla10[[#This Row],[COD]],Carro!B:D,3,FALSE),"") | M36: =IFERROR(VLOOKUP(Tabla10[[#This Row],[COD]],'Outros descontos'!B:P,15,FALSE),"") | N36: =(Tabla10[[#This Row],[HORAS TRABALHADAS]]*Tabla10[[#This Row],[TARIFA]]) - SUM(Tabla10[[#This Row],[ALOJAMENTO]], Tabla10[[#This Row],[IMPOSTO]], Tabla10[[#This Row],[CARRO]]) -> 1018.2452
B37: KI | C37: =IF(D37="", "", INDEX(Colaboradores!A:A, MATCH(D37,Colaboradores!C:C, 0))) -> E0600 | D37: EDGAR STEVEN PENAGOS CESPEDES | E37: 45364 | F37: 46052 | G37: =IFERROR(VLOOKUP(Tabla10[[#This Row],[COD]],'TotalHorasAjustadas (2)'!D:L,8,FALSE),"") -> 225 | H37: =IFERROR(VLOOKUP(Tabla10[[#This Row],[COD]],Tabla15[],4,FALSE),"") -> 16 | I37: =IFERROR(VLOOKUP(Tabla10[[#This Row],[COD]],Alojamentos!B:P,11,FALSE),"") | J37: =IF(ISBLANK(Tabla10[[#This Row],[INICIO VINCULO]]), 0, MAX(0, MIN(IF(ISBLANK(Tabla10[[#This Row],[FIM VINCULO]]), DATE(2026,1,31), Tabla10[[#This Row],[FIM VINCULO]]), DATE(2026,1,31)) - MAX(Tabla10[[#This Row],[INICIO VINCULO]], DATE(2026,1,1)) + 1)) -> 30 | K37: =7.05806*Tabla10[[#This Row],[DIAS DE ALTA]] -> 211.7418 | L37: =IFERROR(VLOOKUP(Tabla10[[#This Row],[COD]],Carro!B:D,3,FALSE),"") | M37: =IFERROR(VLOOKUP(Tabla10[[#This Row],[COD]],'Outros descontos'!B:P,15,FALSE),"") | N37: =(Tabla10[[#This Row],[HORAS TRABALHADAS]]*Tabla10[[#This Row],[TARIFA]]) - SUM(Tabla10[[#This Row],[ALOJAMENTO]], Tabla10[[#This Row],[IMPOSTO]], Tabla10[[#This Row],[CARRO]]) -> 3388.2582
B38: KI | C38: =IF(D38="", "", INDEX(Colaboradores!A:A, MATCH(D38,Colaboradores!C:C, 0))) -> E0161 | D38: EDILBERTO DOMINGUEZ PEREIRA | E38: 45762 | F38: 46053 | G38: =IFERROR(VLOOKUP(Tabla10[[#This Row],[COD]],'TotalHorasAjustadas (2)'!D:L,8,FALSE),"") -> 199 | H38: =IFERROR(VLOOKUP(Tabla10[[#This Row],[COD]],Tabla15[],4,FALSE),"") -> 18 | I38: =IFERROR(VLOOKUP(Tabla10[[#This Row],[COD]],Alojamentos!B:P,11,FALSE),"") | J38: =IF(ISBLANK(Tabla10[[#This Row],[INICIO VINCULO]]), 0, MAX(0, MIN(IF(ISBLANK(Tabla10[[#This Row],[FIM VINCULO]]), DATE(2026,1,31), Tabla10[[#This Row],[FIM VINCULO]]), DATE(2026,1,31)) - MAX(Tabla10[[#This Row],[INICIO VINCULO]], DATE(2026,1,1)) + 1)) -> 31 | K38: =7.05806*Tabla10[[#This Row],[DIAS DE ALTA]] -> 218.79986 | L38: =IFERROR(VLOOKUP(Tabla10[[#This Row],[COD]],Carro!B:D,3,FALSE),"") | M38: =IFERROR(VLOOKUP(Tabla10[[#This Row],[COD]],'Outros descontos'!B:P,15,FALSE),"") | N38: =(Tabla10[[#This Row],[HORAS TRABALHADAS]]*Tabla10[[#This Row],[TARIFA]]) - SUM(Tabla10[[#This Row],[ALOJAMENTO]], Tabla10[[#This Row],[IMPOSTO]], Tabla10[[#This Row],[CARRO]]) -> 3363.2001
B39: KR | C39: =IF(D39="", "", INDEX(Colaboradores!A:A, MATCH(D39,Colaboradores!C:C, 0))) -> E0615 | D39: EDILSON FIERRO DAGUA | E39: 45803 | F39: 46052 | G39: =IFERROR(VLOOKUP(Tabla10[[#This Row],[COD]],'TotalHorasAjustadas (2)'!D:L,8,FALSE),"") -> 227 | H39: =IFERROR(VLOOKUP(Tabla10[[#This Row],[COD]],Tabla15[],4,FALSE),"") -> 15 | I39: =IFERROR(VLOOKUP(Tabla10[[#This Row],[COD]],Alojamentos!B:P,11,FALSE),"") | J39: =IF(ISBLANK(Tabla10[[#This Row],[INICIO VINCULO]]), 0, MAX(0, MIN(IF(ISBLANK(Tabla10[[#This Row],[FIM VINCULO]]), DATE(2026,1,31), Tabla10[[#This Row],[FIM VINCULO]]), DATE(2026,1,31)) - MAX(Tabla10[[#This Row],[INICIO VINCULO]], DATE(2026,1,1)) + 1)) -> 30 | K39: =7.05806*Tabla10[[#This Row],[DIAS DE ALTA]] -> 211.7418 | L39: =IFERROR(VLOOKUP(Tabla10[[#This Row],[COD]],Carro!B:D,3,FALSE),"") -> 74.666667 | M39: =IFERROR(VLOOKUP(Tabla10[[#This Row],[COD]],'Outros descontos'!B:P,15,FALSE),"") | N39: =(Tabla10[[#This Row],[HORAS TRABALHADAS]]*Tabla10[[#This Row],[TARIFA]]) - SUM(Tabla10[[#This Row],[ALOJAMENTO]], Tabla10[[#This Row],[IMPOSTO]], Tabla10[[#This Row],[CARRO]]) -> 3118.5915
B40: LM | C40: =IF(D40="", "", INDEX(Colaboradores!A:A, MATCH(D40,Colaboradores!C:C, 0))) -> E0637 | D40: EDUAR MANUEL DAVILA CERON | E40: 46041 | G40: =IFERROR(VLOOKUP(Tabla10[[#This Row],[COD]],'TotalHorasAjustadas (2)'!D:L,8,FALSE),"") -> 102.5 | H40: 15 | I40: =IFERROR(VLOOKUP(Tabla10[[#This Row],[COD]],Alojamentos!B:P,11,FALSE),"") | J40: =IF(ISBLANK(Tabla10[[#This Row],[INICIO VINCULO]]), 0, MAX(0, MIN(IF(ISBLANK(Tabla10[[#This Row],[FIM VINCULO]]), DATE(2026,1,31), Tabla10[[#This Row],[FIM VINCULO]]), DATE(2026,1,31)) - MAX(Tabla10[[#This Row],[INICIO VINCULO]], DATE(2026,1,1)) + 1)) -> 13 | K40: =7.05806*Tabla10[[#This Row],[DIAS DE ALTA]] -> 91.75478 | L40: =IFERROR(VLOOKUP(Tabla10[[#This Row],[COD]],Carro!B:D,3,FALSE),"") | M40: =IFERROR(VLOOKUP(Tabla10[[#This Row],[COD]],'Outros descontos'!B:P,15,FALSE),"") | N40: =(Tabla10[[#This Row],[HORAS TRABALHADAS]]*Tabla10[[#This Row],[TARIFA]]) - SUM(Tabla10[[#This Row],[ALOJAMENTO]], Tabla10[[#This Row],[IMPOSTO]], Tabla10[[#This Row],[CARRO]]) -> 1445.7452
B41: WS | C41: =IF(D41="", "", INDEX(Colaboradores!A:A, MATCH(D41,Colaboradores!C:C, 0))) -> E0363 | D41: EDUARD YOVANNY LOZANO OSORIO | E41: 45938 | G41: =IFERROR(VLOOKUP(Tabla10[[#This Row],[COD]],'TotalHorasAjustadas (2)'!D:L,8,FALSE),"") -> 175 | H41: =IFERROR(VLOOKUP(Tabla10[[#This Row],[COD]],Tabla15[],4,FALSE),"") -> 15 | I41: =IFERROR(VLOOKUP(Tabla10[[#This Row],[COD]],Alojamentos!B:P,11,FALSE),"") | J41: =IF(ISBLANK(Tabla10[[#This Row],[INICIO VINCULO]]), 0, MAX(0, MIN(IF(ISBLANK(Tabla10[[#This Row],[FIM VINCULO]]), DATE(2026,1,31), Tabla10[[#This Row],[FIM VINCULO]]), DATE(2026,1,31)) - MAX(Tabla10[[#This Row],[INICIO VINCULO]], DATE(2026,1,1)) + 1)) -> 31 | K41: =7.05806*Tabla10[[#This Row],[DIAS DE ALTA]] -> 218.79986 | L41: =IFERROR(VLOOKUP(Tabla10[[#This Row],[COD]],Carro!B:D,3,FALSE),"") | M41: =IFERROR(VLOOKUP(Tabla10[[#This Row],[COD]],'Outros descontos'!B:P,15,FALSE),"") -> 50 | N41: =(Tabla10[[#This Row],[HORAS TRABALHADAS]]*Tabla10[[#This Row],[TARIFA]]) - SUM(Tabla10[[#This Row],[ALOJAMENTO]], Tabla10[[#This Row],[IMPOSTO]], Tabla10[[#This Row],[CARRO]],Tabla10[[#This Row],[OUTROS DEScontos]]) -> 2356.2001
B42: LM | C42: =IF(D42="", "", INDEX(Colaboradores!A:A, MATCH(D42,Colaboradores!C:C, 0))) -> E0257 | D42: EDWAR ANDRES BENACHI ARCE | E42: 46010 | G42: =IFERROR(VLOOKUP(Tabla10[[#This Row],[COD]],'TotalHorasAjustadas (2)'!D:L,8,FALSE),"") -> 215.5 | H42: =IFERROR(VLOOKUP(Tabla10[[#This Row],[COD]],Tabla15[],4,FALSE),"") -> 15 | I42: =IFERROR(VLOOKUP(Tabla10[[#This Row],[COD]],Alojamentos!B:P,11,FALSE),"") | J42: =IF(ISBLANK(Tabla10[[#This Row],[INICIO VINCULO]]), 0, MAX(0, MIN(IF(ISBLANK(Tabla10[[#This Row],[FIM VINCULO]]), DATE(2026,1,31), Tabla10[[#This Row],[FIM VINCULO]]), DATE(2026,1,31)) - MAX(Tabla10[[#This Row],[INICIO VINCULO]], DATE(2026,1,1)) + 1)) -> 31 | K42: =7.05806*Tabla10[[#This Row],[DIAS DE ALTA]] -> 218.79986 | L42: =IFERROR(VLOOKUP(Tabla10[[#This Row],[COD]],Carro!B:D,3,FALSE),"") | M42: =IFERROR(VLOOKUP(Tabla10[[#This Row],[COD]],'Outros descontos'!B:P,15,FALSE),"") | N42: =(Tabla10[[#This Row],[HORAS TRABALHADAS]]*Tabla10[[#This Row],[TARIFA]]) - SUM(Tabla10[[#This Row],[ALOJAMENTO]], Tabla10[[#This Row],[IMPOSTO]], Tabla10[[#This Row],[CARRO]]) -> 3013.7001
B43: WS | C43: =IF(D43="", "", INDEX(Colaboradores!A:A, MATCH(D43,Colaboradores!C:C, 0))) -> E0507 | D43: EDWARD IGNACIO DIAZ AVILA | E43: 45919 | G43: =IFERROR(VLOOKUP(Tabla10[[#This Row],[COD]],'TotalHorasAjustadas (2)'!D:L,8,FALSE),"") -> 250 | H43: =IFERROR(VLOOKUP(Tabla10[[#This Row],[COD]],Tabla15[],4,FALSE),"") -> 15 | I43: =IFERROR(VLOOKUP(Tabla10[[#This Row],[COD]],Alojamentos!B:P,11,FALSE),"") | J43: =IF(ISBLANK(Tabla10[[#This Row],[INICIO VINCULO]]), 0, MAX(0, MIN(IF(ISBLANK(Tabla10[[#This Row],[FIM VINCULO]]), DATE(2026,1,31), Tabla10[[#This Row],[FIM VINCULO]]), DATE(2026,1,31)) - MAX(Tabla10[[#This Row],[INICIO VINCULO]], DATE(2026,1,1)) + 1)) -> 31 | K43: =7.05806*Tabla10[[#This Row],[DIAS DE ALTA]] -> 218.79986 | L43: =IFERROR(VLOOKUP(Tabla10[[#This Row],[COD]],Carro!B:D,3,FALSE),"") -> 67 | M43: =IFERROR(VLOOKUP(Tabla10[[#This Row],[COD]],'Outros descontos'!B:P,15,FALSE),"") | N43: =(Tabla10[[#This Row],[HORAS TRABALHADAS]]*Tabla10[[#This Row],[TARIFA]]) - SUM(Tabla10[[#This Row],[ALOJAMENTO]], Tabla10[[#This Row],[IMPOSTO]], Tabla10[[#This Row],[CARRO]]) -> 3464.2001
B44: WS | C44: =IF(D44="", "", INDEX(Colaboradores!A:A, MATCH(D44,Colaboradores!C:C, 0))) -> E0232 | D44: EDWIN ALEXANDER DIAZ PITRE | E44: 46035 | G44: =IFERROR(VLOOKUP(Tabla10[[#This Row],[COD]],'TotalHorasAjustadas (2)'!D:L,8,FALSE),"") -> 159.5 | H44: 14 | I44: =IFERROR(VLOOKUP(Tabla10[[#This Row],[COD]],Alojamentos!B:P,11,FALSE),"") | J44: =IF(ISBLANK(Tabla10[[#This Row],[INICIO VINCULO]]), 0, MAX(0, MIN(IF(ISBLANK(Tabla10[[#This Row],[FIM VINCULO]]), DATE(2026,1,31), Tabla10[[#This Row],[FIM VINCULO]]), DATE(2026,1,31)) - MAX(Tabla10[[#This Row],[INICIO VINCULO]], DATE(2026,1,1)) + 1)) -> 19 | K44: =7.05806*Tabla10[[#This Row],[DIAS DE ALTA]] -> 134.10314 | L44: =IFERROR(VLOOKUP(Tabla10[[#This Row],[COD]],Carro!B:D,3,FALSE),"") -> 13.333333 | M44: =IFERROR(VLOOKUP(Tabla10[[#This Row],[COD]],'Outros descontos'!B:P,15,FALSE),"") | N44: =(Tabla10[[#This Row],[HORAS TRABALHADAS]]*Tabla10[[#This Row],[TARIFA]]) - SUM(Tabla10[[#This Row],[ALOJAMENTO]], Tabla10[[#This Row],[IMPOSTO]], Tabla10[[#This Row],[CARRO]]) -> 2085.5635
B45: WS | C45: =IF(D45="", "", INDEX(Colaboradores!A:A, MATCH(D45,Colaboradores!C:C, 0))) -> E0364 | D45: EDWIN DIAZ MARULANDA | E45: 45938 | G45: =IFERROR(VLOOKUP(Tabla10[[#This Row],[COD]],'TotalHorasAjustadas (2)'!D:L,8,FALSE),"") -> 170 | H45: =IFERROR(VLOOKUP(Tabla10[[#This Row],[COD]],Tabla15[],4,FALSE),"") -> 15 | I45: =IFERROR(VLOOKUP(Tabla10[[#This Row],[COD]],Alojamentos!B:P,11,FALSE),"") | J45: =IF(ISBLANK(Tabla10[[#This Row],[INICIO VINCULO]]), 0, MAX(0, MIN(IF(ISBLANK(Tabla10[[#This Row],[FIM VINCULO]]), DATE(2026,1,31), Tabla10[[#This Row],[FIM VINCULO]]), DATE(2026,1,31)) - MAX(Tabla10[[#This Row],[INICIO VINCULO]], DATE(2026,1,1)) + 1)) -> 31 | K45: =7.05806*Tabla10[[#This Row],[DIAS DE ALTA]] -> 218.79986 | L45: =IFERROR(VLOOKUP(Tabla10[[#This Row],[COD]],Carro!B:D,3,FALSE),"") | M45: =IFERROR(VLOOKUP(Tabla10[[#This Row],[COD]],'Outros descontos'!B:P,15,FALSE),"") | N45: =(Tabla10[[#This Row],[HORAS TRABALHADAS]]*Tabla10[[#This Row],[TARIFA]]) - SUM(Tabla10[[#This Row],[ALOJAMENTO]], Tabla10[[#This Row],[IMPOSTO]], Tabla10[[#This Row],[CARRO]]) -> 2331.2001
B46: KR | C46: =IF(D46="", "", INDEX(Colaboradores!A:A, MATCH(D46,Colaboradores!C:C, 0))) -> E0180 | D46: EDWIN FERNANDO LINARES MACA | E46: 45796 | F46: 46052 | G46: =IFERROR(VLOOKUP(Tabla10[[#This Row],[COD]],'TotalHorasAjustadas (2)'!D:L,8,FALSE),"") -> 253 | H46: =IFERROR(VLOOKUP(Tabla10[[#This Row],[COD]],Tabla15[],4,FALSE),"") -> 15 | I46: =IFERROR(VLOOKUP(Tabla10[[#This Row],[COD]],Alojamentos!B:P,11,FALSE),"") | J46: =IF(ISBLANK(Tabla10[[#This Row],[INICIO VINCULO]]), 0, MAX(0, MIN(IF(ISBLANK(Tabla10[[#This Row],[FIM VINCULO]]), DATE(2026,1,31), Tabla10[[#This Row],[FIM VINCULO]]), DATE(2026,1,31)) - MAX(Tabla10[[#This Row],[INICIO VINCULO]], DATE(2026,1,1)) + 1)) -> 30 | K46: =7.05806*Tabla10[[#This Row],[DIAS DE ALTA]] -> 211.7418 | L46: =IFERROR(VLOOKUP(Tabla10[[#This Row],[COD]],Carro!B:D,3,FALSE),"") -> 104.44444 | M46: =IFERROR(VLOOKUP(Tabla10[[#This Row],[COD]],'Outros descontos'!B:P,15,FALSE),"") | N46: =(Tabla10[[#This Row],[HORAS TRABALHADAS]]*Tabla10[[#This Row],[TARIFA]]) - SUM(Tabla10[[#This Row],[ALOJAMENTO]], Tabla10[[#This Row],[IMPOSTO]], Tabla10[[#This Row],[CARRO]]) -> 3478.8138
B47: WS | C47: =IF(D47="", "", INDEX(Colaboradores!A:A, MATCH(D47,Colaboradores!C:C, 0))) -> E1712 | D47: EDWIN RODRIGO AVILA PENA | E47: 46037 | G47: =IFERROR(VLOOKUP(Tabla10[[#This Row],[COD]],'TotalHorasAjustadas (2)'!D:L,8,FALSE),"") -> 173 | H47: =IFERROR(VLOOKUP(Tabla10[[#This Row],[COD]],Tabla15[],4,FALSE),"") -> 15 | I47: =IFERROR(VLOOKUP(Tabla10[[#This Row],[COD]],Alojamentos!B:P,11,FALSE),"") | J47: =IF(ISBLANK(Tabla10[[#This Row],[INICIO VINCULO]]), 0, MAX(0, MIN(IF(ISBLANK(Tabla10[[#This Row],[FIM VINCULO]]), DATE(2026,1,31), Tabla10[[#This Row],[FIM VINCULO]]), DATE(2026,1,31)) - MAX(Tabla10[[#This Row],[INICIO VINCULO]], DATE(2026,1,1)) + 1)) -> 17 | K47: =7.05806*Tabla10[[#This Row],[DIAS DE ALTA]] -> 119.98702 | L47: =IFERROR(VLOOKUP(Tabla10[[#This Row],[COD]],Carro!B:D,3,FALSE),"") | M47: =IFERROR(VLOOKUP(Tabla10[[#This Row],[COD]],'Outros descontos'!B:P,15,FALSE),"") | N47: =(Tabla10[[#This Row],[HORAS TRABALHADAS]]*Tabla10[[#This Row],[TARIFA]]) - SUM(Tabla10[[#This Row],[ALOJAMENTO]], Tabla10[[#This Row],[IMPOSTO]], Tabla10[[#This Row],[CARRO]]) -> 2475.013
B48: KR | C48: =IF(D48="", "", INDEX(Colaboradores!A:A, MATCH(D48,Colaboradores!C:C, 0))) -> E0233 | D48: EISON SALAS AHUMEDO | E48: 45769 | F48: 46052 | G48: =IFERROR(VLOOKUP(Tabla10[[#This Row],[COD]],'TotalHorasAjustadas (2)'!D:L,8,FALSE),"") -> 143 | H48: =IFERROR(VLOOKUP(Tabla10[[#This Row],[COD]],Tabla15[],4,FALSE),"") -> 14 | I48: =IFERROR(VLOOKUP(Tabla10[[#This Row],[COD]],Alojamentos!B:P,11,FALSE),"") | J48: =IF(ISBLANK(Tabla10[[#This Row],[INICIO VINCULO]]), 0, MAX(0, MIN(IF(ISBLANK(Tabla10[[#This Row],[FIM VINCULO]]), DATE(2026,1,31), Tabla10[[#This Row],[FIM VINCULO]]), DATE(2026,1,31)) - MAX(Tabla10[[#This Row],[INICIO VINCULO]], DATE(2026,1,1)) + 1)) -> 30 | K48: =7.05806*Tabla10[[#This Row],[DIAS DE ALTA]] -> 211.7418 | L48: =IFERROR(VLOOKUP(Tabla10[[#This Row],[COD]],Carro!B:D,3,FALSE),"") | M48: =IFERROR(VLOOKUP(Tabla10[[#This Row],[COD]],'Outros descontos'!B:P,15,FALSE),"") | N48: =(Tabla10[[#This Row],[HORAS TRABALHADAS]]*Tabla10[[#This Row],[TARIFA]]) - SUM(Tabla10[[#This Row],[ALOJAMENTO]], Tabla10[[#This Row],[IMPOSTO]], Tabla10[[#This Row],[CARRO]]) -> 1790.2582
B49: LM | C49: =IF(D49="", "", INDEX(Colaboradores!A:A, MATCH(D49,Colaboradores!C:C, 0))) -> E0873 | D49: ELKIN ARMANDO GARZON LOPEZ | E49: 46051 | G49: =IFERROR(VLOOKUP(Tabla10[[#This Row],[COD]],'TotalHorasAjustadas (2)'!D:L,8,FALSE),"") -> 132 | H49: =IFERROR(VLOOKUP(Tabla10[[#This Row],[COD]],Tabla15[],4,FALSE),"") -> 15 | I49: =IFERROR(VLOOKUP(Tabla10[[#This Row],[COD]],Alojamentos!B:P,11,FALSE),"") | J49: =IF(ISBLANK(Tabla10[[#This Row],[INICIO VINCULO]]), 0, MAX(0, MIN(IF(ISBLANK(Tabla10[[#This Row],[FIM VINCULO]]), DATE(2026,1,31), Tabla10[[#This Row],[FIM VINCULO]]), DATE(2026,1,31)) - MAX(Tabla10[[#This Row],[INICIO VINCULO]], DATE(2026,1,1)) + 1)) -> 3 | K49: =7.05806*Tabla10[[#This Row],[DIAS DE ALTA]] -> 21.17418 | L49: =IFERROR(VLOOKUP(Tabla10[[#This Row],[COD]],Carro!B:D,3,FALSE),"") -> 128.88889 | M49: =IFERROR(VLOOKUP(Tabla10[[#This Row],[COD]],'Outros descontos'!B:P,15,FALSE),"") | N49: =(Tabla10[[#This Row],[HORAS TRABALHADAS]]*Tabla10[[#This Row],[TARIFA]]) - SUM(Tabla10[[#This Row],[ALOJAMENTO]], Tabla10[[#This Row],[IMPOSTO]], Tabla10[[#This Row],[CARRO]]) -> 1829.9369
B50: LM | C50: =IF(D50="", "", INDEX(Colaboradores!A:A, MATCH(D50,Colaboradores!C:C, 0))) -> E0537 | D50: ELTON JHONNY GONGORA BELTRAN | E50: 46036 | F50: 46041 | G50: 0 | H50: =IFERROR(VLOOKUP(Tabla10[[#This Row],[COD]],Tabla15[],4,FALSE),"") -> 15 | I50: =IFERROR(VLOOKUP(Tabla10[[#This Row],[COD]],Alojamentos!B:P,11,FALSE),"") | J50: =IF(ISBLANK(Tabla10[[#This Row],[INICIO VINCULO]]), 0, MAX(0, MIN(IF(ISBLANK(Tabla10[[#This Row],[FIM VINCULO]]), DATE(2026,1,31), Tabla10[[#This Row],[FIM VINCULO]]), DATE(2026,1,31)) - MAX(Tabla10[[#This Row],[INICIO VINCULO]], DATE(2026,1,1)) + 1)) -> 6 | K50: =7.05806*Tabla10[[#This Row],[DIAS DE ALTA]] -> 42.34836 | L50: =IFERROR(VLOOKUP(Tabla10[[#This Row],[COD]],Carro!B:D,3,FALSE),"") | M50: =IFERROR(VLOOKUP(Tabla10[[#This Row],[COD]],'Outros descontos'!B:P,15,FALSE),"") | N50: 0
B51: WS | D51: EMMANUEL DE LIMA MACIÉL | E51: 45734 | G51: 160 | H51: 0 | I51: =IFERROR(VLOOKUP(Tabla10[[#This Row],[COD]],Alojamentos!B:P,11,FALSE),"") | J51: =IF(ISBLANK(Tabla10[[#This Row],[INICIO VINCULO]]), 0, MAX(0, MIN(IF(ISBLANK(Tabla10[[#This Row],[FIM VINCULO]]), DATE(2026,1,31), Tabla10[[#This Row],[FIM VINCULO]]), DATE(2026,1,31)) - MAX(Tabla10[[#This Row],[INICIO VINCULO]], DATE(2026,1,1)) + 1)) -> 31 | K51: 0 | L51: =IFERROR(VLOOKUP(Tabla10[[#This Row],[COD]],Carro!B:D,3,FALSE),"") | M51: =IFERROR(VLOOKUP(Tabla10[[#This Row],[COD]],'Outros descontos'!B:P,15,FALSE),"") | N51: 2000
B52: KR | C52: =IF(D52="", "", INDEX(Colaboradores!A:A, MATCH(D52,Colaboradores!C:C, 0))) -> E0424 | D52: ENRI JAIME CALDAS BERMUDES | E52: 45769 | F52: 46027 | G52: 20.06 | H52: =IFERROR(VLOOKUP(Tabla10[[#This Row],[COD]],Tabla15[],4,FALSE),"") -> 15 | I52: =IFERROR(VLOOKUP(Tabla10[[#This Row],[COD]],Alojamentos!B:P,11,FALSE),"") | J52: =IF(ISBLANK(Tabla10[[#This Row],[INICIO VINCULO]]), 0, MAX(0, MIN(IF(ISBLANK(Tabla10[[#This Row],[FIM VINCULO]]), DATE(2026,1,31), Tabla10[[#This Row],[FIM VINCULO]]), DATE(2026,1,31)) - MAX(Tabla10[[#This Row],[INICIO VINCULO]], DATE(2026,1,1)) + 1)) -> 5 | K52: =7.05806*Tabla10[[#This Row],[DIAS DE ALTA]] -> 35.2903 | L52: =IFERROR(VLOOKUP(Tabla10[[#This Row],[COD]],Carro!B:D,3,FALSE),"") | M52: =IFERROR(VLOOKUP(Tabla10[[#This Row],[COD]],'Outros descontos'!B:P,15,FALSE),"") | N52: =(Tabla10[[#This Row],[HORAS TRABALHADAS]]*Tabla10[[#This Row],[TARIFA]]) - SUM(Tabla10[[#This Row],[ALOJAMENTO]], Tabla10[[#This Row],[IMPOSTO]], Tabla10[[#This Row],[CARRO]]) -> 265.6097
B53: LM | C53: =IF(D53="", "", INDEX(Colaboradores!A:A, MATCH(D53,Colaboradores!C:C, 0))) -> E0424 | D53: ENRI JAIME CALDAS BERMUDES | E53: 46028 | G53: 170 | H53: =IFERROR(VLOOKUP(Tabla10[[#This Row],[COD]],Tabla15[],4,FALSE),"") -> 15 | I53: =IFERROR(VLOOKUP(Tabla10[[#This Row],[COD]],Alojamentos!B:P,11,FALSE),"") | J53: =IF(ISBLANK(Tabla10[[#This Row],[INICIO VINCULO]]), 0, MAX(0, MIN(IF(ISBLANK(Tabla10[[#This Row],[FIM VINCULO]]), DATE(2026,1,31), Tabla10[[#This Row],[FIM VINCULO]]), DATE(2026,1,31)) - MAX(Tabla10[[#This Row],[INICIO VINCULO]], DATE(2026,1,1)) + 1)) -> 26 | K53: =7.05806*Tabla10[[#This Row],[DIAS DE ALTA]] -> 183.50956 | L53: =IFERROR(VLOOKUP(Tabla10[[#This Row],[COD]],Carro!B:D,3,FALSE),"") | M53: =IFERROR(VLOOKUP(Tabla10[[#This Row],[COD]],'Outros descontos'!B:P,15,FALSE),"") | N53: =(Tabla10[[#This Row],[HORAS TRABALHADAS]]*Tabla10[[#This Row],[TARIFA]]) - SUM(Tabla10[[#This Row],[ALOJAMENTO]], Tabla10[[#This Row],[IMPOSTO]], Tabla10[[#This Row],[CARRO]]) -> 2366.4904
B54: LM | C54: =IF(D54="", "", INDEX(Colaboradores!A:A, MATCH(D54,Colaboradores!C:C, 0))) -> E1117 | D54: ERIK RUBEN RAMIREZ SIMANCAS | E54: 45979 | G54: =IFERROR(VLOOKUP(Tabla10[[#This Row],[COD]],'TotalHorasAjustadas (2)'!D:L,8,FALSE),"") -> 151.5 | H54: =IFERROR(VLOOKUP(Tabla10[[#This Row],[COD]],Tabla15[],4,FALSE),"") -> 15 | I54: =IFERROR(VLOOKUP(Tabla10[[#This Row],[COD]],Alojamentos!B:P,11,FALSE),"") | J54: =IF(ISBLANK(Tabla10[[#This Row],[INICIO VINCULO]]), 0, MAX(0, MIN(IF(ISBLANK(Tabla10[[#This Row],[FIM VINCULO]]), DATE(2026,1,31), Tabla10[[#This Row],[FIM VINCULO]]), DATE(2026,1,31)) - MAX(Tabla10[[#This Row],[INICIO VINCULO]], DATE(2026,1,1)) + 1)) -> 31 | K54: =7.05806*Tabla10[[#This Row],[DIAS DE ALTA]] -> 218.79986 | L54: =IFERROR(VLOOKUP(Tabla10[[#This Row],[COD]],Carro!B:D,3,FALSE),"") | M54: =IFERROR(VLOOKUP(Tabla10[[#This Row],[COD]],'Outros descontos'!B:P,15,FALSE),"") -> 21.74 | N54: =(Tabla10[[#This Row],[HORAS TRABALHADAS]]*Tabla10[[#This Row],[TARIFA]]) - SUM(Tabla10[[#This Row],[ALOJAMENTO]], Tabla10[[#This Row],[IMPOSTO]], Tabla10[[#This Row],[CARRO]]) -> 2053.7001
B55: WS | C55: =IF(D55="", "", INDEX(Colaboradores!A:A, MATCH(D55,Colaboradores!C:C, 0))) -> E1713 | D55: ERNESTO GERMAN HERRERA | E55: 45945 | F55: 46052 | G55: =IFERROR(VLOOKUP(Tabla10[[#This Row],[COD]],'TotalHorasAjustadas (2)'!D:L,8,FALSE),"") -> 162 | H55: =IFERROR(VLOOKUP(Tabla10[[#This Row],[COD]],Tabla15[],4,FALSE),"") -> 15 | I55: =IFERROR(VLOOKUP(Tabla10[[#This Row],[COD]],Alojamentos!B:P,11,FALSE),"") -> 300 | J55: =IF(ISBLANK(Tabla10[[#This Row],[INICIO VINCULO]]), 0, MAX(0, MIN(IF(ISBLANK(Tabla10[[#This Row],[FIM VINCULO]]), DATE(2026,1,31), Tabla10[[#This Row],[FIM VINCULO]]), DATE(2026,1,31)) - MAX(Tabla10[[#This Row],[INICIO VINCULO]], DATE(2026,1,1)) + 1)) -> 30 | K55: =7.05806*Tabla10[[#This Row],[DIAS DE ALTA]] -> 211.7418 | L55: =IFERROR(VLOOKUP(Tabla10[[#This Row],[COD]],Carro!B:D,3,FALSE),"") | M55: =IFERROR(VLOOKUP(Tabla10[[#This Row],[COD]],'Outros descontos'!B:P,15,FALSE),"") | N55: =(Tabla10[[#This Row],[HORAS TRABALHADAS]]*Tabla10[[#This Row],[TARIFA]]) - SUM(Tabla10[[#This Row],[ALOJAMENTO]], Tabla10[[#This Row],[IMPOSTO]], Tabla10[[#This Row],[CARRO]]) -> 1918.2582
B56: WS | D56: EVA MARIA KOTRIK REIS | E56: 45819 | G56: 160 | H56: 0 | I56: =IFERROR(VLOOKUP(Tabla10[[#This Row],[COD]],Alojamentos!B:P,11,FALSE),"") | J56: =IF(ISBLANK(Tabla10[[#This Row],[INICIO VINCULO]]), 0, MAX(0, MIN(IF(ISBLANK(Tabla10[[#This Row],[FIM VINCULO]]), DATE(2026,1,31), Tabla10[[#This Row],[FIM VINCULO]]), DATE(2026,1,31)) - MAX(Tabla10[[#This Row],[INICIO VINCULO]], DATE(2026,1,1)) + 1)) -> 31 | K56: 0 | L56: =IFERROR(VLOOKUP(Tabla10[[#This Row],[COD]],Carro!B:D,3,FALSE),"") | M56: =IFERROR(VLOOKUP(Tabla10[[#This Row],[COD]],'Outros descontos'!B:P,15,FALSE),"") | N56: 1325
B57: KI | C57: =IF(D57="", "", INDEX(Colaboradores!A:A, MATCH(D57,Colaboradores!C:C, 0))) -> E0125 | D57: EVELIO ANGULO ANGULO | E57: 45761 | F57: 46052 | G57: =IFERROR(VLOOKUP(Tabla10[[#This Row],[COD]],'TotalHorasAjustadas (2)'!D:L,8,FALSE),"") -> 142 | H57: =IFERROR(VLOOKUP(Tabla10[[#This Row],[COD]],Tabla15[],4,FALSE),"") -> 15 | I57: =IFERROR(VLOOKUP(Tabla10[[#This Row],[COD]],Alojamentos!B:P,11,FALSE),"") | J57: =IF(ISBLANK(Tabla10[[#This Row],[INICIO VINCULO]]), 0, MAX(0, MIN(IF(ISBLANK(Tabla10[[#This Row],[FIM VINCULO]]), DATE(2026,1,31), Tabla10[[#This Row],[FIM VINCULO]]), DATE(2026,1,31)) - MAX(Tabla10[[#This Row],[INICIO VINCULO]], DATE(2026,1,1)) + 1)) -> 30 | K57: =7.05806*Tabla10[[#This Row],[DIAS DE ALTA]] -> 211.7418 | L57: =IFERROR(VLOOKUP(Tabla10[[#This Row],[COD]],Carro!B:D,3,FALSE),"") -> 66.666667 | M57: =IFERROR(VLOOKUP(Tabla10[[#This Row],[COD]],'Outros descontos'!B:P,15,FALSE),"") | N57: =(Tabla10[[#This Row],[HORAS TRABALHADAS]]*Tabla10[[#This Row],[TARIFA]]) - SUM(Tabla10[[#This Row],[ALOJAMENTO]], Tabla10[[#This Row],[IMPOSTO]], Tabla10[[#This Row],[CARRO]]) -> 1851.5915
B58: WS | C58: =IF(D58="", "", INDEX(Colaboradores!A:A, MATCH(D58,Colaboradores!C:C, 0))) -> E0389 | D58: FABIAN ARTURO RUIZ GARCIA | E58: 45939 | G58: =IFERROR(VLOOKUP(Tabla10[[#This Row],[COD]],'TotalHorasAjustadas (2)'!D:L,8,FALSE),"") -> 176 | H58: =IFERROR(VLOOKUP(Tabla10[[#This Row],[COD]],Tabla15[],4,FALSE),"") -> 15 | I58: =IFERROR(VLOOKUP(Tabla10[[#This Row],[COD]],Alojamentos!B:P,11,FALSE),"") -> 300 | J58: =IF(ISBLANK(Tabla10[[#This Row],[INICIO VINCULO]]), 0, MAX(0, MIN(IF(ISBLANK(Tabla10[[#This Row],[FIM VINCULO]]), DATE(2026,1,31), Tabla10[[#This Row],[FIM VINCULO]]), DATE(2026,1,31)) - MAX(Tabla10[[#This Row],[INICIO VINCULO]], DATE(2026,1,1)) + 1)) -> 31 | K58: =7.05806*Tabla10[[#This Row],[DIAS DE ALTA]] -> 218.79986 | L58: =IFERROR(VLOOKUP(Tabla10[[#This Row],[COD]],Carro!B:D,3,FALSE),"") | M58: =IFERROR(VLOOKUP(Tabla10[[#This Row],[COD]],'Outros descontos'!B:P,15,FALSE),"") | N58: =(Tabla10[[#This Row],[HORAS TRABALHADAS]]*Tabla10[[#This Row],[TARIFA]]) - SUM(Tabla10[[#This Row],[ALOJAMENTO]], Tabla10[[#This Row],[IMPOSTO]], Tabla10[[#This Row],[CARRO]]) -> 2121.2001
B59: LM | C59: =IF(D59="", "", INDEX(Colaboradores!A:A, MATCH(D59,Colaboradores!C:C, 0))) -> E0429 | D59: FABIO ANDRES LUJAN ARANGO | E59: 46013 | G59: =IFERROR(VLOOKUP(Tabla10[[#This Row],[COD]],'TotalHorasAjustadas (2)'!D:L,8,FALSE),"") -> 176.56 | H59: =IFERROR(VLOOKUP(Tabla10[[#This Row],[COD]],Tabla15[],4,FALSE),"") -> 15 | I59: =IFERROR(VLOOKUP(Tabla10[[#This Row],[COD]],Alojamentos!B:P,11,FALSE),"") | J59: =IF(ISBLANK(Tabla10[[#This Row],[INICIO VINCULO]]), 0, MAX(0, MIN(IF(ISBLANK(Tabla10[[#This Row],[FIM VINCULO]]), DATE(2026,1,31), Tabla10[[#This Row],[FIM VINCULO]]), DATE(2026,1,31)) - MAX(Tabla10[[#This Row],[INICIO VINCULO]], DATE(2026,1,1)) + 1)) -> 31 | K59: =7.05806*Tabla10[[#This Row],[DIAS DE ALTA]] -> 218.79986 | L59: =IFERROR(VLOOKUP(Tabla10[[#This Row],[COD]],Carro!B:D,3,FALSE),"") | M59: =IFERROR(VLOOKUP(Tabla10[[#This Row],[COD]],'Outros descontos'!B:P,15,FALSE),"") | N59: =(Tabla10[[#This Row],[HORAS TRABALHADAS]]*Tabla10[[#This Row],[TARIFA]]) - SUM(Tabla10[[#This Row],[ALOJAMENTO]], Tabla10[[#This Row],[IMPOSTO]], Tabla10[[#This Row],[CARRO]]) -> 2429.6001
B60: WS | D60: FERNANDO HENRIQUE GONÇALVES PZIVITOVSKI | E60: 45819 | G60: 160 | H60: 0 | I60: =IFERROR(VLOOKUP(Tabla10[[#This Row],[COD]],Alojamentos!B:P,11,FALSE),"") | J60: =IF(ISBLANK(Tabla10[[#This Row],[INICIO VINCULO]]), 0, MAX(0, MIN(IF(ISBLANK(Tabla10[[#This Row],[FIM VINCULO]]), DATE(2026,1,31), Tabla10[[#This Row],[FIM VINCULO]]), DATE(2026,1,31)) - MAX(Tabla10[[#This Row],[INICIO VINCULO]], DATE(2026,1,1)) + 1)) -> 31 | K60: 0 | L60: =IFERROR(VLOOKUP(Tabla10[[#This Row],[COD]],Carro!B:D,3,FALSE),"") | M60: =IFERROR(VLOOKUP(Tabla10[[#This Row],[COD]],'Outros descontos'!B:P,15,FALSE),"") | N60: 2481.89
B61: KI | C61: =IF(D61="", "", INDEX(Colaboradores!A:A, MATCH(D61,Colaboradores!C:C, 0))) -> E2082 | D61: FERNEY ALEXANDER VARGAS SERRANO | E61: 45761 | F61: 46052 | G61: =IFERROR(VLOOKUP(Tabla10[[#This Row],[COD]],'TotalHorasAjustadas (2)'!D:L,8,FALSE),"") -> 135 | H61: 15 | I61: =IFERROR(VLOOKUP(Tabla10[[#This Row],[COD]],Alojamentos!B:P,11,FALSE),"") | J61: =IF(ISBLANK(Tabla10[[#This Row],[INICIO VINCULO]]), 0, MAX(0, MIN(IF(ISBLANK(Tabla10[[#This Row],[FIM VINCULO]]), DATE(2026,1,31), Tabla10[[#This Row],[FIM VINCULO]]), DATE(2026,1,31)) - MAX(Tabla10[[#This Row],[INICIO VINCULO]], DATE(2026,1,1)) + 1)) -> 30 | K61: =7.05806*Tabla10[[#This Row],[DIAS DE ALTA]] -> 211.7418 | L61: =IFERROR(VLOOKUP(Tabla10[[#This Row],[COD]],Carro!B:D,3,FALSE),"") | M61: =IFERROR(VLOOKUP(Tabla10[[#This Row],[COD]],'Outros descontos'!B:P,15,FALSE),"") | N61: =(Tabla10[[#This Row],[HORAS TRABALHADAS]]*Tabla10[[#This Row],[TARIFA]]) - SUM(Tabla10[[#This Row],[ALOJAMENTO]], Tabla10[[#This Row],[IMPOSTO]], Tabla10[[#This Row],[CARRO]]) -> 1813.2582
B62: KR | C62: =IF(D62="", "", INDEX(Colaboradores!A:A, MATCH(D62,Colaboradores!C:C, 0))) -> E0229 | D62: FRANCISCO JAVIER MERCADO MELENDEZ | E62: 45761 | F62: 46052 | G62: =IFERROR(VLOOKUP(Tabla10[[#This Row],[COD]],'TotalHorasAjustadas (2)'!D:L,8,FALSE),"") -> 144 | H62: =IFERROR(VLOOKUP(Tabla10[[#This Row],[COD]],Tabla15[],4,FALSE),"") -> 14 | I62: =IFERROR(VLOOKUP(Tabla10[[#This Row],[COD]],Alojamentos!B:P,11,FALSE),"") | J62: =IF(ISBLANK(Tabla10[[#This Row],[INICIO VINCULO]]), 0, MAX(0, MIN(IF(ISBLANK(Tabla10[[#This Row],[FIM VINCULO]]), DATE(2026,1,31), Tabla10[[#This Row],[FIM VINCULO]]), DATE(2026,1,31)) - MAX(Tabla10[[#This Row],[INICIO VINCULO]], DATE(2026,1,1)) + 1)) -> 30 | K62: =7.05806*Tabla10[[#This Row],[DIAS DE ALTA]] -> 211.7418 | L62: =IFERROR(VLOOKUP(Tabla10[[#This Row],[COD]],Carro!B:D,3,FALSE),"") | M62: =IFERROR(VLOOKUP(Tabla10[[#This Row],[COD]],'Outros descontos'!B:P,15,FALSE),"") | N62: =(Tabla10[[#This Row],[HORAS TRABALHADAS]]*Tabla10[[#This Row],[TARIFA]]) - SUM(Tabla10[[#This Row],[ALOJAMENTO]], Tabla10[[#This Row],[IMPOSTO]], Tabla10[[#This Row],[CARRO]]) -> 1804.2582
B63: WS | C63: =IF(D63="", "", INDEX(Colaboradores!A:A, MATCH(D63,Colaboradores!C:C, 0))) -> E0414 | D63: FREDIS ANTONIO MORELOS COLON | E63: 45828 | F63: 46036 | G63: =IFERROR(VLOOKUP(Tabla10[[#This Row],[COD]],'TotalHorasAjustadas (2)'!D:L,8,FALSE),"") -> 80 | H63: =IFERROR(VLOOKUP(Tabla10[[#This Row],[COD]],Tabla15[],4,FALSE),"") -> 16 | I63: =IFERROR(VLOOKUP(Tabla10[[#This Row],[COD]],Alojamentos!B:P,11,FALSE),"") | J63: =IF(ISBLANK(Tabla10[[#This Row],[INICIO VINCULO]]), 0, MAX(0, MIN(IF(ISBLANK(Tabla10[[#This Row],[FIM VINCULO]]), DATE(2026,1,31), Tabla10[[#This Row],[FIM VINCULO]]), DATE(2026,1,31)) - MAX(Tabla10[[#This Row],[INICIO VINCULO]], DATE(2026,1,1)) + 1)) -> 14 | K63: =7.05806*Tabla10[[#This Row],[DIAS DE ALTA]] -> 98.81284 | L63: =IFERROR(VLOOKUP(Tabla10[[#This Row],[COD]],Carro!B:D,3,FALSE),"") | M63: =IFERROR(VLOOKUP(Tabla10[[#This Row],[COD]],'Outros descontos'!B:P,15,FALSE),"") | N63: =(Tabla10[[#This Row],[HORAS TRABALHADAS]]*Tabla10[[#This Row],[TARIFA]]) - SUM(Tabla10[[#This Row],[ALOJAMENTO]], Tabla10[[#This Row],[IMPOSTO]], Tabla10[[#This Row],[CARRO]]) -> 1181.1872
B64: LM | C64: =IF(D64="", "", INDEX(Colaboradores!A:A, MATCH(D64,Colaboradores!C:C, 0))) -> E0414 | D64: FREDIS ANTONIO MORELOS COLON | E64: 46042 | G64: =IFERROR(VLOOKUP(Tabla10[[#This Row],[COD]],'TotalHorasAjustadas (2)'!D:L,8,FALSE),"") -> 80 | H64: =IFERROR(VLOOKUP(Tabla10[[#This Row],[COD]],Tabla15[],4,FALSE),"") -> 16 | I64: =IFERROR(VLOOKUP(Tabla10[[#This Row],[COD]],Alojamentos!B:P,11,FALSE),"") | J64: =IF(ISBLANK(Tabla10[[#This Row],[INICIO VINCULO]]), 0, MAX(0, MIN(IF(ISBLANK(Tabla10[[#This Row],[FIM VINCULO]]), DATE(2026,1,31), Tabla10[[#This Row],[FIM VINCULO]]), DATE(2026,1,31)) - MAX(Tabla10[[#This Row],[INICIO VINCULO]], DATE(2026,1,1)) + 1)) -> 12 | K64: =7.05806*Tabla10[[#This Row],[DIAS DE ALTA]] -> 84.69672 | L64: =IFERROR(VLOOKUP(Tabla10[[#This Row],[COD]],Carro!B:D,3,FALSE),"") | M64: =IFERROR(VLOOKUP(Tabla10[[#This Row],[COD]],'Outros descontos'!B:P,15,FALSE),"") | N64: =(Tabla10[[#This Row],[HORAS TRABALHADAS]]*Tabla10[[#This Row],[TARIFA]]) - SUM(Tabla10[[#This Row],[ALOJAMENTO]], Tabla10[[#This Row],[IMPOSTO]], Tabla10[[#This Row],[CARRO]]) -> 1195.3033
B65: KR | C65: =IF(D65="", "", INDEX(Colaboradores!A:A, MATCH(D65,Colaboradores!C:C, 0))) -> E0394 | D65: FREDY MANCERA URIBE | E65: 45761 | F65: 46052 | G65: =IFERROR(VLOOKUP(Tabla10[[#This Row],[COD]],'TotalHorasAjustadas (2)'!D:L,8,FALSE),"") -> 143 | H65: =IFERROR(VLOOKUP(Tabla10[[#This Row],[COD]],Tabla15[],4,FALSE),"") -> 15 | I65: =IFERROR(VLOOKUP(Tabla10[[#This Row],[COD]],Alojamentos!B:P,11,FALSE),"") -> 300 | J65: =IF(ISBLANK(Tabla10[[#This Row],[INICIO VINCULO]]), 0, MAX(0, MIN(IF(ISBLANK(Tabla10[[#This Row],[FIM VINCULO]]), DATE(2026,1,31), Tabla10[[#This Row],[FIM VINCULO]]), DATE(2026,1,31)) - MAX(Tabla10[[#This Row],[INICIO VINCULO]], DATE(2026,1,1)) + 1)) -> 30 | K65: =7.05806*Tabla10[[#This Row],[DIAS DE ALTA]] -> 211.7418 | L65: =IFERROR(VLOOKUP(Tabla10[[#This Row],[COD]],Carro!B:D,3,FALSE),"") | M65: =IFERROR(VLOOKUP(Tabla10[[#This Row],[COD]],'Outros descontos'!B:P,15,FALSE),"") | N65: =(Tabla10[[#This Row],[HORAS TRABALHADAS]]*Tabla10[[#This Row],[TARIFA]]) - SUM(Tabla10[[#This Row],[ALOJAMENTO]], Tabla10[[#This Row],[IMPOSTO]], Tabla10[[#This Row],[CARRO]]) -> 1633.2582
B66: KR | C66: =IF(D66="", "", INDEX(Colaboradores!A:A, MATCH(D66,Colaboradores!C:C, 0))) -> E0104 | D66: GILBER MORA DIAZ | E66: 45751 | G66: =IFERROR(VLOOKUP(Tabla10[[#This Row],[COD]],'TotalHorasAjustadas (2)'!D:L,8,FALSE),"") -> 173 | H66: =IFERROR(VLOOKUP(Tabla10[[#This Row],[COD]],Tabla15[],4,FALSE),"") -> 15 | I66: =IFERROR(VLOOKUP(Tabla10[[#This Row],[COD]],Alojamentos!B:P,11,FALSE),"") | J66: =IF(ISBLANK(Tabla10[[#This Row],[INICIO VINCULO]]), 0, MAX(0, MIN(IF(ISBLANK(Tabla10[[#This Row],[FIM VINCULO]]), DATE(2026,1,31), Tabla10[[#This Row],[FIM VINCULO]]), DATE(2026,1,31)) - MAX(Tabla10[[#This Row],[INICIO VINCULO]], DATE(2026,1,1)) + 1)) -> 31 | K66: =7.05806*Tabla10[[#This Row],[DIAS DE ALTA]] -> 218.79986 | L66: =IFERROR(VLOOKUP(Tabla10[[#This Row],[COD]],Carro!B:D,3,FALSE),"") | M66: =IFERROR(VLOOKUP(Tabla10[[#This Row],[COD]],'Outros descontos'!B:P,15,FALSE),"") | N66: =(Tabla10[[#This Row],[HORAS TRABALHADAS]]*Tabla10[[#This Row],[TARIFA]]) - SUM(Tabla10[[#This Row],[ALOJAMENTO]], Tabla10[[#This Row],[IMPOSTO]], Tabla10[[#This Row],[CARRO]]) -> 2376.2001
B67: LM | C67: =IF(D67="", "", INDEX(Colaboradores!A:A, MATCH(D67,Colaboradores!C:C, 0))) -> E0094 | D67: GONZALO ARIEL NAVARRO | E67: 45931 | G67: =IFERROR(VLOOKUP(Tabla10[[#This Row],[COD]],'TotalHorasAjustadas (2)'!D:L,8,FALSE),"") -> 185 | H67: =IFERROR(VLOOKUP(Tabla10[[#This Row],[COD]],Tabla15[],4,FALSE),"") -> 15 | I67: =IFERROR(VLOOKUP(Tabla10[[#This Row],[COD]],Alojamentos!B:P,11,FALSE),"") -> 300 | J67: =IF(ISBLANK(Tabla10[[#This Row],[INICIO VINCULO]]), 0, MAX(0, MIN(IF(ISBLANK(Tabla10[[#This Row],[FIM VINCULO]]), DATE(2026,1,31), Tabla10[[#This Row],[FIM VINCULO]]), DATE(2026,1,31)) - MAX(Tabla10[[#This Row],[INICIO VINCULO]], DATE(2026,1,1)) + 1)) -> 31 | K67: =7.05806*Tabla10[[#This Row],[DIAS DE ALTA]] -> 218.79986 | L67: =IFERROR(VLOOKUP(Tabla10[[#This Row],[COD]],Carro!B:D,3,FALSE),"") | M67: =IFERROR(VLOOKUP(Tabla10[[#This Row],[COD]],'Outros descontos'!B:P,15,FALSE),"") | N67: =(Tabla10[[#This Row],[HORAS TRABALHADAS]]*Tabla10[[#This Row],[TARIFA]]) - SUM(Tabla10[[#This Row],[ALOJAMENTO]], Tabla10[[#This Row],[IMPOSTO]], Tabla10[[#This Row],[CARRO]]) -> 2256.2001
B68: LM | C68: =IF(D68="", "", INDEX(Colaboradores!A:A, MATCH(D68,Colaboradores!C:C, 0))) -> E1216 | D68: GONZALO QUINTANA PIMIENTO | E68: 46052 | G68: =IFERROR(VLOOKUP(Tabla10[[#This Row],[COD]],'TotalHorasAjustadas (2)'!D:L,8,FALSE),"") -> 13 | H68: 15 | I68: =IFERROR(VLOOKUP(Tabla10[[#This Row],[COD]],Alojamentos!B:P,11,FALSE),"") | J68: =IF(ISBLANK(Tabla10[[#This Row],[INICIO VINCULO]]), 0, MAX(0, MIN(IF(ISBLANK(Tabla10[[#This Row],[FIM VINCULO]]), DATE(2026,1,31), Tabla10[[#This Row],[FIM VINCULO]]), DATE(2026,1,31)) - MAX(Tabla10[[#This Row],[INICIO VINCULO]], DATE(2026,1,1)) + 1)) -> 2 | K68: =7.05806*Tabla10[[#This Row],[DIAS DE ALTA]] -> 14.11612 | L68: =IFERROR(VLOOKUP(Tabla10[[#This Row],[COD]],Carro!B:D,3,FALSE),"") | M68: =IFERROR(VLOOKUP(Tabla10[[#This Row],[COD]],'Outros descontos'!B:P,15,FALSE),"") | N68: =(Tabla10[[#This Row],[HORAS TRABALHADAS]]*Tabla10[[#This Row],[TARIFA]]) - SUM(Tabla10[[#This Row],[ALOJAMENTO]], Tabla10[[#This Row],[IMPOSTO]], Tabla10[[#This Row],[CARRO]]) -> 180.88388
B69: WS | C69: =IF(D69="", "", INDEX(Colaboradores!A:A, MATCH(D69,Colaboradores!C:C, 0))) -> E0387 | D69: GUILLERMO ARCINIEGAS MURILLO | E69: 45939 | G69: =IFERROR(VLOOKUP(Tabla10[[#This Row],[COD]],'TotalHorasAjustadas (2)'!D:L,8,FALSE),"") -> 170 | H69: =IFERROR(VLOOKUP(Tabla10[[#This Row],[COD]],Tabla15[],4,FALSE),"") -> 15 | I69: =IFERROR(VLOOKUP(Tabla10[[#This Row],[COD]],Alojamentos!B:P,11,FALSE),"") -> 300 | J69: =IF(ISBLANK(Tabla10[[#This Row],[INICIO VINCULO]]), 0, MAX(0, MIN(IF(ISBLANK(Tabla10[[#This Row],[FIM VINCULO]]), DATE(2026,1,31), Tabla10[[#This Row],[FIM VINCULO]]), DATE(2026,1,31)) - MAX(Tabla10[[#This Row],[INICIO VINCULO]], DATE(2026,1,1)) + 1)) -> 31 | K69: =7.05806*Tabla10[[#This Row],[DIAS DE ALTA]] -> 218.79986 | L69: =IFERROR(VLOOKUP(Tabla10[[#This Row],[COD]],Carro!B:D,3,FALSE),"") | M69: =IFERROR(VLOOKUP(Tabla10[[#This Row],[COD]],'Outros descontos'!B:P,15,FALSE),"") | N69: =(Tabla10[[#This Row],[HORAS TRABALHADAS]]*Tabla10[[#This Row],[TARIFA]]) - SUM(Tabla10[[#This Row],[ALOJAMENTO]], Tabla10[[#This Row],[IMPOSTO]], Tabla10[[#This Row],[CARRO]]) -> 2031.2001
B70: LM | C70: =IF(D70="", "", INDEX(Colaboradores!A:A, MATCH(D70,Colaboradores!C:C, 0))) -> E0089 | D70: GUSTAVO DAMIAN DONOSO | E70: 45931 | G70: =IFERROR(VLOOKUP(Tabla10[[#This Row],[COD]],'TotalHorasAjustadas (2)'!D:L,8,FALSE),"") -> 163 | H70: =IFERROR(VLOOKUP(Tabla10[[#This Row],[COD]],Tabla15[],4,FALSE),"") -> 18 | I70: =IFERROR(VLOOKUP(Tabla10[[#This Row],[COD]],Alojamentos!B:P,11,FALSE),"") -> 300 | J70: =IF(ISBLANK(Tabla10[[#This Row],[INICIO VINCULO]]), 0, MAX(0, MIN(IF(ISBLANK(Tabla10[[#This Row],[FIM VINCULO]]), DATE(2026,1,31), Tabla10[[#This Row],[FIM VINCULO]]), DATE(2026,1,31)) - MAX(Tabla10[[#This Row],[INICIO VINCULO]], DATE(2026,1,1)) + 1)) -> 31 | K70: =7.05806*Tabla10[[#This Row],[DIAS DE ALTA]] -> 218.79986 | L70: =IFERROR(VLOOKUP(Tabla10[[#This Row],[COD]],Carro!B:D,3,FALSE),"") | M70: =IFERROR(VLOOKUP(Tabla10[[#This Row],[COD]],'Outros descontos'!B:P,15,FALSE),"") | N70: =(Tabla10[[#This Row],[HORAS TRABALHADAS]]*Tabla10[[#This Row],[TARIFA]]) - SUM(Tabla10[[#This Row],[ALOJAMENTO]], Tabla10[[#This Row],[IMPOSTO]], Tabla10[[#This Row],[CARRO]]) -> 2415.2001
B71: LM | C71: =IF(D71="", "", INDEX(Colaboradores!A:A, MATCH(D71,Colaboradores!C:C, 0))) -> E1504 | D71: HARRIS HUMBERTO MENDOZA ANGULO | E71: 46041 | G71: =IFERROR(VLOOKUP(Tabla10[[#This Row],[COD]],'TotalHorasAjustadas (2)'!D:L,8,FALSE),"") -> 111 | H71: 15 | I71: =IFERROR(VLOOKUP(Tabla10[[#This Row],[COD]],Alojamentos!B:P,11,FALSE),"") -> 30 | J71: =IF(ISBLANK(Tabla10[[#This Row],[INICIO VINCULO]]), 0, MAX(0, MIN(IF(ISBLANK(Tabla10[[#This Row],[FIM VINCULO]]), DATE(2026,1,31), Tabla10[[#This Row],[FIM VINCULO]]), DATE(2026,1,31)) - MAX(Tabla10[[#This Row],[INICIO VINCULO]], DATE(2026,1,1)) + 1)) -> 13 | K71: =7.05806*Tabla10[[#This Row],[DIAS DE ALTA]] -> 91.75478 | L71: =IFERROR(VLOOKUP(Tabla10[[#This Row],[COD]],Carro!B:D,3,FALSE),"") | M71: =IFERROR(VLOOKUP(Tabla10[[#This Row],[COD]],'Outros descontos'!B:P,15,FALSE),"") | N71: =(Tabla10[[#This Row],[HORAS TRABALHADAS]]*Tabla10[[#This Row],[TARIFA]]) - SUM(Tabla10[[#This Row],[ALOJAMENTO]], Tabla10[[#This Row],[IMPOSTO]], Tabla10[[#This Row],[CARRO]]) -> 1543.2452
B72: LM | C72: =IF(D72="", "", INDEX(Colaboradores!A:A, MATCH(D72,Colaboradores!C:C, 0))) -> E0557 | D72: HECTOR FABIO MAHETE CEDEÑO | E72: 45932 | G72: =IFERROR(VLOOKUP(Tabla10[[#This Row],[COD]],'TotalHorasAjustadas (2)'!D:L,8,FALSE),"") -> 218 | H72: =IFERROR(VLOOKUP(Tabla10[[#This Row],[COD]],Tabla15[],4,FALSE),"") -> 16 | I72: =IFERROR(VLOOKUP(Tabla10[[#This Row],[COD]],Alojamentos!B:P,11,FALSE),"") -> 300 | J72: =IF(ISBLANK(Tabla10[[#This Row],[INICIO VINCULO]]), 0, MAX(0, MIN(IF(ISBLANK(Tabla10[[#This Row],[FIM VINCULO]]), DATE(2026,1,31), Tabla10[[#This Row],[FIM VINCULO]]), DATE(2026,1,31)) - MAX(Tabla10[[#This Row],[INICIO VINCULO]], DATE(2026,1,1)) + 1)) -> 31 | K72: =7.05806*Tabla10[[#This Row],[DIAS DE ALTA]] -> 218.79986 | L72: =IFERROR(VLOOKUP(Tabla10[[#This Row],[COD]],Carro!B:D,3,FALSE),"") | M72: =IFERROR(VLOOKUP(Tabla10[[#This Row],[COD]],'Outros descontos'!B:P,15,FALSE),"") | N72: =(Tabla10[[#This Row],[HORAS TRABALHADAS]]*Tabla10[[#This Row],[TARIFA]]) - SUM(Tabla10[[#This Row],[ALOJAMENTO]], Tabla10[[#This Row],[IMPOSTO]], Tabla10[[#This Row],[CARRO]]) -> 2969.2001
B73: LM | C73: =IF(D73="", "", INDEX(Colaboradores!A:A, MATCH(D73,Colaboradores!C:C, 0))) -> E1074 | D73: HECTOR FABIO VASQUEZ MAYORGA | E73: 46048 | G73: =IFERROR(VLOOKUP(Tabla10[[#This Row],[COD]],'TotalHorasAjustadas (2)'!D:L,8,FALSE),"") -> 39.5 | H73: =IFERROR(VLOOKUP(Tabla10[[#This Row],[COD]],Tabla15[],4,FALSE),"") -> 16 | I73: =IFERROR(VLOOKUP(Tabla10[[#This Row],[COD]],Alojamentos!B:P,11,FALSE),"") | J73: =IF(ISBLANK(Tabla10[[#This Row],[INICIO VINCULO]]), 0, MAX(0, MIN(IF(ISBLANK(Tabla10[[#This Row],[FIM VINCULO]]), DATE(2026,1,31), Tabla10[[#This Row],[FIM VINCULO]]), DATE(2026,1,31)) - MAX(Tabla10[[#This Row],[INICIO VINCULO]], DATE(2026,1,1)) + 1)) -> 6 | K73: =7.05806*Tabla10[[#This Row],[DIAS DE ALTA]] -> 42.34836 | L73: =IFERROR(VLOOKUP(Tabla10[[#This Row],[COD]],Carro!B:D,3,FALSE),"") -> 15 | M73: =IFERROR(VLOOKUP(Tabla10[[#This Row],[COD]],'Outros descontos'!B:P,15,FALSE),"") | N73: =(Tabla10[[#This Row],[HORAS TRABALHADAS]]*Tabla10[[#This Row],[TARIFA]]) - SUM(Tabla10[[#This Row],[ALOJAMENTO]], Tabla10[[#This Row],[IMPOSTO]], Tabla10[[#This Row],[CARRO]]) -> 574.65164
B74: LM | C74: =IF(D74="", "", INDEX(Colaboradores!A:A, MATCH(D74,Colaboradores!C:C, 0))) -> E0274 | D74: HECTOR GIOVANNI MORENO SUSA | E74: 46051 | G74: =IFERROR(VLOOKUP(Tabla10[[#This Row],[COD]],'TotalHorasAjustadas (2)'!D:L,8,FALSE),"") -> 19.5 | H74: 15 | I74: =IFERROR(VLOOKUP(Tabla10[[#This Row],[COD]],Alojamentos!B:P,11,FALSE),"") | J74: =IF(ISBLANK(Tabla10[[#This Row],[INICIO VINCULO]]), 0, MAX(0, MIN(IF(ISBLANK(Tabla10[[#This Row],[FIM VINCULO]]), DATE(2026,1,31), Tabla10[[#This Row],[FIM VINCULO]]), DATE(2026,1,31)) - MAX(Tabla10[[#This Row],[INICIO VINCULO]], DATE(2026,1,1)) + 1)) -> 3 | K74: =7.05806*Tabla10[[#This Row],[DIAS DE ALTA]] -> 21.17418 | L74: =IFERROR(VLOOKUP(Tabla10[[#This Row],[COD]],Carro!B:D,3,FALSE),"") | M74: =IFERROR(VLOOKUP(Tabla10[[#This Row],[COD]],'Outros descontos'!B:P,15,FALSE),"") | N74: =(Tabla10[[#This Row],[HORAS TRABALHADAS]]*Tabla10[[#This Row],[TARIFA]]) - SUM(Tabla10[[#This Row],[ALOJAMENTO]], Tabla10[[#This Row],[IMPOSTO]], Tabla10[[#This Row],[CARRO]]) -> 271.32582
B75: KR | C75: =IF(D75="", "", INDEX(Colaboradores!A:A, MATCH(D75,Colaboradores!C:C, 0))) -> E2083 | D75: HECTOR MANUEL BUELVAS ZAMBRANO | E75: 45751 | G75: 183.5 | H75: 15 | I75: =IFERROR(VLOOKUP(Tabla10[[#This Row],[COD]],Alojamentos!B:P,11,FALSE),"") -> 300 | J75: =IF(ISBLANK(Tabla10[[#This Row],[INICIO VINCULO]]), 0, MAX(0, MIN(IF(ISBLANK(Tabla10[[#This Row],[FIM VINCULO]]), DATE(2026,1,31), Tabla10[[#This Row],[FIM VINCULO]]), DATE(2026,1,31)) - MAX(Tabla10[[#This Row],[INICIO VINCULO]], DATE(2026,1,1)) + 1)) -> 31 | K75: =7.05806*Tabla10[[#This Row],[DIAS DE ALTA]] -> 218.79986 | L75: =IFERROR(VLOOKUP(Tabla10[[#This Row],[COD]],Carro!B:D,3,FALSE),"") | M75: =IFERROR(VLOOKUP(Tabla10[[#This Row],[COD]],'Outros descontos'!B:P,15,FALSE),"") | N75: =(Tabla10[[#This Row],[HORAS TRABALHADAS]]*Tabla10[[#This Row],[TARIFA]]) - SUM(Tabla10[[#This Row],[ALOJAMENTO]], Tabla10[[#This Row],[IMPOSTO]], Tabla10[[#This Row],[CARRO]]) -> 2233.7001
B76: KI | C76: =IF(D76="", "", INDEX(Colaboradores!A:A, MATCH(D76,Colaboradores!C:C, 0))) -> E0404 | D76: HEINER GONZALEZ ALAPE | E76: 45761 | F76: 46023 | G76: 0 | H76: 0 | I76: =IFERROR(VLOOKUP(Tabla10[[#This Row],[COD]],Alojamentos!B:P,11,FALSE),"") -> 300 | J76: =IF(ISBLANK(Tabla10[[#This Row],[INICIO VINCULO]]), 0, MAX(0, MIN(IF(ISBLANK(Tabla10[[#This Row],[FIM VINCULO]]), DATE(2026,1,31), Tabla10[[#This Row],[FIM VINCULO]]), DATE(2026,1,31)) - MAX(Tabla10[[#This Row],[INICIO VINCULO]], DATE(2026,1,1)) + 1)) -> 1 | K76: =7.05806*Tabla10[[#This Row],[DIAS DE ALTA]] -> 7.05806 | L76: =IFERROR(VLOOKUP(Tabla10[[#This Row],[COD]],Carro!B:D,3,FALSE),"") | M76: =IFERROR(VLOOKUP(Tabla10[[#This Row],[COD]],'Outros descontos'!B:P,15,FALSE),"") | N76: 0
B77: LM | C77: =IF(D77="", "", INDEX(Colaboradores!A:A, MATCH(D77,Colaboradores!C:C, 0))) -> E1306 | D77: HENRY ALEXANDER RAMIREZ | E77: 46052 | G77: 0 | H77: 15 | I77: =IFERROR(VLOOKUP(Tabla10[[#This Row],[COD]],Alojamentos!B:P,11,FALSE),"") -> 20 | J77: =IF(ISBLANK(Tabla10[[#This Row],[INICIO VINCULO]]), 0, MAX(0, MIN(IF(ISBLANK(Tabla10[[#This Row],[FIM VINCULO]]), DATE(2026,1,31), Tabla10[[#This Row],[FIM VINCULO]]), DATE(2026,1,31)) - MAX(Tabla10[[#This Row],[INICIO VINCULO]], DATE(2026,1,1)) + 1)) -> 2 | K77: =7.05806*Tabla10[[#This Row],[DIAS DE ALTA]] -> 14.11612 | L77: =IFERROR(VLOOKUP(Tabla10[[#This Row],[COD]],Carro!B:D,3,FALSE),"") | M77: =IFERROR(VLOOKUP(Tabla10[[#This Row],[COD]],'Outros descontos'!B:P,15,FALSE),"") | N77: 0
B78: WS | C78: =IF(D78="", "", INDEX(Colaboradores!A:A, MATCH(D78,Colaboradores!C:C, 0))) -> E0501 | D78: HERNAN RODRIGUEZ CUY | E78: 45896 | G78: 132.5 | H78: =IFERROR(VLOOKUP(Tabla10[[#This Row],[COD]],Tabla15[],4,FALSE),"") -> 15 | I78: =IFERROR(VLOOKUP(Tabla10[[#This Row],[COD]],Alojamentos!B:P,11,FALSE),"") | J78: =IF(ISBLANK(Tabla10[[#This Row],[INICIO VINCULO]]), 0, MAX(0, MIN(IF(ISBLANK(Tabla10[[#This Row],[FIM VINCULO]]), DATE(2026,1,31), Tabla10[[#This Row],[FIM VINCULO]]), DATE(2026,1,31)) - MAX(Tabla10[[#This Row],[INICIO VINCULO]], DATE(2026,1,1)) + 1)) -> 31 | K78: =7.05806*Tabla10[[#This Row],[DIAS DE ALTA]] -> 218.79986 | L78: =IFERROR(VLOOKUP(Tabla10[[#This Row],[COD]],Carro!B:D,3,FALSE),"") | M78: =IFERROR(VLOOKUP(Tabla10[[#This Row],[COD]],'Outros descontos'!B:P,15,FALSE),"") | N78: =(Tabla10[[#This Row],[HORAS TRABALHADAS]]*Tabla10[[#This Row],[TARIFA]]) - SUM(Tabla10[[#This Row],[ALOJAMENTO]], Tabla10[[#This Row],[IMPOSTO]], Tabla10[[#This Row],[CARRO]]) -> 1768.7001
B79: LM | C79: =IF(D79="", "", INDEX(Colaboradores!A:A, MATCH(D79,Colaboradores!C:C, 0))) -> E1958 | D79: HERNANDO ENRIQUE MAESTRE CASTILLA | E79: 45985 | G79: =IFERROR(VLOOKUP(Tabla10[[#This Row],[COD]],'TotalHorasAjustadas (2)'!D:L,8,FALSE),"") -> 152 | H79: =IFERROR(VLOOKUP(Tabla10[[#This Row],[COD]],Tabla15[],4,FALSE),"") -> 15 | I79: =IFERROR(VLOOKUP(Tabla10[[#This Row],[COD]],Alojamentos!B:P,11,FALSE),"") | J79: =IF(ISBLANK(Tabla10[[#This Row],[INICIO VINCULO]]), 0, MAX(0, MIN(IF(ISBLANK(Tabla10[[#This Row],[FIM VINCULO]]), DATE(2026,1,31), Tabla10[[#This Row],[FIM VINCULO]]), DATE(2026,1,31)) - MAX(Tabla10[[#This Row],[INICIO VINCULO]], DATE(2026,1,1)) + 1)) -> 31 | K79: =7.05806*Tabla10[[#This Row],[DIAS DE ALTA]] -> 218.79986 | L79: =IFERROR(VLOOKUP(Tabla10[[#This Row],[COD]],Carro!B:D,3,FALSE),"") -> 140 | M79: =IFERROR(VLOOKUP(Tabla10[[#This Row],[COD]],'Outros descontos'!B:P,15,FALSE),"") -> 53.16 | N79: =(Tabla10[[#This Row],[HORAS TRABALHADAS]]*Tabla10[[#This Row],[TARIFA]]) - SUM(Tabla10[[#This Row],[ALOJAMENTO]], Tabla10[[#This Row],[IMPOSTO]], Tabla10[[#This Row],[CARRO]],Tabla10[[#This Row],[OUTROS DEScontos]]) -> 1868.0401
B80: KR | C80: =IF(D80="", "", INDEX(Colaboradores!A:A, MATCH(D80,Colaboradores!C:C, 0))) -> E0112 | D80: JAHIR SURLEY DELGADO AGREDO | E80: 45751 | G80: =IFERROR(VLOOKUP(Tabla10[[#This Row],[COD]],'TotalHorasAjustadas (2)'!D:L,8,FALSE),"") -> 167 | H80: =IFERROR(VLOOKUP(Tabla10[[#This Row],[COD]],Tabla15[],4,FALSE),"") -> 15 | I80: =IFERROR(VLOOKUP(Tabla10[[#This Row],[COD]],Alojamentos!B:P,11,FALSE),"") | J80: =IF(ISBLANK(Tabla10[[#This Row],[INICIO VINCULO]]), 0, MAX(0, MIN(IF(ISBLANK(Tabla10[[#This Row],[FIM VINCULO]]), DATE(2026,1,31), Tabla10[[#This Row],[FIM VINCULO]]), DATE(2026,1,31)) - MAX(Tabla10[[#This Row],[INICIO VINCULO]], DATE(2026,1,1)) + 1)) -> 31 | K80: =7.05806*Tabla10[[#This Row],[DIAS DE ALTA]] -> 218.79986 | L80: =IFERROR(VLOOKUP(Tabla10[[#This Row],[COD]],Carro!B:D,3,FALSE),"") -> 89.52381 | M80: =IFERROR(VLOOKUP(Tabla10[[#This Row],[COD]],'Outros descontos'!B:P,15,FALSE),"") | N80: =(Tabla10[[#This Row],[HORAS TRABALHADAS]]*Tabla10[[#This Row],[TARIFA]]) - SUM(Tabla10[[#This Row],[ALOJAMENTO]], Tabla10[[#This Row],[IMPOSTO]], Tabla10[[#This Row],[CARRO]]) -> 2196.6763
B81: WS | C81: =IF(D81="", "", INDEX(Colaboradores!A:A, MATCH(D81,Colaboradores!C:C, 0))) -> E0419 | D81: JAIME ANTONIO PERTUZ VALDIRIS | E81: 45828 | G81: =IFERROR(VLOOKUP(Tabla10[[#This Row],[COD]],'TotalHorasAjustadas (2)'!D:L,8,FALSE),"") -> 203 | H81: =IFERROR(VLOOKUP(Tabla10[[#This Row],[COD]],Tabla15[],4,FALSE),"") -> 16 | I81: =IFERROR(VLOOKUP(Tabla10[[#This Row],[COD]],Alojamentos!B:P,11,FALSE),"") | J81: =IF(ISBLANK(Tabla10[[#This Row],[INICIO VINCULO]]), 0, MAX(0, MIN(IF(ISBLANK(Tabla10[[#This Row],[FIM VINCULO]]), DATE(2026,1,31), Tabla10[[#This Row],[FIM VINCULO]]), DATE(2026,1,31)) - MAX(Tabla10[[#This Row],[INICIO VINCULO]], DATE(2026,1,1)) + 1)) -> 31 | K81: =7.05806*Tabla10[[#This Row],[DIAS DE ALTA]] -> 218.79986 | L81: =IFERROR(VLOOKUP(Tabla10[[#This Row],[COD]],Carro!B:D,3,FALSE),"") | M81: =IFERROR(VLOOKUP(Tabla10[[#This Row],[COD]],'Outros descontos'!B:P,15,FALSE),"") | N81: =(Tabla10[[#This Row],[HORAS TRABALHADAS]]*Tabla10[[#This Row],[TARIFA]]) - SUM(Tabla10[[#This Row],[ALOJAMENTO]], Tabla10[[#This Row],[IMPOSTO]], Tabla10[[#This Row],[CARRO]]) -> 3029.2001
B82: WS | C82: =IF(D82="", "", INDEX(Colaboradores!A:A, MATCH(D82,Colaboradores!C:C, 0))) -> E0384 | D82: JAIVER JOSE POLANCO PEREZ | E82: 45939 | G82: =IFERROR(VLOOKUP(Tabla10[[#This Row],[COD]],'TotalHorasAjustadas (2)'!D:L,8,FALSE),"") -> 176 | H82: =IFERROR(VLOOKUP(Tabla10[[#This Row],[COD]],Tabla15[],4,FALSE),"") -> 15 | I82: =IFERROR(VLOOKUP(Tabla10[[#This Row],[COD]],Alojamentos!B:P,11,FALSE),"") -> 300 | J82: =IF(ISBLANK(Tabla10[[#This Row],[INICIO VINCULO]]), 0, MAX(0, MIN(IF(ISBLANK(Tabla10[[#This Row],[FIM VINCULO]]), DATE(2026,1,31), Tabla10[[#This Row],[FIM VINCULO]]), DATE(2026,1,31)) - MAX(Tabla10[[#This Row],[INICIO VINCULO]], DATE(2026,1,1)) + 1)) -> 31 | K82: =7.05806*Tabla10[[#This Row],[DIAS DE ALTA]] -> 218.79986 | L82: =IFERROR(VLOOKUP(Tabla10[[#This Row],[COD]],Carro!B:D,3,FALSE),"") | M82: =IFERROR(VLOOKUP(Tabla10[[#This Row],[COD]],'Outros descontos'!B:P,15,FALSE),"") | N82: =(Tabla10[[#This Row],[HORAS TRABALHADAS]]*Tabla10[[#This Row],[TARIFA]]) - SUM(Tabla10[[#This Row],[ALOJAMENTO]], Tabla10[[#This Row],[IMPOSTO]], Tabla10[[#This Row],[CARRO]]) -> 2121.2001
B83: LM | C83: =IF(D83="", "", INDEX(Colaboradores!A:A, MATCH(D83,Colaboradores!C:C, 0))) -> E0097 | D83: JEAN CARLO GARCIA GARCIA | E83: 45931 | G83: =IFERROR(VLOOKUP(Tabla10[[#This Row],[COD]],'TotalHorasAjustadas (2)'!D:L,8,FALSE),"") -> 183 | H83: =IFERROR(VLOOKUP(Tabla10[[#This Row],[COD]],Tabla15[],4,FALSE),"") -> 15 | I83: =IFERROR(VLOOKUP(Tabla10[[#This Row],[COD]],Alojamentos!B:P,11,FALSE),"") -> 300 | J83: =IF(ISBLANK(Tabla10[[#This Row],[INICIO VINCULO]]), 0, MAX(0, MIN(IF(ISBLANK(Tabla10[[#This Row],[FIM VINCULO]]), DATE(2026,1,31), Tabla10[[#This Row],[FIM VINCULO]]), DATE(2026,1,31)) - MAX(Tabla10[[#This Row],[INICIO VINCULO]], DATE(2026,1,1)) + 1)) -> 31 | K83: =7.05806*Tabla10[[#This Row],[DIAS DE ALTA]] -> 218.79986 | L83: =IFERROR(VLOOKUP(Tabla10[[#This Row],[COD]],Carro!B:D,3,FALSE),"") | M83: =IFERROR(VLOOKUP(Tabla10[[#This Row],[COD]],'Outros descontos'!B:P,15,FALSE),"") | N83: =(Tabla10[[#This Row],[HORAS TRABALHADAS]]*Tabla10[[#This Row],[TARIFA]]) - SUM(Tabla10[[#This Row],[ALOJAMENTO]], Tabla10[[#This Row],[IMPOSTO]], Tabla10[[#This Row],[CARRO]]) -> 2226.2001
B84: KR | C84: =IF(D84="", "", INDEX(Colaboradores!A:A, MATCH(D84,Colaboradores!C:C, 0))) -> E0398 | D84: JEFFERSON ANDRES OROZCO RODRIGUEZ | E84: 45764 | F84: 46052 | G84: =IFERROR(VLOOKUP(Tabla10[[#This Row],[COD]],'TotalHorasAjustadas (2)'!D:L,8,FALSE),"") -> 143 | H84: =IFERROR(VLOOKUP(Tabla10[[#This Row],[COD]],Tabla15[],4,FALSE),"") -> 14 | I84: =IFERROR(VLOOKUP(Tabla10[[#This Row],[COD]],Alojamentos!B:P,11,FALSE),"") -> 300 | J84: =IF(ISBLANK(Tabla10[[#This Row],[INICIO VINCULO]]), 0, MAX(0, MIN(IF(ISBLANK(Tabla10[[#This Row],[FIM VINCULO]]), DATE(2026,1,31), Tabla10[[#This Row],[FIM VINCULO]]), DATE(2026,1,31)) - MAX(Tabla10[[#This Row],[INICIO VINCULO]], DATE(2026,1,1)) + 1)) -> 30 | K84: =7.05806*Tabla10[[#This Row],[DIAS DE ALTA]] -> 211.7418 | L84: =IFERROR(VLOOKUP(Tabla10[[#This Row],[COD]],Carro!B:D,3,FALSE),"") | M84: =IFERROR(VLOOKUP(Tabla10[[#This Row],[COD]],'Outros descontos'!B:P,15,FALSE),"") | N84: =(Tabla10[[#This Row],[HORAS TRABALHADAS]]*Tabla10[[#This Row],[TARIFA]]) - SUM(Tabla10[[#This Row],[ALOJAMENTO]], Tabla10[[#This Row],[IMPOSTO]], Tabla10[[#This Row],[CARRO]]) -> 1490.2582
B85: KR | C85: =IF(D85="", "", INDEX(Colaboradores!A:A, MATCH(D85,Colaboradores!C:C, 0))) -> E0182 | D85: JEFFERSON ANDRES VALIENTE PEREZ | E85: 45820 | F85: 46052 | G85: =IFERROR(VLOOKUP(Tabla10[[#This Row],[COD]],'TotalHorasAjustadas (2)'!D:L,8,FALSE),"") -> 282 | H85: =IFERROR(VLOOKUP(Tabla10[[#This Row],[COD]],Tabla15[],4,FALSE),"") -> 15 | I85: =IFERROR(VLOOKUP(Tabla10[[#This Row],[COD]],Alojamentos!B:P,11,FALSE),"") | J85: =IF(ISBLANK(Tabla10[[#This Row],[INICIO VINCULO]]), 0, MAX(0, MIN(IF(ISBLANK(Tabla10[[#This Row],[FIM VINCULO]]), DATE(2026,1,31), Tabla10[[#This Row],[FIM VINCULO]]), DATE(2026,1,31)) - MAX(Tabla10[[#This Row],[INICIO VINCULO]], DATE(2026,1,1)) + 1)) -> 30 | K85: =7.05806*Tabla10[[#This Row],[DIAS DE ALTA]] -> 211.7418 | L85: =IFERROR(VLOOKUP(Tabla10[[#This Row],[COD]],Carro!B:D,3,FALSE),"") -> 104.44444 | M85: =IFERROR(VLOOKUP(Tabla10[[#This Row],[COD]],'Outros descontos'!B:P,15,FALSE),"") -> 100 | N85: =(Tabla10[[#This Row],[HORAS TRABALHADAS]]*Tabla10[[#This Row],[TARIFA]]) - SUM(Tabla10[[#This Row],[ALOJAMENTO]], Tabla10[[#This Row],[IMPOSTO]], Tabla10[[#This Row],[CARRO]],Tabla10[[#This Row],[OUTROS DEScontos]]) -> 3813.8138
B86: LM | C86: =IF(D86="", "", INDEX(Colaboradores!A:A, MATCH(D86,Colaboradores!C:C, 0))) -> E1662 | D86: JEFFERSON STEVEN CARBALIDO VIDALES | E86: 46028 | F86: 46036 | G86: 0 | H86: 15 | I86: =IFERROR(VLOOKUP(Tabla10[[#This Row],[COD]],Alojamentos!B:P,11,FALSE),"") | J86: =IF(ISBLANK(Tabla10[[#This Row],[INICIO VINCULO]]), 0, MAX(0, MIN(IF(ISBLANK(Tabla10[[#This Row],[FIM VINCULO]]), DATE(2026,1,31), Tabla10[[#This Row],[FIM VINCULO]]), DATE(2026,1,31)) - MAX(Tabla10[[#This Row],[INICIO VINCULO]], DATE(2026,1,1)) + 1)) -> 9 | K86: =7.05806*Tabla10[[#This Row],[DIAS DE ALTA]] -> 63.52254 | L86: =IFERROR(VLOOKUP(Tabla10[[#This Row],[COD]],Carro!B:D,3,FALSE),"") | M86: =IFERROR(VLOOKUP(Tabla10[[#This Row],[COD]],'Outros descontos'!B:P,15,FALSE),"") | N86: 0
B87: KI | C87: =IF(D87="", "", INDEX(Colaboradores!A:A, MATCH(D87,Colaboradores!C:C, 0))) -> E0148 | D87: JHESUAT EMANUEL DELGADO ALPALA | E87: 45761 | F87: 46023 | G87: 0 | H87: 0 | I87: =IFERROR(VLOOKUP(Tabla10[[#This Row],[COD]],Alojamentos!B:P,11,FALSE),"") | J87: =IF(ISBLANK(Tabla10[[#This Row],[INICIO VINCULO]]), 0, MAX(0, MIN(IF(ISBLANK(Tabla10[[#This Row],[FIM VINCULO]]), DATE(2026,1,31), Tabla10[[#This Row],[FIM VINCULO]]), DATE(2026,1,31)) - MAX(Tabla10[[#This Row],[INICIO VINCULO]], DATE(2026,1,1)) + 1)) -> 1 | K87: =7.05806*Tabla10[[#This Row],[DIAS DE ALTA]] -> 7.05806 | L87: =IFERROR(VLOOKUP(Tabla10[[#This Row],[COD]],Carro!B:D,3,FALSE),"") | M87: =IFERROR(VLOOKUP(Tabla10[[#This Row],[COD]],'Outros descontos'!B:P,15,FALSE),"") | N87: 0
B88: WS | C88: =IF(D88="", "", INDEX(Colaboradores!A:A, MATCH(D88,Colaboradores!C:C, 0))) -> E0029 | D88: JHOBERGS JESUS PARRA DE ARCO | E88: 45957 | G88: =IFERROR(VLOOKUP(Tabla10[[#This Row],[COD]],'TotalHorasAjustadas (2)'!D:L,8,FALSE),"") -> 158 | H88: =IFERROR(VLOOKUP(Tabla10[[#This Row],[COD]],Tabla15[],4,FALSE),"") -> 15 | I88: =IFERROR(VLOOKUP(Tabla10[[#This Row],[COD]],Alojamentos!B:P,11,FALSE),"") | J88: =IF(ISBLANK(Tabla10[[#This Row],[INICIO VINCULO]]), 0, MAX(0, MIN(IF(ISBLANK(Tabla10[[#This Row],[FIM VINCULO]]), DATE(2026,1,31), Tabla10[[#This Row],[FIM VINCULO]]), DATE(2026,1,31)) - MAX(Tabla10[[#This Row],[INICIO VINCULO]], DATE(2026,1,1)) + 1)) -> 31 | K88: =7.05806*Tabla10[[#This Row],[DIAS DE ALTA]] -> 218.79986 | L88: =IFERROR(VLOOKUP(Tabla10[[#This Row],[COD]],Carro!B:D,3,FALSE),"") | M88: =IFERROR(VLOOKUP(Tabla10[[#This Row],[COD]],'Outros descontos'!B:P,15,FALSE),"") | N88: =(Tabla10[[#This Row],[HORAS TRABALHADAS]]*Tabla10[[#This Row],[TARIFA]]) - SUM(Tabla10[[#This Row],[ALOJAMENTO]], Tabla10[[#This Row],[IMPOSTO]], Tabla10[[#This Row],[CARRO]]) -> 2151.2001
B89: KR | C89: =IF(D89="", "", INDEX(Colaboradores!A:A, MATCH(D89,Colaboradores!C:C, 0))) -> E0196 | D89: JHON ADAIMER MORALES MORALES | E89: 45764 | F89: 46053 | G89: =IFERROR(VLOOKUP(Tabla10[[#This Row],[COD]],'TotalHorasAjustadas (2)'!D:L,8,FALSE),"") -> 160 | H89: =IFERROR(VLOOKUP(Tabla10[[#This Row],[COD]],Tabla15[],4,FALSE),"") -> 13 | I89: =IFERROR(VLOOKUP(Tabla10[[#This Row],[COD]],Alojamentos!B:P,11,FALSE),"") -> 300 | J89: =IF(ISBLANK(Tabla10[[#This Row],[INICIO VINCULO]]), 0, MAX(0, MIN(IF(ISBLANK(Tabla10[[#This Row],[FIM VINCULO]]), DATE(2026,1,31), Tabla10[[#This Row],[FIM VINCULO]]), DATE(2026,1,31)) - MAX(Tabla10[[#This Row],[INICIO VINCULO]], DATE(2026,1,1)) + 1)) -> 31 | K89: =7.05806*Tabla10[[#This Row],[DIAS DE ALTA]] -> 218.79986 | L89: =IFERROR(VLOOKUP(Tabla10[[#This Row],[COD]],Carro!B:D,3,FALSE),"") | M89: =IFERROR(VLOOKUP(Tabla10[[#This Row],[COD]],'Outros descontos'!B:P,15,FALSE),"") | N89: =(Tabla10[[#This Row],[HORAS TRABALHADAS]]*Tabla10[[#This Row],[TARIFA]]) - SUM(Tabla10[[#This Row],[ALOJAMENTO]], Tabla10[[#This Row],[IMPOSTO]], Tabla10[[#This Row],[CARRO]]) -> 1561.2001
B90: WS | C90: =IF(D90="", "", INDEX(Colaboradores!A:A, MATCH(D90,Colaboradores!C:C, 0))) -> E0381 | D90: JHONNY ESTID QUIJANO TREJO | E90: 45922 | G90: =IFERROR(VLOOKUP(Tabla10[[#This Row],[COD]],'TotalHorasAjustadas (2)'!D:L,8,FALSE),"") -> 83 | H90: =IFERROR(VLOOKUP(Tabla10[[#This Row],[COD]],Tabla15[],4,FALSE),"") -> 15 | I90: =IFERROR(VLOOKUP(Tabla10[[#This Row],[COD]],Alojamentos!B:P,11,FALSE),"") | J90: =IF(ISBLANK(Tabla10[[#This Row],[INICIO VINCULO]]), 0, MAX(0, MIN(IF(ISBLANK(Tabla10[[#This Row],[FIM VINCULO]]), DATE(2026,1,31), Tabla10[[#This Row],[FIM VINCULO]]), DATE(2026,1,31)) - MAX(Tabla10[[#This Row],[INICIO VINCULO]], DATE(2026,1,1)) + 1)) -> 31 | K90: =7.05806*Tabla10[[#This Row],[DIAS DE ALTA]] -> 218.79986 | L90: =IFERROR(VLOOKUP(Tabla10[[#This Row],[COD]],Carro!B:D,3,FALSE),"") -> 50 | M90: =IFERROR(VLOOKUP(Tabla10[[#This Row],[COD]],'Outros descontos'!B:P,15,FALSE),"") | N90: =(Tabla10[[#This Row],[HORAS TRABALHADAS]]*Tabla10[[#This Row],[TARIFA]]) - SUM(Tabla10[[#This Row],[ALOJAMENTO]], Tabla10[[#This Row],[IMPOSTO]], Tabla10[[#This Row],[CARRO]]) -> 976.20014
B91: LM | C91: =IF(D91="", "", INDEX(Colaboradores!A:A, MATCH(D91,Colaboradores!C:C, 0))) -> E0547 | D91: JOHN MAURY LOPEZ SOCARRAS | E91: 46028 | F91: 46041 | G91: 0 | H91: =IFERROR(VLOOKUP(Tabla10[[#This Row],[COD]],Tabla15[],4,FALSE),"") -> 15 | I91: =IFERROR(VLOOKUP(Tabla10[[#This Row],[COD]],Alojamentos!B:P,11,FALSE),"") | J91: =IF(ISBLANK(Tabla10[[#This Row],[INICIO VINCULO]]), 0, MAX(0, MIN(IF(ISBLANK(Tabla10[[#This Row],[FIM VINCULO]]), DATE(2026,1,31), Tabla10[[#This Row],[FIM VINCULO]]), DATE(2026,1,31)) - MAX(Tabla10[[#This Row],[INICIO VINCULO]], DATE(2026,1,1)) + 1)) -> 14 | K91: =7.05806*Tabla10[[#This Row],[DIAS DE ALTA]] -> 98.81284 | L91: =IFERROR(VLOOKUP(Tabla10[[#This Row],[COD]],Carro!B:D,3,FALSE),"") | M91: =IFERROR(VLOOKUP(Tabla10[[#This Row],[COD]],'Outros descontos'!B:P,15,FALSE),"") | N91: 0
B92: KI | C92: =IF(D92="", "", INDEX(Colaboradores!A:A, MATCH(D92,Colaboradores!C:C, 0))) -> E0268 | D92: JOHNNY JAVIER BORJA MANGA | E92: 45695 | F92: 46052 | G92: =IFERROR(VLOOKUP(Tabla10[[#This Row],[COD]],'TotalHorasAjustadas (2)'!D:L,8,FALSE),"") -> 135 | H92: =IFERROR(VLOOKUP(Tabla10[[#This Row],[COD]],Tabla15[],4,FALSE),"") -> 15 | I92: =IFERROR(VLOOKUP(Tabla10[[#This Row],[COD]],Alojamentos!B:P,11,FALSE),"") -> 300 | J92: =IF(ISBLANK(Tabla10[[#This Row],[INICIO VINCULO]]), 0, MAX(0, MIN(IF(ISBLANK(Tabla10[[#This Row],[FIM VINCULO]]), DATE(2026,1,31), Tabla10[[#This Row],[FIM VINCULO]]), DATE(2026,1,31)) - MAX(Tabla10[[#This Row],[INICIO VINCULO]], DATE(2026,1,1)) + 1)) -> 30 | K92: =7.05806*Tabla10[[#This Row],[DIAS DE ALTA]] -> 211.7418 | L92: =IFERROR(VLOOKUP(Tabla10[[#This Row],[COD]],Carro!B:D,3,FALSE),"") | M92: =IFERROR(VLOOKUP(Tabla10[[#This Row],[COD]],'Outros descontos'!B:P,15,FALSE),"") | N92: =(Tabla10[[#This Row],[HORAS TRABALHADAS]]*Tabla10[[#This Row],[TARIFA]]) - SUM(Tabla10[[#This Row],[ALOJAMENTO]], Tabla10[[#This Row],[IMPOSTO]], Tabla10[[#This Row],[CARRO]]) -> 1513.2582
B93: LM | C93: =IF(D93="", "", INDEX(Colaboradores!A:A, MATCH(D93,Colaboradores!C:C, 0))) -> E0069 | D93: JONATAS HERTEL LOUZADA | E93: 45926 | G93: 160 | H93: =IFERROR(VLOOKUP(Tabla10[[#This Row],[COD]],Tabla15[],4,FALSE),"") -> 17.5 | I93: =IFERROR(VLOOKUP(Tabla10[[#This Row],[COD]],Alojamentos!B:P,11,FALSE),"") | J93: =IF(ISBLANK(Tabla10[[#This Row],[INICIO VINCULO]]), 0, MAX(0, MIN(IF(ISBLANK(Tabla10[[#This Row],[FIM VINCULO]]), DATE(2026,1,31), Tabla10[[#This Row],[FIM VINCULO]]), DATE(2026,1,31)) - MAX(Tabla10[[#This Row],[INICIO VINCULO]], DATE(2026,1,1)) + 1)) -> 31 | K93: =7.05806*Tabla10[[#This Row],[DIAS DE ALTA]] -> 218.79986 | L93: =IFERROR(VLOOKUP(Tabla10[[#This Row],[COD]],Carro!B:D,3,FALSE),"") | M93: =IFERROR(VLOOKUP(Tabla10[[#This Row],[COD]],'Outros descontos'!B:P,15,FALSE),"") | N93: =(Tabla10[[#This Row],[HORAS TRABALHADAS]]*Tabla10[[#This Row],[TARIFA]]) - SUM(Tabla10[[#This Row],[ALOJAMENTO]], Tabla10[[#This Row],[IMPOSTO]], Tabla10[[#This Row],[CARRO]]) -> 2581.2001
B94: WS | C94: =IF(D94="", "", INDEX(Colaboradores!A:A, MATCH(D94,Colaboradores!C:C, 0))) -> E0552 | D94: JONATHAN ALEJANDRO MARTINEZ CASTIBLANCO | E94: 45945 | G94: =IFERROR(VLOOKUP(Tabla10[[#This Row],[COD]],'TotalHorasAjustadas (2)'!D:L,8,FALSE),"") -> 268 | H94: =IFERROR(VLOOKUP(Tabla10[[#This Row],[COD]],Tabla15[],4,FALSE),"") -> 15 | I94: =IFERROR(VLOOKUP(Tabla10[[#This Row],[COD]],Alojamentos!B:P,11,FALSE),"") | J94: =IF(ISBLANK(Tabla10[[#This Row],[INICIO VINCULO]]), 0, MAX(0, MIN(IF(ISBLANK(Tabla10[[#This Row],[FIM VINCULO]]), DATE(2026,1,31), Tabla10[[#This Row],[FIM VINCULO]]), DATE(2026,1,31)) - MAX(Tabla10[[#This Row],[INICIO VINCULO]], DATE(2026,1,1)) + 1)) -> 31 | K94: =7.05806*Tabla10[[#This Row],[DIAS DE ALTA]] -> 218.79986 | L94: =IFERROR(VLOOKUP(Tabla10[[#This Row],[COD]],Carro!B:D,3,FALSE),"") -> 66.666667 | M94: =IFERROR(VLOOKUP(Tabla10[[#This Row],[COD]],'Outros descontos'!B:P,15,FALSE),"") -> 148.97 | N94: =(Tabla10[[#This Row],[HORAS TRABALHADAS]]*Tabla10[[#This Row],[TARIFA]]) - SUM(Tabla10[[#This Row],[ALOJAMENTO]], Tabla10[[#This Row],[IMPOSTO]], Tabla10[[#This Row],[CARRO]],Tabla10[[#This Row],[OUTROS DEScontos]]) -> 3585.5635
B95: KI | C95: =IF(D95="", "", INDEX(Colaboradores!A:A, MATCH(D95,Colaboradores!C:C, 0))) -> E0591 | D95: JONATHAN BLANDON HINCAPIE | E95: 45777 | F95: 46052 | G95: =IFERROR(VLOOKUP(Tabla10[[#This Row],[COD]],'TotalHorasAjustadas (2)'!D:L,8,FALSE),"") -> 179 | H95: =IFERROR(VLOOKUP(Tabla10[[#This Row],[COD]],Tabla15[],4,FALSE),"") -> 15 | I95: =IFERROR(VLOOKUP(Tabla10[[#This Row],[COD]],Alojamentos!B:P,11,FALSE),"") | J95: =IF(ISBLANK(Tabla10[[#This Row],[INICIO VINCULO]]), 0, MAX(0, MIN(IF(ISBLANK(Tabla10[[#This Row],[FIM VINCULO]]), DATE(2026,1,31), Tabla10[[#This Row],[FIM VINCULO]]), DATE(2026,1,31)) - MAX(Tabla10[[#This Row],[INICIO VINCULO]], DATE(2026,1,1)) + 1)) -> 30 | K95: =7.05806*Tabla10[[#This Row],[DIAS DE ALTA]] -> 211.7418 | L95: =IFERROR(VLOOKUP(Tabla10[[#This Row],[COD]],Carro!B:D,3,FALSE),"") | M95: =IFERROR(VLOOKUP(Tabla10[[#This Row],[COD]],'Outros descontos'!B:P,15,FALSE),"") | N95: =(Tabla10[[#This Row],[HORAS TRABALHADAS]]*Tabla10[[#This Row],[TARIFA]]) - SUM(Tabla10[[#This Row],[ALOJAMENTO]], Tabla10[[#This Row],[IMPOSTO]], Tabla10[[#This Row],[CARRO]]) -> 2473.2582
B96: KI | D96: JONATHAN DUBINSKI DA SILVA | E96: 45734 | G96: 160 | H96: 0 | I96: =IFERROR(VLOOKUP(Tabla10[[#This Row],[COD]],Alojamentos!B:P,11,FALSE),"") | J96: =IF(ISBLANK(Tabla10[[#This Row],[INICIO VINCULO]]), 0, MAX(0, MIN(IF(ISBLANK(Tabla10[[#This Row],[FIM VINCULO]]), DATE(2026,1,31), Tabla10[[#This Row],[FIM VINCULO]]), DATE(2026,1,31)) - MAX(Tabla10[[#This Row],[INICIO VINCULO]], DATE(2026,1,1)) + 1)) -> 31 | K96: 0 | L96: =IFERROR(VLOOKUP(Tabla10[[#This Row],[COD]],Carro!B:D,3,FALSE),"") | M96: =IFERROR(VLOOKUP(Tabla10[[#This Row],[COD]],'Outros descontos'!B:P,15,FALSE),"") | N96: 1423.58
B97: WS | C97: =IF(D97="", "", INDEX(Colaboradores!A:A, MATCH(D97,Colaboradores!C:C, 0))) -> E0585 | D97: JONATHAN FELACIO FISGATIVA | E97: 46010 | G97: =IFERROR(VLOOKUP(Tabla10[[#This Row],[COD]],'TotalHorasAjustadas (2)'!D:L,8,FALSE),"") -> 156 | H97: =IFERROR(VLOOKUP(Tabla10[[#This Row],[COD]],Tabla15[],4,FALSE),"") -> 15 | I97: =IFERROR(VLOOKUP(Tabla10[[#This Row],[COD]],Alojamentos!B:P,11,FALSE),"") | J97: =IF(ISBLANK(Tabla10[[#This Row],[INICIO VINCULO]]), 0, MAX(0, MIN(IF(ISBLANK(Tabla10[[#This Row],[FIM VINCULO]]), DATE(2026,1,31), Tabla10[[#This Row],[FIM VINCULO]]), DATE(2026,1,31)) - MAX(Tabla10[[#This Row],[INICIO VINCULO]], DATE(2026,1,1)) + 1)) -> 31 | K97: =7.05806*Tabla10[[#This Row],[DIAS DE ALTA]] -> 218.79986 | L97: =IFERROR(VLOOKUP(Tabla10[[#This Row],[COD]],Carro!B:D,3,FALSE),"") | M97: =IFERROR(VLOOKUP(Tabla10[[#This Row],[COD]],'Outros descontos'!B:P,15,FALSE),"") | N97: =(Tabla10[[#This Row],[HORAS TRABALHADAS]]*Tabla10[[#This Row],[TARIFA]]) - SUM(Tabla10[[#This Row],[ALOJAMENTO]], Tabla10[[#This Row],[IMPOSTO]], Tabla10[[#This Row],[CARRO]]) -> 2121.2001
B98: KI | C98: =IF(D98="", "", INDEX(Colaboradores!A:A, MATCH(D98,Colaboradores!C:C, 0))) -> E0164 | D98: JORGE ARLEY ALVAREZ GONZALEZ | E98: 45779 | F98: 46053 | G98: =IFERROR(VLOOKUP(Tabla10[[#This Row],[COD]],'TotalHorasAjustadas (2)'!D:L,8,FALSE),"") -> 199 | H98: =IFERROR(VLOOKUP(Tabla10[[#This Row],[COD]],Tabla15[],4,FALSE),"") -> 16 | I98: =IFERROR(VLOOKUP(Tabla10[[#This Row],[COD]],Alojamentos!B:P,11,FALSE),"") | J98: =IF(ISBLANK(Tabla10[[#This Row],[INICIO VINCULO]]), 0, MAX(0, MIN(IF(ISBLANK(Tabla10[[#This Row],[FIM VINCULO]]), DATE(2026,1,31), Tabla10[[#This Row],[FIM VINCULO]]), DATE(2026,1,31)) - MAX(Tabla10[[#This Row],[INICIO VINCULO]], DATE(2026,1,1)) + 1)) -> 31 | K98: =7.05806*Tabla10[[#This Row],[DIAS DE ALTA]] -> 218.79986 | L98: =IFERROR(VLOOKUP(Tabla10[[#This Row],[COD]],Carro!B:D,3,FALSE),"") | M98: =IFERROR(VLOOKUP(Tabla10[[#This Row],[COD]],'Outros descontos'!B:P,15,FALSE),"") | N98: =(Tabla10[[#This Row],[HORAS TRABALHADAS]]*Tabla10[[#This Row],[TARIFA]]) - SUM(Tabla10[[#This Row],[ALOJAMENTO]], Tabla10[[#This Row],[IMPOSTO]], Tabla10[[#This Row],[CARRO]]) -> 2965.2001
B99: WS | C99: =IF(D99="", "", INDEX(Colaboradores!A:A, MATCH(D99,Colaboradores!C:C, 0))) -> E0377 | D99: JOSE ANTONIO MORALES HURTADO | E99: 45939 | G99: =IFERROR(VLOOKUP(Tabla10[[#This Row],[COD]],'TotalHorasAjustadas (2)'!D:L,8,FALSE),"") -> 168 | H99: =IFERROR(VLOOKUP(Tabla10[[#This Row],[COD]],Tabla15[],4,FALSE),"") -> 15 | I99: =IFERROR(VLOOKUP(Tabla10[[#This Row],[COD]],Alojamentos!B:P,11,FALSE),"") -> 300 | J99: =IF(ISBLANK(Tabla10[[#This Row],[INICIO VINCULO]]), 0, MAX(0, MIN(IF(ISBLANK(Tabla10[[#This Row],[FIM VINCULO]]), DATE(2026,1,31), Tabla10[[#This Row],[FIM VINCULO]]), DATE(2026,1,31)) - MAX(Tabla10[[#This Row],[INICIO VINCULO]], DATE(2026,1,1)) + 1)) -> 31 | K99: =7.05806*Tabla10[[#This Row],[DIAS DE ALTA]] -> 218.79986 | L99: =IFERROR(VLOOKUP(Tabla10[[#This Row],[COD]],Carro!B:D,3,FALSE),"") | M99: =IFERROR(VLOOKUP(Tabla10[[#This Row],[COD]],'Outros descontos'!B:P,15,FALSE),"") | N99: =(Tabla10[[#This Row],[HORAS TRABALHADAS]]*Tabla10[[#This Row],[TARIFA]]) - SUM(Tabla10[[#This Row],[ALOJAMENTO]], Tabla10[[#This Row],[IMPOSTO]], Tabla10[[#This Row],[CARRO]]) -> 2001.2001
B100: WS | C100: =IF(D100="", "", INDEX(Colaboradores!A:A, MATCH(D100,Colaboradores!C:C, 0))) -> E0291 | D100: JOSE DAYNER ACOSTA LENIS | E100: 45945 | G100: =IFERROR(VLOOKUP(Tabla10[[#This Row],[COD]],'TotalHorasAjustadas (2)'!D:L,8,FALSE),"") -> 241 | H100: =IFERROR(VLOOKUP(Tabla10[[#This Row],[COD]],Tabla15[],4,FALSE),"") -> 15 | I100: =IFERROR(VLOOKUP(Tabla10[[#This Row],[COD]],Alojamentos!B:P,11,FALSE),"") -> 300 | J100: =IF(ISBLANK(Tabla10[[#This Row],[INICIO VINCULO]]), 0, MAX(0, MIN(IF(ISBLANK(Tabla10[[#This Row],[FIM VINCULO]]), DATE(2026,1,31), Tabla10[[#This Row],[FIM VINCULO]]), DATE(2026,1,31)) - MAX(Tabla10[[#This Row],[INICIO VINCULO]], DATE(2026,1,1)) + 1)) -> 31 | K100: =7.05806*Tabla10[[#This Row],[DIAS DE ALTA]] -> 218.79986 | L100: =IFERROR(VLOOKUP(Tabla10[[#This Row],[COD]],Carro!B:D,3,FALSE),"") | M100: =IFERROR(VLOOKUP(Tabla10[[#This Row],[COD]],'Outros descontos'!B:P,15,FALSE),"") -> 21.74 | N100: =(Tabla10[[#This Row],[HORAS TRABALHADAS]]*Tabla10[[#This Row],[TARIFA]]) - SUM(Tabla10[[#This Row],[ALOJAMENTO]], Tabla10[[#This Row],[IMPOSTO]], Tabla10[[#This Row],[CARRO]]) -> 3096.2001
...

Sheet TotalHorasAjustadas (2)
A1: Cliente | B1: Empresa | C1: Funcion | D1: COD_colab | E1: Trabalhador | F1: Periodo_fat | G1: Total_Horas | H1: Dias_lancados | I1: Soma_qtd_hrs_old | J1: Soma_Qtd_hrs | K1: Total_Horas_Ajustado | L1: Dif_Horas
A2: 105-INGENIERIA PARA EL DESAROLLO TECNOLOGICO | B2: KOTRIK | C2: SOLDADOR TIG (GTAW) | D2: E1512 | E2: JOIN VILLEGAS | F2: 46023 | G2: 216 | H2: 31 | I2: 0 | J2: 0 | K2: 216 | L2: 0
A3: 105-INGENIERIA PARA EL DESAROLLO TECNOLOGICO | B3: KOTRIK | C3: SOLDADOR ELECTRODO (SMAW) | D3: E0354 | E3: SANTIAGO CELU YUBYINER | F3: 46023 | G3: 252 | H3: 31 | I3: 0 | J3: 0 | K3: 252 | L3: 0
A4: 148-MONTAJES GOMUR S.L | B4: KOTRIK | C4: CALDERERO / SOLDADOR (MIG-MAG) | D4: E1800 | E4: PABLO MANOLO ROMERO HUERTAS | F4: 46023 | G4: 208 | H4: 31 | I4: 0 | J4: 0 | K4: 208 | L4: 0
A5: 148-MONTAJES GOMUR S.L | B5: KOTRIK | C5: SOLDADOR ELECTRODO (SMAW) | D5: E0475 | E5: VICTOR GALVEZ PALACIOS | F5: 46023 | G5: 203 | H5: 31 | I5: 0 | J5: 0 | K5: 203 | L5: 0
A6: 148-MONTAJES GOMUR S.L | B6: KOTRIK | C6: SOLDADOR ELECTRODO (SMAW) | D6: E0474 | E6: ZEVALLOS BENITES JOSUE | F6: 46023 | G6: 173 | H6: 31 | I6: 0 | J6: 0 | K6: 173 | L6: 0
A7: 191-TALLERES LANDALICE SA | B7: KOTRIK | C7: SOLDADOR ELECTRODO (SMAW) | D7: E1359 | E7: LUIZ GUILHERME AMARAL ALVES | F7: 46023 | G7: 48 | H7: 31 | I7: 8 | J7: 2 | K7: 42 | L7: -6
A8: 203-TECNOLOGIA MECANICA I ELECTRA SLU | B8: KOTRIK | C8: SOLDADOR ELECTRODO (SMAW) | D8: E0592 | E8: DARWIN JOSE VASQUEZ ORTEGA | F8: 46023 | G8: 191.25 | H8: 31 | I8: 0 | J8: 0 | K8: 191.25 | L8: 0
A9: 203-TECNOLOGIA MECANICA I ELECTRA SLU | B9: KOTRIK | C9: SOLDADOR ELECTRODO (SMAW) | D9: E0591 | E9: JONATHAN BLANDON HINCAPIE | F9: 46023 | G9: 179 | H9: 31 | I9: 0 | J9: 0 | K9: 179 | L9: 0
A10: 225-CARVISA CONTAINER SLU | B10: KOTRIK | C10: SOLDADOR ELECTRODO (SMAW) | D10: E0001590 | E10: BAIRON BURBANO | F10: 46023 | G10: 142 | H10: 31 | I10: 0 | J10: 0 | K10: 142 | L10: 0
A11: 225-CARVISA CONTAINER SLU | B11: KOTRIK | C11: SOLDADOR ELECTRODO (SMAW) | D11: E0873 | E11: ELKIN GARZON LOPEZ | F11: 46023 | G11: 132 | H11: 31 | I11: 0 | J11: 0 | K11: 132 | L11: 0
A12: 225-CARVISA CONTAINER SLU | B12: KOTRIK | C12: SOLDADOR ELECTRODO (SMAW) | D12: E0890 | E12: FABIAN CERÓN | F12: 46023 | G12: 136 | H12: 31 | I12: 0 | J12: 0 | K12: 136 | L12: 0
A13: 30-CALDENOR | B13: KOTRIK | C13: SOLDADOR ELECTRODO (SMAW) | D13: E1895 | E13: DAMIAN ZAMBRANO | F13: 46023 | G13: 142 | H13: 31 | I13: 0 | J13: 0 | K13: 142 | L13: 0
A14: 30-CALDENOR | B14: KOTRIK | C14: SOLDADOR ELECTRODO (SMAW) | D14: E0125 | E14: EVALIO ANGULO | F14: 46023 | G14: 142 | H14: 31 | I14: 0 | J14: 0 | K14: 142 | L14: 0
A15: 30-CALDENOR | B15: KOTRIK | D15: E1415 | E15: JHON EINER INSUASTI TULANDE | F15: 46023 | G15: 142 | H15: 31 | I15: 0 | J15: 0 | K15: 142 | L15: 0
A16: 30-CALDENOR | B16: KOTRIK | C16: SOLDADOR MIG-MAG / ELECTRODO (GMAW / SMAW) | D16: E1818 | E16: WILBER LOPEZ BALETA | F16: 46023 | G16: 133 | H16: 31 | I16: 0 | J16: 0 | K16: 133 | L16: 0
A17: 42-CALDESOL | B17: KOTRIK | C17: SOLDADOR ELECTRODO (SMAW) | D17: E0146 | E17: JESUS CARDENAS RIVERA | F17: 46023 | G17: 354 | H17: 62 | I17: 0 | J17: 0 | K17: 354 | L17: 0
A18: 43-CAM IMPIANTI INDUSTRIALI SRL | B18: KOTRIK | C18: TUBERO | D18: E0166 | E18: ALVARO ROJAS | F18: 46023 | G18: 144 | H18: 31 | I18: 0 | J18: 0 | K18: 144 | L18: 0
A19: 43-CAM IMPIANTI INDUSTRIALI SRL | B19: KOTRIK | C19: TUBERO | D19: E0155 | E19: CARLOS A. RAMOS Q. | F19: 46023 | G19: 225 | H19: 31 | I19: 0 | J19: 0 | K19: 225 | L19: 0
A20: 43-CAM IMPIANTI INDUSTRIALI SRL | B20: KOTRIK | C20: AYUDANTE | D20: E0152 | E20: CARLOS ADRIAN CAMELO CALDERON | F20: 46023 | G20: 161 | H20: 31 | I20: 0 | J20: 0 | K20: 161 | L20: 0
A21: 43-CAM IMPIANTI INDUSTRIALI SRL | B21: KOTRIK | C21: SOLDADOR ELECTRODO (SMAW) | D21: E0161 | E21: EDILBERTO DOMINGUEZ | F21: 46023 | G21: 215 | H21: 31 | I21: 16 | J21: 0 | K21: 199 | L21: -16
A22: 43-CAM IMPIANTI INDUSTRIALI SRL | B22: KOTRIK | C22: SOLDADOR ELECTRODO (SMAW) | D22: E0151 | E22: GUILLERMO POSADA | F22: 46023 | G22: 215 | H22: 31 | I22: 0 | J22: 10 | K22: 225 | L22: 10
A23: 43-CAM IMPIANTI INDUSTRIALI SRL | B23: KOTRIK | C23: AYUDANTE | D23: E2070 | E23: HENÁN QUINTERO JARAMILLO | F23: 46023 | G23: 146 | H23: 31 | I23: 0 | J23: 0 | K23: 146 | L23: 0
A24: 43-CAM IMPIANTI INDUSTRIALI SRL | B24: KOTRIK | C24: SOLDADOR ELECTRODO (SMAW) | D24: E0123 | E24: JIM PAUL CHUNGA LUJAN | F24: 46023 | G24: 199 | H24: 31 | I24: 0 | J24: 0 | K24: 199 | L24: 0
A25: 43-CAM IMPIANTI INDUSTRIALI SRL | B25: KOTRIK | C25: TUBERO | D25: E0034 | E25: JORDY ALEXADER ALVA PAYAC | F25: 46023 | G25: 199 | H25: 31 | I25: 10 | J25: 7 | K25: 196 | L25: -3
A26: 43-CAM IMPIANTI INDUSTRIALI SRL | B26: KOTRIK | C26: SOLDADOR ELECTRODO (SMAW) | D26: E0164 | E26: JORGE ARLEY ALVAREZ GONZALEZ | F26: 46023 | G26: 199 | H26: 31 | I26: 0 | J26: 0 | K26: 199 | L26: 0
A27: 43-CAM IMPIANTI INDUSTRIALI SRL | B27: KOTRIK | C27: TUBERO | D27: E0163 | E27: JOSE DE JESUS MENDOZA | F27: 46023 | G27: 162 | H27: 31 | I27: 0 | J27: 0 | K27: 162 | L27: 0
A28: 43-CAM IMPIANTI INDUSTRIALI SRL | B28: KOTRIK | C28: AYUDANTE | D28: E1751 | E28: NELSON JAIME PITRE CASTILLA | F28: 46023 | G28: 147 | H28: 31 | I28: 0 | J28: 0 | K28: 147 | L28: 0
A29: 43-CAM IMPIANTI INDUSTRIALI SRL | B29: KOTRIK | D29: E1426 | E29: RENZO CHUNGA LUJAN | F29: 46023 | G29: 199 | H29: 31 | I29: 0 | J29: 0 | K29: 199 | L29: 0
A30: 43-CAM IMPIANTI INDUSTRIALI SRL | B30: KOTRIK | C30: TUBERO | D30: E0116 | E30: ROGER HALDER CHILCA LEON | F30: 46023 | G30: 180 | H30: 31 | I30: 0 | J30: 0 | K30: 180 | L30: 0
A31: 43-CAM IMPIANTI INDUSTRIALI SRL | B31: KOTRIK | C31: TUBERO | D31: E0036 | E31: ROLANDO CATUNTA M. | F31: 46023 | G31: 199 | H31: 31 | I31: 0 | J31: 0 | K31: 199 | L31: 0
A32: 43-CAM IMPIANTI INDUSTRIALI SRL | B32: KOTRIK | C32: SOLDADOR TIG / ELECTRODO (GTAW / SMAW) | D32: E0600 | E32: STIVEN PENAGOS | F32: 46023 | G32: 225 | H32: 31 | I32: 0 | J32: 0 | K32: 225 | L32: 0
A33: 43-CAM IMPIANTI INDUSTRIALI SRL | B33: KOTRIK | C33: SOLDADOR ELECTRODO (SMAW) | D33: E0296 | E33: WILMER YANAYACO | F33: 46023 | G33: 188 | H33: 31 | I33: 0 | J33: 0 | K33: 188 | L33: 0
A34: 43-CAM IMPIANTI INDUSTRIALI SRL | B34: KOTRIK | C34: TUBERO | D34: E1788 | E34: YANNY ALBERTO HERNANDEZ LOZANO | F34: 46023 | G34: 235 | H34: 31 | I34: 10 | J34: 0 | K34: 225 | L34: -10
A35: 43-CAM IMPIANTI INDUSTRIALI SRL | B35: KOTRIK | C35: TUBERO | D35: E0032 | E35: YOBER HUAMAN VELASQUEZ | F35: 46023 | G35: 144 | H35: 31 | I35: 0 | J35: 0 | K35: 144 | L35: 0
A36: 71-ELYTT ENERGY | B36: KOTRIK | C36: SOLDADOR ELECTRODO (SMAW) | D36: E0615 | E36: EDILSON FIERRO | F36: 46023 | G36: 227 | H36: 31 | I36: 0 | J36: 0 | K36: 227 | L36: 0
A37: 71-ELYTT ENERGY | B37: KOTRIK | C37: SOLDADOR ELECTRODO (SMAW) | D37: E0237 | E37: FREDY JAVIER CCALLA ROJAS | F37: 46023 | G37: 248 | H37: 31 | I37: 0 | J37: 0 | K37: 248 | L37: 0
A38: 71-ELYTT ENERGY | B38: KOTRIK | C38: SOLDADOR ELECTRODO (SMAW) | D38: E0240 | E38: HECTOR LUIS PARRAGA ZAVALA | F38: 46023 | G38: 252 | H38: 31 | I38: 0 | J38: 0 | K38: 252 | L38: 0
A39: 71-ELYTT ENERGY | B39: KOTRIK | C39: SOLDADOR ELECTRODO (SMAW) | D39: E0238 | E39: ISRAEL BENAVIDES PRECIADO | F39: 46023 | G39: 276 | H39: 31 | I39: 0 | J39: 0 | K39: 276 | L39: 0
A40: 71-ELYTT ENERGY | B40: KOTRIK | D40: E1416 | E40: JHON JAIRO MUÑOZ BARBOSA | F40: 46023 | G40: 307 | H40: 31 | I40: 0 | J40: 0 | K40: 307 | L40: 0
A41: 84-GRUPO LOAFA | B41: KOTRIK | C41: SOLDADOR ELECTRODO (SMAW) | D41: E0277 | E41: CAMILO ANDRES VALERO PEREZ | F41: 46023 | G41: 201 | H41: 31 | I41: 0 | J41: 0 | K41: 201 | L41: 0
A42: 119-LASAFE SLU | B42: LUMINOUS | C42: SOLDADOR ELECTRODO (SMAW) | D42: E0406 | E42: ALAN GERSON RAMIREZ ACARO | F42: 46023 | G42: 157 | H42: 31 | I42: 0 | J42: 0 | K42: 157 | L42: 0
A43: 119-LASAFE SLU | B43: LUMINOUS | C43: CALDERERO MONTADOR | D43: E1813 | E43: LEONARDO RIOS CORREA | F43: 46023 | G43: 164 | H43: 31 | I43: 0 | J43: 0 | K43: 164 | L43: 0
A44: 119-LASAFE SLU | B44: LUMINOUS | C44: SOLDADOR ELECTRODO (SMAW) | D44: E0405 | E44: YULDOR MAURICIO BOLAÑOS | F44: 46023 | G44: 157 | H44: 31 | I44: 0 | J44: 0 | K44: 157 | L44: 0
A45: 130-MEN MONTAJES INDUSTRIALES | B45: LUMINOUS | C45: TUBERO | D45: E1673 | E45: CRISTIAN CAMILO CABALLERO CORREDOR | F45: 46023 | G45: 188.4 | H45: 31 | I45: 0 | J45: 0 | K45: 188.4 | L45: 0
A46: 130-MEN MONTAJES INDUSTRIALES | B46: LUMINOUS | C46: SOLDADOR ELECTRODO (SMAW) | D46: E0424 | E46: ENRI JAIME CALDAS BERMUDES | F46: 46023 | G46: 190.06 | H46: 31 | I46: 0 | J46: 0 | K46: 190.06 | L46: 0
A47: 130-MEN MONTAJES INDUSTRIALES | B47: LUMINOUS | C47: SOLDADOR TIG (GTAW) | D47: E2056 | E47: FABIAN ORLANDO VARGAS RIOS | F47: 46023 | G47: 184.73 | H47: 31 | I47: 0 | J47: 0 | K47: 184.73 | L47: 0
A48: 130-MEN MONTAJES INDUSTRIALES | B48: LUMINOUS | C48: SOLDADOR ELECTRODO (SMAW) | D48: E0429 | E48: FABIO LUJAN | F48: 46023 | G48: 176.56 | H48: 31 | I48: 0 | J48: 0 | K48: 176.56 | L48: 0
A49: 130-MEN MONTAJES INDUSTRIALES | B49: LUMINOUS | C49: SOLDADOR ELECTRODO (SMAW) | D49: E0300 | E49: HERNAN ALEJANDRO TARAZONA | F49: 46023 | G49: 188.4 | H49: 31 | I49: 0 | J49: 0 | K49: 188.4 | L49: 0
A50: 130-MEN MONTAJES INDUSTRIALES | B50: LUMINOUS | C50: SOLDADOR ELECTRODO (SMAW) | D50: E0426 | E50: JUAN ALBERTO RODRÍGUEZ | F50: 46023 | G50: 178 | H50: 31 | I50: 0 | J50: 0 | K50: 178 | L50: 0
A51: 130-MEN MONTAJES INDUSTRIALES | B51: LUMINOUS | C51: SOLDADOR ELECTRODO (SMAW) | D51: E0425 | E51: KEVIN FRANKLYN LESCANO REYES | F51: 46023 | G51: 178.73 | H51: 31 | I51: 0 | J51: 0 | K51: 178.73 | L51: 0
A52: 130-MEN MONTAJES INDUSTRIALES | B52: LUMINOUS | C52: SOLDADOR ELECTRODO (SMAW) | D52: E0147 | E52: MAURICIO TORO RAMIREZ | F52: 46023 | G52: 180.73 | H52: 31 | I52: 0 | J52: 0 | K52: 180.73 | L52: 0
... A157: 621-TALLERES METALICOS LEZIAGA S.L.U | B157: LUMINOUS | C157: SOLDADOR ELECTRODO (SMAW) | D157: E0274 | E157: HECTOR GIOVANNI MORENO SUSA | F157: 46023 | G157: 19.5 | H157: 31 | I157: 0 | J157: 0 | K157: 19.5 | L157: 0
A158: 621-TALLERES METALICOS LEZIAGA S.L.U | B158: LUMINOUS | D158: E0503 | E158: RODRIGO AVILA | F158: 46023 | G158: 19.5 | H158: 31 | I158: 0 | J158: 0 | K158: 19.5 | L158: 0
A159: 76-ERBIA SL | B159: LUMINOUS | C159: SOLDADOR ELECTRODO (SMAW) | D159: E0250 | E159: BORIS ALI CHUNGA LUJÁN | F159: 46023 | G159: 196.55 | H159: 31 | I159: 0 | J159: 0 | K159: 196.55 | L159: 0
A160: 76-ERBIA SL | B160: LUMINOUS | C160: SOLDADOR ELECTRODO (SMAW) | D160: E0251 | E160: HAROLD SERNAQUE | F160: 46023 | G160: 188.5 | H160: 31 | I160: 0 | J160: 0 | K160: 188.5 | L160: 0
A161: 111-IQUORD | B161: ROSAS | C161: SOLDADOR ELECTRODO (SMAW) | D161: E0398 | E161: ANDRES OROZCO | F161: 46023 | G161: 143 | H161: 31 | I161: 0 | J161: 0 | K161: 143 | L161: 0
A162: 111-IQUORD | B162: ROSAS | C162: SOLDADOR ELECTRODO (SMAW) | D162: E0396 | E162: CARLOS JIMENEZ | F162: 46023 | G162: 143 | H162: 31 | I162: 0 | J162: 0 | K162: 143 | L162: 0
A163: 111-IQUORD | B163: ROSAS | C163: SOLDADOR ELECTRODO (SMAW) | D163: E0394 | E163: FREDY MANCERA | F163: 46023 | G163: 143 | H163: 31 | I163: 0 | J163: 0 | K163: 143 | L163: 0
A164: 111-IQUORD | B164: ROSAS | C164: SOLDADOR ELECTRODO (SMAW) | D164: E1435 | E164: JAVIER BALDOVINO | F164: 46023 | G164: 136 | H164: 31 | I164: 0 | J164: 0 | K164: 136 | L164: 0
A165: 111-IQUORD | B165: ROSAS | C165: SOLDADOR ELECTRODO (SMAW) | D165: E0395 | E165: JUAN C BENAVIDES R | F165: 46023 | G165: 143 | H165: 31 | I165: 0 | J165: 0 | K165: 143 | L165: 0
A166: 111-IQUORD | B166: ROSAS | C166: SOLDADOR ELECTRODO (SMAW) | D166: E0392 | E166: MILTON SOSA | F166: 46023 | G166: 143 | H166: 31 | I166: 0 | J166: 0 | K166: 143 | L166: 0
A167: 111-IQUORD | B167: ROSAS | C167: SOLDADOR ELECTRODO (SMAW) | D167: E0400 | E167: NORBEY VARON ESQUIVEL | F167: 46023 | G167: 143 | H167: 31 | I167: 0 | J167: 0 | K167: 143 | L167: 0
A168: 111-IQUORD | B168: ROSAS | C168: SOLDADOR ELECTRODO (SMAW) | D168: E0393 | E168: VICTOR BLANCO BRAVO | F168: 46023 | G168: 135 | H168: 31 | I168: 0 | J168: 0 | K168: 135 | L168: 0
A169: 136-METALLIC SOLUTIONS | B169: ROSAS | D169: E1701 | E169: JAIRO MUÑOZ | F169: 46023 | G169: 148 | H169: 31 | I169: 0 | J169: 0 | K169: 148 | L169: 0
A170: 136-METALLIC SOLUTIONS | B170: ROSAS | C170: MONTADOR (ARMADOR) / SOLDADOR (MIG-MAG / ELECTRODO) | D170: E1547 | E170: JULIO CESAR MANJARRES | F170: 46023 | G170: 170 | H170: 31 | I170: 0 | J170: 0 | K170: 170 | L170: 0
A171: 136-METALLIC SOLUTIONS | B171: ROSAS | C171: SOLDADOR ELECTRODO (SMAW) | D171: E0447 | E171: NORBEY BALLESTEROS | F171: 46023 | G171: 161 | H171: 31 | I171: 0 | J171: 0 | K171: 161 | L171: 0
A172: 136-METALLIC SOLUTIONS | B172: ROSAS | C172: SOLDADOR ELECTRODO (SMAW) | D172: E0445 | E172: SERGIO ANDRES LANDINES B | F172: 46023 | G172: 154.5 | H172: 31 | I172: 0 | J172: 0 | K172: 154.5 | L172: 0
A173: 136-METALLIC SOLUTIONS | B173: ROSAS | C173: SOLDADOR ELECTRODO (SMAW) | D173: E0446 | E173: SERGIO CORDOBA T | F173: 46023 | G173: 161 | H173: 31 | I173: 0 | J173: 0 | K173: 161 | L173: 0
A174: 158-PMA ESTRUCTURAS | B174: ROSAS | C174: SOLDADOR ELECTRODO (SMAW) | D174: E0491 | E174: CARLOS MARIO JARAMILLO LOPEZ | F174: 46023 | G174: 151.5 | H174: 31 | I174: 0 | J174: 0 | K174: 151.5 | L174: 0
A175: 158-PMA ESTRUCTURAS | B175: ROSAS | C175: SOLDADOR ELECTRODO (SMAW) | D175: E0492 | E175: JHON FREDY CASTRO JIMENEZ | F175: 46023 | G175: 114 | H175: 31 | I175: 0 | J175: 0 | K175: 114 | L175: 0
A176: 176-SISTEMAS DE FILTRADO Y TRATAMIENTO DE FLUIDOS S.L | B176: ROSAS | C176: SOLDADOR ELECTRODO (SMAW) | D176: E0553 | E176: CARLOS JULIO ACOSTA | F176: 46023 | G176: 170 | H176: 31 | I176: 0 | J176: 0 | K176: 170 | L176: 0
A177: 188-TALLERES BAMA | B177: ROSAS | C177: SOLDADOR ELECTRODO (SMAW) | D177: E0558 | E177: BREIDIS CARDOZO | F177: 46023 | G177: 194 | H177: 31 | I177: 0 | J177: 0 | K177: 194 | L177: 0
A178: 205-TOKIO METAL SL | B178: ROSAS | C178: SOLDADOR ELECTRODO (SMAW) | D178: E0593 | E178: ALEXANDRICO CARDONA RAMIREZ | F178: 46023 | G178: 150 | H178: 31 | I178: 0 | J178: 0 | K178: 150 | L178: 0
A179: 218-INAGAL SOLDADURA SL | B179: ROSAS | D179: E1407 | E179: CARLOS MANTILLA | F179: 46023 | G179: 132.28 | H179: 31 | I179: 0 | J179: 0 | K179: 132.28 | L179: 0
A180: 218-INAGAL SOLDADURA SL | B180: ROSAS | D180: E1423 | E180: LENNIN JESUS CANON C. | F180: 46023 | G180: 124.45 | H180: 31 | I180: 0 | J180: 0 | K180: 124.45 | L180: 0
A181: 218-INAGAL SOLDADURA SL | B181: ROSAS | D181: E1424 | E181: PEDRO DE LA HOZ SALCEDO | F181: 46023 | G181: 121.62 | H181: 31 | I181: 0 | J181: 0 | K181: 121.62 | L181: 0
A182: 218-INAGAL SOLDADURA SL | B182: ROSAS | D182: E1436 | E182: RIGOBERTO ROMERO REINA | F182: 46023 | G182: 127.21 | H182: 31 | I182: 0 | J182: 0 | K182: 127.21 | L182: 0
A183: 224-BEKOTER INSTALACIONES INDUSTRIALES SL | B183: ROSAS | D183: E1287 | E183: ACEVEDO GUZMÁN ORLANDO | F183: 46023 | G183: 238 | H183: 31 | I183: 0 | J183: 0 | K183: 238 | L183: 0
A184: 224-BEKOTER INSTALACIONES INDUSTRIALES SL | B184: ROSAS | C184: SOLDADOR ELECTRODO (SMAW) | D184: E0045 | E184: VICTOR TUANAMA GARCIA | F184: 46023 | G184: 238 | H184: 31 | I184: 0 | J184: 0 | K184: 238 | L184: 0
A185: 25-BIANNA RECYCLING | B185: ROSAS | D185: E0106 | E185: EDU PANDURO | F185: 46023 | G185: 173 | H185: 31 | I185: 10 | J185: 10 | K185: 172.5 | L185: 0
A186: 25-BIANNA RECYCLING | B186: ROSAS | C186: SOLDADOR ELECTRODO (SMAW) | D186: E0107 | E186: EDUARDO JOSÉ RUSSO LINERO | F186: 46023 | G186: 173 | H186: 31 | I186: 0 | J186: 0 | K186: 173 | L186: 0
A187: 25-BIANNA RECYCLING | B187: ROSAS | C187: CALDERERO MONTADOR | D187: E0104 | E187: GILBER MORA | F187: 46023 | G187: 173 | H187: 31 | I187: 0 | J187: 0 | K187: 173 | L187: 0
A188: 25-BIANNA RECYCLING | B188: ROSAS | D188: E0103 | E188: HECTOR BUELVAS | F188: 46023 | G188: 183.5 | H188: 31 | I188: 0 | J188: 0 | K188: 183.5 | L188: 0
A189: 25-BIANNA RECYCLING | B189: ROSAS | C189: SOLDADOR ELECTRODO (SMAW) | D189: E0112 | E189: JAHIR DELGADO | F189: 46023 | G189: 158 | H189: 31 | I189: 6 | J189: 15 | K189: 167 | L189: 9
A190: 25-BIANNA RECYCLING | B190: ROSAS | C190: SOLDADOR ELECTRODO (SMAW) | D190: E0108 | E190: JHON FREDY PEREZ | F190: 46023 | G190: 167 | H190: 31 | I190: 10 | J190: 7 | K190: 164 | L190: -3
A191: 25-BIANNA RECYCLING | B191: ROSAS | C191: MECÁNICO INDUSTRIAL | D191: E1543 | E191: JUAN VILLANUEVA DE LA HOZ | F191: 46023 | G191: 170 | H191: 31 | I191: 0 | J191: 0 | K191: 170 | L191: 0
A192: 25-BIANNA RECYCLING | B192: ROSAS | C192: SOLDADOR ELECTRODO (SMAW) | D192: E0105 | E192: JUAN VILLANUEVA GALVIS | F192: 46023 | G192: 167 | H192: 31 | I192: 0 | J192: 0 | K192: 167 | L192: 0
A193: 25-BIANNA RECYCLING | B193: ROSAS | C193: SOLDADOR ELECTRODO (SMAW) | D193: E0111 | E193: XEMIR SOLER ROMERO | F193: 46023 | G193: 137 | H193: 31 | I193: 0 | J193: 0 | K193: 137 | L193: 0
A194: 60-CORDOBA S.L | B194: ROSAS | C194: SOLDADOR ELECTRODO (SMAW) | D194: E0180 | E194: EDWIN F. LINARES | F194: 46023 | G194: 253 | H194: 31 | I194: 0 | J194: 0 | K194: 253 | L194: 0
A195: 60-CORDOBA S.L | B195: ROSAS | C195: SOLDADOR ELECTRODO (SMAW) | D195: E0182 | E195: JEFFERSON ANDRES VALIENTE PEREZ | F195: 46023 | G195: 282 | H195: 31 | I195: 0 | J195: 0 | K195: 282 | L195: 0
A196: 60-CORDOBA S.L | B196: ROSAS | C196: SOLDADOR ELECTRODO (SMAW) | D196: E0181 | E196: JOSE ELMES PASTES DOMINGUEZ | F196: 46023 | G196: 275 | H196: 31 | I196: 0 | J196: 0 | K196: 275 | L196: 0
A197: 64-DOHERCO MIRANDA S.L | B197: ROSAS | C197: SOLDADOR ELECTRODO (SMAW) | D197: E0194 | E197: ALAN NAVAS | F197: 46023 | G197: 144 | H197: 31 | I197: 0 | J197: 0 | K197: 144 | L197: 0
A198: 64-DOHERCO MIRANDA S.L | B198: ROSAS | C198: SOLDADOR ELECTRODO (SMAW) | D198: E0195 | E198: BLADIMIR DIAZ | F198: 46023 | G198: 144 | H198: 31 | I198: 0 | J198: 0 | K198: 144 | L198: 0
A199: 64-DOHERCO MIRANDA S.L | B199: ROSAS | C199: SOLDADOR ELECTRODO (SMAW) | D199: E0196 | E199: JHON ADAIMER MORALES | F199: 46023 | G199: 160 | H199: 31 | I199: 0 | J199: 0 | K199: 160 | L199: 0
A200: 70-ELECTRODINAMIC JO-AN S.L | B200: ROSAS | C200: SOLDADOR ELECTRODO (SMAW) | D200: E0233 | E200: EISON SALAS | F200: 46023 | G200: 143 | H200: 31 | I200: 0 | J200: 0 | K200: 143 | L200: 0
... A202: 70-ELECTRODINAMIC JO-AN S.L | B202: ROSAS | C202: SOLDADOR ELECTRODO (SMAW) | D202: E0229 | E202: FRANCISCO MERCADO | F202: 46023 | G202: 144 | H202: 31 | I202: 0 | J202: 0 | K202: 144 | L202: 0
A203: 70-ELECTRODINAMIC JO-AN S.L | B203: ROSAS | D203: E1440 | E203: MARIO SUAREZ | F203: 46023 | G203: 135 | H203: 31 | I203: 0 | J203: 0 | K203: 135 | L203: 0
A204: 70-ELECTRODINAMIC JO-AN S.L | B204: ROSAS | D204: E1442 | E204: NEIRON CARCAMO | F204: 46023 | G204: 144 | H204: 31 | I204: 0 | J204: 0 | K204: 144 | L204: 0
A205: 70-ELECTRODINAMIC JO-AN S.L | B205: ROSAS | C205: SOLDADOR ELECTRODO (SMAW) | D205: E0234 | E205: WILMAN DE AVILA | F205: 46023 | G205: 143 | H205: 31 | I205: 0 | J205: 0 | K205: 143 | L205: 0
...

Sheet Tarifas dezembro att
D2: Cod trabalhador | E2: Colaborador | F2: Nome cliente 1 | G2: Tarifa cliente 1
D3: E1704 | E3: ELICEO FUENTES PARRA | F3: AEB DRYTECH | G3: 16
D4: E1671 | E4: JORGE ENRIQUE SANABRIA MORENO | F4: AEB DRYTECH | G4: 16
D5: E1754 | E5: NORVEY GONZALEZ LOPEZ | F5: AEB DRYTECH | G5: 16
D6: E0620 | E6: REMY SENNDER FARIAS ACARO | F6: AEB DRYTECH | G6: 16
D7: E0058 | E7: HENRRY CASTRO COLLACHAGUA | F7: ALUMINIO YACHT COSTA SL | G7: 15
D8: E0062 | E8: AYRTON MAXIMO CUMPA SENADOR | F8: ARDANORE | G8: 15
D9: E0063 | E9: CESAR EDUARDO GONZALES BARRIENTOS | F9: ARDANORE | G9: 15
D10: E0064 | E10: JAIME MANOLO ALVAREZ TORRES | F10: ARDANORE | G10: 15
D11: E0067 | E11: JAVIER SAUL PEREA CAMARGO | F11: ARDANORE | G11: 15
D12: E0065 | E12: JESUS ALBERTO GONZALES FERNANDEZ | F12: ARDANORE | G12: 15
D13: E0066 | E13: LUIS ALBERTO RAMIREZ PINEDO | F13: ARDANORE | G13: 15
D14: E0061 | E14: SIMION LUCIANO CHILINGANO PILLACA | F14: ARDANORE | G14: 15
... D422: E0593 | E422: ALEX MAURICIO CARDONA RAMIREZ | F422: TOKIO METAL | G422: 15

Sheet Informações
B5: Previsão | E5: Total general | L5: Total general | P5: Previsão | S5: Total general | W5: Previsão | Z5: Total general
B6: Etiquetas de fila | C6: Suma de Valor previsão de folha | E6: Etiquetas de fila | F6: Suma de Liquido total | I6: Etiquetas de fila | J6: Suma de Valor previsão de folha | L6: Etiquetas de fila | M6: Suma de Liquido total | P6: Rótulos de Linha | Q6: Suma de Valor previsão de folha | S6: Rótulos de Linha | T6: Suma de Liquido total | W6: Etiquetas de fila | X6: Suma de Valor previsão de folha | Z6: Etiquetas de fila | AA6: Suma de Liquido total
B7: Ativo | C7: 26061.387 | E7: Ativo | F7: 25221.387 | I7: Ativo | J7: 59508.195 | L7: Ativo | M7: 59508.195 | P7: Ativo | Q7: 95502.527 | S7: Ativo | T7: 94330.027 | W7: Ativo | X7: 87270.985 | Z7: Ativo | AA7: 86369.485
B8: Não ativo | C8: 90076.542 | E8: Não ativo | F8: 89836.542 | I8: Não ativo | J8: 54285.071 | L8: Não ativo | M8: 54285.071 | P8: Não ativo | Q8: 282185.52 | S8: Não ativo | T8: 298030.77 | W8: Não ativo | X8: 146093.77 | Z8: Não ativo | AA8: 143426.77
B9: Total general | C9: 116137.93 | E9: Total general | F9: 115057.93 | I9: Total general | J9: 113793.27 | L9: Total general | M9: 113793.27 | P9: Total Geral | Q9: 377688.05 | S9: Total Geral | T9: 392360.8 | W9: Total general | X9: 233364.75 | Z9: Total general | AA9: 229796.25
P12: Cuenta de Colaborador
B13: Cuenta de Colaborador | E13: Banco | F13: 213335.37 | I13: Cuenta de Colaborador | L13: Banco | M13: 254049.84 | P13: 163 | S13: Banco | T13: 852000 | Z13: Banco | AA13: 375000
B14: 43 | E14: Diferença | F14: =F13-GETPIVOTDATA("Liquido total",$E$6) -> 98277.441 | I14: 50 | L14: Diferença | M14: =M13-GETPIVOTDATA("Liquido total",$L$6) -> 140256.57 | S14: Diferença | T14: =T13-GETPIVOTDATA("Liquido total",$S$6) -> 459639.2 | Z14: Diferença | AA14: =AA13-GETPIVOTDATA("Liquido total",$Z$6) -> 145203.75
B19: Altas Segurança Social | I19: Altas Segurança Social | P19: Altas Segurança Social | W19: Altas Segurança Social
B20: Etiquetas de fila | C20: Cuenta de Status SS | I20: Etiquetas de fila | J20: Cuenta de Status SS | P20: Rótulos de Linha | Q20: Cuenta de Status SS | W20: Etiquetas de fila | X20: Cuenta de Status SS
B21: Ativo | C21: 11 | I21: Ativo | J21: 26 | P21: Ativo | Q21: 42 | W21: Ativo | X21: 46
B22: Não ativo | C22: 32 | I22: Não ativo | J22: 24 | P22: Não ativo | Q22: 121 | W22: Não ativo | X22: 73
B23: Total general | C23: 43 | I23: Total general | J23: 50 | P23: Total Geral | Q23: 163 | W23: Total general | X23: 119
B26: Valores | E26: Valores | I26: Valores
B27: Suma de Auxilio alojamento | C27: 910 | E27: Suma de Imposto ss | F27: 2117.4 | I27: Suma de Auxilio alojamento | J27: 4800
B28: Suma de Outros acréscimos | E28: Suma de Adiantamento | F28: 200 | I28: Suma de Outros acréscimos
E29: Suma de Desconto Carro | F29: 1340.1111
E30: Suma de Outros descontos
E31: Suma de Taxa bancária | F31: 175.44
B34: Etiquetas de fila | C34: Suma de Liquido total | I34: Etiquetas de fila | J34: Suma de Liquido total
B35: Pendente | C35: 115057.93 | I35: Pendente | J35: 111564.09
B36: Total general | C36: 115057.93 | I36: Pago | J36: 2229.18
I37: Total general | J37: 113793.27

Sheet Confirmaçoes
B2: auxilio alojamento | G2: Impostos | L2: Adiantamentos | Q2: Desconto carro | V2: Suministros | AA2: Multas | AF2: Limpeza e danos | AK2: Tarifa
B4: ID | C4: Nomes | D4: valor | E4: Revisão | G4: ID | H4: Nomes | I4: valor | J4: Revisão | L4: ID | M4: Nomes | N4: valor | O4: Revisão | Q4: ID | R4: Nomes | S4: valor | T4: Revisão | V4: ID | W4: Nomes | X4: valor | Y4: Revisão | AA4: ID | AB4: Nomes | AC4: valor | AD4: Revisão | AF4: ID | AG4: Nomes | AH4: valor | AI4: Revisão | AK4: ID | AL4: Nomes | AM4: valor | AN4: Revisão
B5: KR | C5: ALAN FRANCISCO NAVAS DIAZ | G5: KR | H5: ALAN FRANCISCO NAVAS DIAZ | I5: 218.798 | L5: KR | M5: ALAN FRANCISCO NAVAS DIAZ | Q5: KR | R5: ALAN FRANCISCO NAVAS DIAZ | V5: KI | W5: ALVARO ENRIQUE ROJAS DE LA OSSA | AA5: KR | AB5: ALAN FRANCISCO NAVAS DIAZ | AF5: KR | AG5: ALAN FRANCISCO NAVAS DIAZ | AK5: KR | AL5: ALAN FRANCISCO NAVAS DIAZ | AM5: 13
B6: LM | C6: ALAN GERSON RAMIREZ ACARO | G6: LM | H6: ALAN GERSON RAMIREZ ACARO | I6: 0 | L6: LM | M6: ALAN GERSON RAMIREZ ACARO | Q6: LM | R6: ALAN GERSON RAMIREZ ACARO | S6: 106.66667 | V6: KI | W6: BAIRON RENE BURBANO MORALES | Y6: OK | AA6: LM | AB6: ALAN GERSON RAMIREZ ACARO | AF6: LM | AG6: ALAN GERSON RAMIREZ ACARO | AK6: LM | AL6: ALAN GERSON RAMIREZ ACARO | AM6: 15
B7: WS | C7: ALBEIRO OBANDO MICOLTA | D7: 300 | G7: WS | H7: ALBEIRO OBANDO MICOLTA | I7: 218.798 | L7: WS | M7: ALBEIRO OBANDO MICOLTA | Q7: WS | R7: ALBEIRO OBANDO MICOLTA | V7: KI | W7: CAMILO ANDRES VALERO PEREZ | AA7: WS | AB7: ALBEIRO OBANDO MICOLTA | AF7: WS | AG7: ALBEIRO OBANDO MICOLTA | AK7: WS | AL7: ALBEIRO OBANDO MICOLTA | AM7: 17
B8: WS | C8: ALEX DAVID GOMEZ VILLADA | G8: WS | H8: ALEX DAVID GOMEZ VILLADA | I8: 0 | L8: WS | M8: ALEX DAVID GOMEZ VILLADA | Q8: WS | R8: ALEX DAVID GOMEZ VILLADA | V8: KI | W8: CARLOS ADRIAN CAMELO CALDERON | AA8: WS | AB8: ALEX DAVID GOMEZ VILLADA | AF8: WS | AG8: ALEX DAVID GOMEZ VILLADA | AK8: WS | AL8: ALEX DAVID GOMEZ VILLADA | AM8: 15
B9: KR | C9: ALEX MAURICIO CARDONA RAMIREZ | G9: KR | H9: ALEX MAURICIO CARDONA RAMIREZ | I9: 0 | L9: KR | M9: ALEX MAURICIO CARDONA RAMIREZ | Q9: KR | R9: ALEX MAURICIO CARDONA RAMIREZ | V9: KI | W9: CARLOS ALBERTO RAMOS URBANO | AA9: KR | AB9: ALEX MAURICIO CARDONA RAMIREZ | AF9: KR | AG9: ALEX MAURICIO CARDONA RAMIREZ | AK9: KR | AL9: ALEX MAURICIO CARDONA RAMIREZ | AM9: 15
B10: LM | C10: ALEXANDER GUZMAN | G10: LM | H10: ALEXANDER GUZMAN | I10: 0 | L10: LM | M10: ALEXANDER GUZMAN | Q10: LM | R10: ALEXANDER GUZMAN | S10: 10 | V10: KI | W10: DAMIAN ZAMBRANO TULANDE | AA10: LM | AB10: ALEXANDER GUZMAN | AF10: LM | AG10: ALEXANDER GUZMAN | AK10: LM | AL10: ALEXANDER GUZMAN | AM10: 15
B11: WS | C11: ALEXANDER MANUEL LOPEZ ROJAS | G11: WS | H11: ALEXANDER MANUEL LOPEZ ROJAS | I11: 218.798 | L11: WS | M11: ALEXANDER MANUEL LOPEZ ROJAS | Q11: WS | R11: ALEXANDER MANUEL LOPEZ ROJAS | V11: KI | W11: DARWIN JOSE VASQUEZ ORTEGA | AA11: WS | AB11: ALEXANDER MANUEL LOPEZ ROJAS | AF11: WS | AG11: ALEXANDER MANUEL LOPEZ ROJAS | AK11: WS | AL11: ALEXANDER MANUEL LOPEZ ROJAS | AM11: 12
B12: LM | C12: ALEXIS ENRIQUE MORENO ARRIETA | G12: LM | H12: ALEXIS ENRIQUE MORENO ARRIETA | I12: 21.174 | L12: LM | M12: ALEXIS ENRIQUE MORENO ARRIETA | Q12: LM | R12: ALEXIS ENRIQUE MORENO ARRIETA | S12: 84.444444 | V12: KI | W12: EDGAR STEVEN PENAGOS CESPEDES | AA12: LM | AB12: ALEXIS ENRIQUE MORENO ARRIETA | AF12: LM | AG12: ALEXIS ENRIQUE MORENO ARRIETA | AK12: LM | AL12: ALEXIS ENRIQUE MORENO ARRIETA | AM12: 15
B13: LM | C13: ALIRIO ORTIZ MOLINA | D13: 240 | G13: LM | H13: ALIRIO ORTIZ MOLINA | I13: 0 | L13: LM | M13: ALIRIO ORTIZ MOLINA | Q13: LM | R13: ALIRIO ORTIZ MOLINA | V13: KI | W13: EDILBERTO DOMINGUEZ PEREIRA | AA13: LM | AB13: ALIRIO ORTIZ MOLINA | AF13: LM | AG13: ALIRIO ORTIZ MOLINA | AK13: LM | AL13: ALIRIO ORTIZ MOLINA | AM13: 15
B14: WS | C14: ALVARO ARIZA CONTRERAS | G14: WS | H14: ALVARO ARIZA CONTRERAS | I14: 0 | L14: WS | M14: ALVARO ARIZA CONTRERAS | Q14: WS | R14: ALVARO ARIZA CONTRERAS | V14: KI | W14: EDILSON FIERRO DAGUA | AA14: WS | AB14: ALVARO ARIZA CONTRERAS | AF14: WS | AG14: ALVARO ARIZA CONTRERAS | AK14: WS | AL14: ALVARO ARIZA CONTRERAS | AM14: 15
B15: KI | C15: ALVARO ENRIQUE ROJAS DE LA OSSA | G15: KI | H15: ALVARO ENRIQUE ROJAS DE LA OSSA | I15: 218.798 | L15: KI | M15: ALVARO ENRIQUE ROJAS DE LA OSSA | Q15: KI | R15: ALVARO ENRIQUE ROJAS DE LA OSSA | V15: KI | W15: ELKIN ARMANDO GARZON LOPEZ | Y15: OK | AA15: KI | AB15: ALVARO ENRIQUE ROJAS DE LA OSSA | AF15: KI | AG15: ALVARO ENRIQUE ROJAS DE LA OSSA | AK15: KI | AL15: ALVARO ENRIQUE ROJAS DE LA OSSA | AM15: 17
B16: WS | C16: ALVARO FIGUEROA ARANGO | G16: WS | H16: ALVARO FIGUEROA ARANGO | I16: 0 | L16: WS | M16: ALVARO FIGUEROA ARANGO | N16: 200 | Q16: WS | R16: ALVARO FIGUEROA ARANGO | S16: 111.11111 | V16: KI | W16: EVELIO ANGULO ANGULO | AA16: WS | AB16: ALVARO FIGUEROA ARANGO | AC16: 40 | AF16: WS | AG16: ALVARO FIGUEROA ARANGO | AH16: 0 | AK16: WS | AL16: ALVARO FIGUEROA ARANGO | AM16: 15
B17: WS | C17: ALVARO JAVIER NARVAEZ MUÑOZ | D17: 300 | G17: WS | H17: ALVARO JAVIER NARVAEZ MUÑOZ | I17: 0 | L17: WS | M17: ALVARO JAVIER NARVAEZ MUÑOZ | Q17: WS | R17: ALVARO JAVIER NARVAEZ MUÑOZ | V17: KI | W17: FABIAN LEONARDO CERON VALENCIA | AA17: WS | AB17: ALVARO JAVIER NARVAEZ MUÑOZ | AF17: WS | AG17: ALVARO JAVIER NARVAEZ MUÑOZ | AK17: WS | AL17: ALVARO JAVIER NARVAEZ MUÑOZ | AM17: 15
B18: LM | C18: ALVARO SEGOVIA TORRES | G18: LM | H18: ALVARO SEGOVIA TORRES | I18: 169.392 | L18: LM | M18: ALVARO SEGOVIA TORRES | Q18: LM | R18: ALVARO SEGOVIA TORRES | S18: 26.666667 | V18: KI | W18: FREDY JAVIER CCALLA ROJAS | AA18: LM | AB18: ALVARO SEGOVIA TORRES | AF18: LM | AG18: ALVARO SEGOVIA TORRES | AK18: LM | AL18: ALVARO SEGOVIA TORRES | AM18: 15
B19: LM | C19: ANDERSON CHELUVAY GONZALEZ TRUJILLO | D19: 300 | G19: LM | H19: ANDERSON CHELUVAY GONZALEZ TRUJILLO | I19: 0 | L19: LM | M19: ANDERSON CHELUVAY GONZALEZ TRUJILLO | Q19: LM | R19: ANDERSON CHELUVAY GONZALEZ TRUJILLO | S19: 102.66 | V19: KI | W19: GUILLERMO LEON POSADA LONDONO | AA19: LM | AB19: ANDERSON CHELUVAY GONZALEZ TRUJILLO | AF19: LM | AG19: ANDERSON CHELUVAY GONZALEZ TRUJILLO | AK19: LM | AL19: ANDERSON CHELUVAY GONZALEZ TRUJILLO | AM19: 15
B20: WS | C20: ANDRES ALEXANDER BEJARANO PEREZ | G20: WS | H20: ANDRES ALEXANDER BEJARANO PEREZ | I20: 0 | L20: WS | M20: ANDRES ALEXANDER BEJARANO PEREZ | Q20: WS | R20: ANDRES ALEXANDER BEJARANO PEREZ | V20: KI | W20: HECTOR LUIS PARRAGA ZAVALA | AA20: WS | AB20: ANDRES ALEXANDER BEJARANO PEREZ | AF20: WS | AG20: ANDRES ALEXANDER BEJARANO PEREZ | AK20: WS | AL20: ANDRES ALEXANDER BEJARANO PEREZ | AM20: 15
B21: WS | C21: ANDRES FELIPE GOMEZ PUERTA | D21: 300 | G21: WS | H21: ANDRES FELIPE GOMEZ PUERTA | I21: 0 | L21: WS | M21: ANDRES FELIPE GOMEZ PUERTA | Q21: WS | R21: ANDRES FELIPE GOMEZ PUERTA | V21: KI | W21: HERNAN BERNARDO QUINTERO JARAMILLO | AA21: WS | AB21: ANDRES FELIPE GOMEZ PUERTA | AF21: WS | AG21: ANDRES FELIPE GOMEZ PUERTA | AK21: WS | AL21: ANDRES FELIPE GOMEZ PUERTA | AM21: 15
B22: WS | C22: ANDRES FELIPE MARULANDA ARAQUE | G22: WS | H22: ANDRES FELIPE MARULANDA ARAQUE | I22: 218.798 | L22: WS | M22: ANDRES FELIPE MARULANDA ARAQUE | Q22: WS | R22: ANDRES FELIPE MARULANDA ARAQUE | S22: 66.666667 | V22: KI | W22: ISRAEL BENAVIDES PRECIADO | X22: 148.97 | AA22: WS | AB22: ANDRES FELIPE MARULANDA ARAQUE | AC22: 0 | AF22: WS | AG22: ANDRES FELIPE MARULANDA ARAQUE | AH22: 0 | AK22: WS | AL22: ANDRES FELIPE MARULANDA ARAQUE | AM22: 15
B23: WS | C23: ANDRES FELIPE PULIDO GOMEZ | D23: 110 | G23: WS | H23: ANDRES FELIPE PULIDO GOMEZ | I23: 0 | L23: WS | M23: ANDRES FELIPE PULIDO GOMEZ | Q23: WS | R23: ANDRES FELIPE PULIDO GOMEZ | V23: KI | W23: JAN CESAR VILLEGAS MOSCOTE | AA23: WS | AB23: ANDRES FELIPE PULIDO GOMEZ | AF23: WS | AG23: ANDRES FELIPE PULIDO GOMEZ | AK23: WS | AL23: ANDRES FELIPE PULIDO GOMEZ | AM23: 15
B24: LM | C24: ANGEL TEHERAN CARABALLO | D24: 30 | G24: LM | H24: ANGEL TEHERAN CARABALLO | I24: 0 | L24: LM | M24: ANGEL TEHERAN CARABALLO | Q24: LM | R24: ANGEL TEHERAN CARABALLO | V24: KI | W24: JESUS DAVID CARDENAS RIVERA | AA24: LM | AB24: ANGEL TEHERAN CARABALLO | AF24: LM | AG24: ANGEL TEHERAN CARABALLO | AK24: LM | AL24: ANGEL TEHERAN CARABALLO | AM24: 15
B25: WS | C25: ANUAR JIMENEZ DELGADO | G25: WS | H25: ANUAR JIMENEZ DELGADO | I25: 0 | L25: WS | M25: ANUAR JIMENEZ DELGADO | Q25: WS | R25: ANUAR JIMENEZ DELGADO | V25: KI | W25: JHON EINER INSUASTI TULANDE | AA25: WS | AB25: ANUAR JIMENEZ DELGADO | AF25: WS | AG25: ANUAR JIMENEZ DELGADO | AK25: WS | AL25: ANUAR JIMENEZ DELGADO | AM25: 15
B26: LM | C26: ARLEY DARIO PANTOJA CABRERA | G26: LM | H26: ARLEY DARIO PANTOJA CABRERA | I26: 0 | L26: LM | M26: ARLEY DARIO PANTOJA CABRERA | Q26: LM | R26: ARLEY DARIO PANTOJA CABRERA | S26: 102.66 | V26: KI | W26: JHON JAIRO MUÑOZ BARBOSA | AA26: LM | AB26: ARLEY DARIO PANTOJA CABRERA | AF26: LM | AG26: ARLEY DARIO PANTOJA CABRERA | AK26: LM | AL26: ARLEY DARIO PANTOJA CABRERA | AM26: 15
B27: WS | C27: ARMANDO DENIS ENRIQUEZ BLAS | G27: WS | H27: ARMANDO DENIS ENRIQUEZ BLAS | I27: 0 | L27: WS | M27: ARMANDO DENIS ENRIQUEZ BLAS | Q27: WS | R27: ARMANDO DENIS ENRIQUEZ BLAS | V27: KI | W27: JIM PAUL CHUNGA LUJAN | AA27: WS | AB27: ARMANDO DENIS ENRIQUEZ BLAS | AF27: WS | AG27: ARMANDO DENIS ENRIQUEZ BLAS | AK27: WS | AL27: ARMANDO DENIS ENRIQUEZ BLAS | AM27: 16
B28: WS | C28: ARMANDO QUIROGA JOVEN | G28: WS | H28: ARMANDO QUIROGA JOVEN | I28: 0 | L28: WS | M28: ARMANDO QUIROGA JOVEN | Q28: WS | R28: ARMANDO QUIROGA JOVEN | V28: KI | W28: JONATHAN BLANDON HINCAPIE | AA28: WS | AB28: ARMANDO QUIROGA JOVEN | AF28: WS | AG28: ARMANDO QUIROGA JOVEN | AK28: WS | AL28: ARMANDO QUIROGA JOVEN | AM28: 15
B29: LM | C29: AYRTON MAXIMO CUMPA SENADOR | G29: LM | H29: AYRTON MAXIMO CUMPA SENADOR | I29: 0 | L29: LM | M29: AYRTON MAXIMO CUMPA SENADOR | Q29: LM | R29: AYRTON MAXIMO CUMPA SENADOR | S29: 86.666667 | V29: KI | W29: JORDY ALEXANDER ALVA PAYAC | AA29: LM | AB29: AYRTON MAXIMO CUMPA SENADOR | AC29: 250 | AF29: LM | AG29: AYRTON MAXIMO CUMPA SENADOR | AH29: 0 | AK29: LM | AL29: AYRTON MAXIMO CUMPA SENADOR | AM29: 15
B30: KI | C30: BAIRON RENE BURBANO MORALES | D30: 300 | E30: OK - APAGAGO | G30: KI | H30: BAIRON RENE BURBANO MORALES | I30: 0 | L30: KI | M30: BAIRON RENE BURBANO MORALES | N30: 200 | O30: OK | Q30: KI | R30: BAIRON RENE BURBANO MORALES | S30: 128.88889 | V30: KI | W30: JORGE ARLEY ALVAREZ GONZALEZ | AA30: KI | AB30: BAIRON RENE BURBANO MORALES | AD30: OK | AF30: KI | AG30: BAIRON RENE BURBANO MORALES | AI30: OK | AK30: KI | AL30: BAIRON RENE BURBANO MORALES | AM30: 15 | AN30: OK
B31: LM | C31: BAIRON RENE BURBANO MORALES | D31: 300 | G31: LM | H31: BAIRON RENE BURBANO MORALES | I31: 0 | L31: LM | M31: BAIRON RENE BURBANO MORALES | N31: 200 | Q31: LM | R31: BAIRON RENE BURBANO MORALES | S31: 128.88889 | T31: OK | V31: KI | W31: JOSE DE JESUS MENDOZA PADILLA | AA31: LM | AB31: BAIRON RENE BURBANO MORALES | AF31: LM | AG31: BAIRON RENE BURBANO MORALES | AK31: LM | AL31: BAIRON RENE BURBANO MORALES | AM31: 15
B32: KR | C32: BLADIMIRO DIAZ MARTINEZ | D32: 300 | G32: KR | H32: BLADIMIRO DIAZ MARTINEZ | I32: 218.798 | L32: KR | M32: BLADIMIRO DIAZ MARTINEZ | Q32: KR | R32: BLADIMIRO DIAZ MARTINEZ | V32: KI | W32: JOSUE ENRIQUE ZEVALLOS BENITES | X32: 197.2 | AA32: KR | AB32: BLADIMIRO DIAZ MARTINEZ | AF32: KR | AG32: BLADIMIRO DIAZ MARTINEZ | AK32: KR | AL32: BLADIMIRO DIAZ MARTINEZ | AM32: 13
B33: WS | C33: BLAKIS ANTONIO BARBOZA TRUJILLO | G33: WS | H33: BLAKIS ANTONIO BARBOZA TRUJILLO | I33: 0 | L33: WS | M33: BLAKIS ANTONIO BARBOZA TRUJILLO | Q33: WS | R33: BLAKIS ANTONIO BARBOZA TRUJILLO | S33: 81.111111 | V33: KI | W33: LUIZ GUILHERME AMARAL ALVES | AA33: WS | AB33: BLAKIS ANTONIO BARBOZA TRUJILLO | AF33: WS | AG33: BLAKIS ANTONIO BARBOZA TRUJILLO | AK33: WS | AL33: BLAKIS ANTONIO BARBOZA TRUJILLO | AM33: 14
B34: LM | C34: BORIS ALI CHUNGA LUJAN | G34: LM | H34: BORIS ALI CHUNGA LUJAN | I34: 0 | L34: LM | M34: BORIS ALI CHUNGA LUJAN | Q34: LM | R34: BORIS ALI CHUNGA LUJAN | V34: KI | W34: NELSON JAIME PITRE CASTILLA | AA34: LM | AB34: BORIS ALI CHUNGA LUJAN | AF34: LM | AG34: BORIS ALI CHUNGA LUJAN | AK34: LM | AL34: BORIS ALI CHUNGA LUJAN | AM34: 15
B35: WS | C35: BRANDON RAMIREZ ZAPATA | G35: WS | H35: BRANDON RAMIREZ ZAPATA | I35: 0 | L35: WS | M35: BRANDON RAMIREZ ZAPATA | Q35: WS | R35: BRANDON RAMIREZ ZAPATA | S35: 115 | V35: KI | W35: PABLO MANOLO ROMERO HUERTAS | AA35: WS | AB35: BRANDON RAMIREZ ZAPATA | AC35: 0 | AF35: WS | AG35: BRANDON RAMIREZ ZAPATA | AH35: 0 | AK35: WS | AL35: BRANDON RAMIREZ ZAPATA | AM35: 15
B36: WS | C36: BRAYAN JOSE ALARCON MORALES | G36: WS | H36: BRAYAN JOSE ALARCON MORALES | I36: 0 | L36: WS | M36: BRAYAN JOSE ALARCON MORALES | Q36: WS | R36: BRAYAN JOSE ALARCON MORALES | V36: KI | W36: PEDRO CARLOS ARMENDARIZ | Y36: OK | AA36: WS | AB36: BRAYAN JOSE ALARCON MORALES | AC36: 0 | AF36: WS | AG36: BRAYAN JOSE ALARCON MORALES | AH36: 0 | AK36: WS | AL36: BRAYAN JOSE ALARCON MORALES | AM36: 15
B37: WS | C37: BRAYAN JOSE SALINAS MARTINEZ | G37: WS | H37: BRAYAN JOSE SALINAS MARTINEZ | I37: 0 | L37: WS | M37: BRAYAN JOSE SALINAS MARTINEZ | Q37: WS | R37: BRAYAN JOSE SALINAS MARTINEZ | V37: KI | W37: RENZO JUNIOR CHUNGA LUJAN | AA37: WS | AB37: BRAYAN JOSE SALINAS MARTINEZ | AF37: WS | AG37: BRAYAN JOSE SALINAS MARTINEZ | AK37: WS | AL37: BRAYAN JOSE SALINAS MARTINEZ | AM37: 15
B38: WS | C38: BRAYAN JULIAN GAZCON MARIN | G38: WS | H38: BRAYAN JULIAN GAZCON MARIN | I38: 0 | L38: WS | M38: BRAYAN JULIAN GAZCON MARIN | Q38: WS | R38: BRAYAN JULIAN GAZCON MARIN | S38: 50 | V38: KI | W38: ROGER HALDER CHILCA LEON | AA38: WS | AB38: BRAYAN JULIAN GAZCON MARIN | AF38: WS | AG38: BRAYAN JULIAN GAZCON MARIN | AK38: WS | AL38: BRAYAN JULIAN GAZCON MARIN | AM38: 15
B39: KR | C39: BREIDIS JOSE CARDOZO GALUE | G39: KR | H39: BREIDIS JOSE CARDOZO GALUE | I39: 218.798 | L39: KR | M39: BREIDIS JOSE CARDOZO GALUE | Q39: KR | R39: BREIDIS JOSE CARDOZO GALUE | V39: KI | W39: ROLANDO CATUNTA MAMANI | AA39: KR | AB39: BREIDIS JOSE CARDOZO GALUE | AF39: KR | AG39: BREIDIS JOSE CARDOZO GALUE | AK39: KR | AL39: BREIDIS JOSE CARDOZO GALUE | AM39: 15
B40: LM | C40: BREINER MOLINA PELAEZ | G40: LM | H40: BREINER MOLINA PELAEZ | I40: 0 | L40: LM | M40: BREINER MOLINA PELAEZ | Q40: LM | R40: BREINER MOLINA PELAEZ | S40: 102.66 | V40: KI | W40: VICTOR ARTURO GALVEZ PALACIOS | X40: 197.2 | AA40: LM | AB40: BREINER MOLINA PELAEZ | AC40: 0 | AF40: LM | AG40: BREINER MOLINA PELAEZ | AH40: 0 | AK40: LM | AL40: BREINER MOLINA PELAEZ | AM40: 15
B41: LM | C41: CAMILO ANDRES RUBIO LEON | G41: LM | H41: CAMILO ANDRES RUBIO LEON | I41: 218.798 | L41: LM | M41: CAMILO ANDRES RUBIO LEON | Q41: LM | R41: CAMILO ANDRES RUBIO LEON | V41: KI | W41: VICTOR EDGARDO RAMIREZ GRANDA | AA41: LM | AB41: CAMILO ANDRES RUBIO LEON | AC41: 0 | AF41: LM | AG41: CAMILO ANDRES RUBIO LEON | AH41: 21.74 | AK41: LM | AL41: CAMILO ANDRES RUBIO LEON | AM41: 14
B42: KI | C42: CAMILO ANDRES VALERO PEREZ | G42: KI | H42: CAMILO ANDRES VALERO PEREZ | I42: 218.798 | L42: KI | M42: CAMILO ANDRES VALERO PEREZ | Q42: KI | R42: CAMILO ANDRES VALERO PEREZ | S42: 145 | V42: KI | W42: WILBER LOPEZ BALETA | AA42: KI | AB42: CAMILO ANDRES VALERO PEREZ | AF42: KI | AG42: CAMILO ANDRES VALERO PEREZ | AK42: KI | AL42: CAMILO ANDRES VALERO PEREZ | AM42: 15
B43: KI | C43: CARLOS ADRIAN CAMELO CALDERON | G43: KI | H43: CARLOS ADRIAN CAMELO CALDERON | I43: 0 | L43: KI | M43: CARLOS ADRIAN CAMELO CALDERON | Q43: KI | R43: CARLOS ADRIAN CAMELO CALDERON | V43: KI | W43: WILLIAM NOE MANRIQUE MOREYRA | Y43: OK | AA43: KI | AB43: CARLOS ADRIAN CAMELO CALDERON | AF43: KI | AG43: CARLOS ADRIAN CAMELO CALDERON | AK43: KI | AL43: CARLOS ADRIAN CAMELO CALDERON | AM43: 13
B44: WS | C44: CARLOS ALBERTO CORREA OREJUELA | G44: WS | H44: CARLOS ALBERTO CORREA OREJUELA | I44: 0 | L44: WS | M44: CARLOS ALBERTO CORREA OREJUELA | Q44: WS | R44: CARLOS ALBERTO CORREA OREJUELA | V44: KI | W44: WILMER YANAYACO PINEDO | AA44: WS | AB44: CARLOS ALBERTO CORREA OREJUELA | AF44: WS | AG44: CARLOS ALBERTO CORREA OREJUELA | AK44: WS | AL44: CARLOS ALBERTO CORREA OREJUELA | AM44: 15
B45: KI | C45: CARLOS ALBERTO RAMOS URBANO | G45: KI | H45: CARLOS ALBERTO RAMOS URBANO | I45: 0 | L45: KI | M45: CARLOS ALBERTO RAMOS URBANO | Q45: KI | R45: CARLOS ALBERTO RAMOS URBANO | V45: KI | W45: YANNY ALBERTO HERNANDEZ LOZANO | AA45: KI | AB45: CARLOS ALBERTO RAMOS URBANO | AF45: KI | AG45: CARLOS ALBERTO RAMOS URBANO | AK45: KI | AL45: CARLOS ALBERTO RAMOS URBANO | AM45: 16
B46: WS | C46: CARLOS ANDRES ARROYO BERTEL | G46: WS | H46: CARLOS ANDRES ARROYO BERTEL | I46: 0 | L46: WS | M46: CARLOS ANDRES ARROYO BERTEL | Q46: WS | R46: CARLOS ANDRES ARROYO BERTEL | V46: KI | W46: YOBER HUAMAN VELASQUE | AA46: WS | AB46: CARLOS ANDRES ARROYO BERTEL | AC46: 0 | AF46: WS | AG46: CARLOS ANDRES ARROYO BERTEL | AH46: 0 | AK46: WS | AL46: CARLOS ANDRES ARROYO BERTEL | AM46: 15
B47: KR | C47: CARLOS ANDRES JIMENEZ RAMIREZ | D47: 300 | G47: KR | H47: CARLOS ANDRES JIMENEZ RAMIREZ | I47: 211.74 | L47: KR | M47: CARLOS ANDRES JIMENEZ RAMIREZ | Q47: KR | R47: CARLOS ANDRES JIMENEZ RAMIREZ | V47: KI | W47: YUBYINER SANTIAGO CELIS | AA47: KR | AB47: CARLOS ANDRES JIMENEZ RAMIREZ | AF47: KR | AG47: CARLOS ANDRES JIMENEZ RAMIREZ | AK47: KR | AL47: CARLOS ANDRES JIMENEZ RAMIREZ | AM47: 15
B48: KR | C48: CARLOS ANDRES MANTILLA URREGO | G48: KR | H48: CARLOS ANDRES MANTILLA URREGO | I48: 0 | L48: KR | M48: CARLOS ANDRES MANTILLA URREGO | Q48: KR | R48: CARLOS ANDRES MANTILLA URREGO | V48: KR | W48: ALAN FRANCISCO NAVAS DIAZ | AA48: KR | AB48: CARLOS ANDRES MANTILLA URREGO | AF48: KR | AG48: CARLOS ANDRES MANTILLA URREGO | AK48: KR | AL48: CARLOS ANDRES MANTILLA URREGO | AM48: 15
B49: WS | C49: CARLOS ANDRES SILVA CORREA | G49: WS | H49: CARLOS ANDRES SILVA CORREA | I49: 0 | L49: WS | M49: CARLOS ANDRES SILVA CORREA | Q49: WS | R49: CARLOS ANDRES SILVA CORREA | V49: KR | W49: ALEX MAURICIO CARDONA RAMIREZ | AA49: WS | AB49: CARLOS ANDRES SILVA CORREA | AC49: 0 | AF49: WS | AG49: CARLOS ANDRES SILVA CORREA | AH49: 0 | AK49: WS | AL49: CARLOS ANDRES SILVA CORREA | AM49: 15
B50: WS | C50: CARLOS ARTURO GONZALEZ GOMEZ | G50: WS | H50: CARLOS ARTURO GONZALEZ GOMEZ | I50: 0 | L50: WS | M50: CARLOS ARTURO GONZALEZ GOMEZ | Q50: WS | R50: CARLOS ARTURO GONZALEZ GOMEZ | S50: 63.333333 | V50: KR | W50: BLADIMIRO DIAZ MARTINEZ | AA50: WS | AB50: CARLOS ARTURO GONZALEZ GOMEZ | AF50: WS | AG50: CARLOS ARTURO GONZALEZ GOMEZ | AK50: WS | AL50: CARLOS ARTURO GONZALEZ GOMEZ | AM50: 14
B51: LM | C51: CARLOS DANIEL RODRIGUEZ PENA | G51: LM | H51: CARLOS DANIEL RODRIGUEZ PENA | I51: 0 | L51: LM | M51: CARLOS DANIEL RODRIGUEZ PENA | Q51: LM | R51: CARLOS DANIEL RODRIGUEZ PENA | S51: 45 | V51: KR | W51: BREIDIS JOSE CARDOZO GALUE | AA51: LM | AB51: CARLOS DANIEL RODRIGUEZ PENA | AF51: LM | AG51: CARLOS DANIEL RODRIGUEZ PENA | AK51: LM | AL51: CARLOS DANIEL RODRIGUEZ PENA | AM51: 15
B52: LM | C52: CARLOS EDUARDO CARDENAS ESPINOSA | D52: 300 | G52: LM | H52: CARLOS EDUARDO CARDENAS ESPINOSA | I52: 42.348 | L52: LM | M52: CARLOS EDUARDO CARDENAS ESPINOSA | Q52: LM | R52: CARLOS EDUARDO CARDENAS ESPINOSA | V52: KR | W52: CARLOS ANDRES JIMENEZ RAMIREZ | AA52: LM | AB52: CARLOS EDUARDO CARDENAS ESPINOSA | AF52: LM | AG52: CARLOS EDUARDO CARDENAS ESPINOSA | AK52: LM | AL52: CARLOS EDUARDO CARDENAS ESPINOSA | AM52: 15
B53: KR | C53: CARLOS JULIO ACOSTA CAMACHO | D53: 300 | G53: KR | H53: CARLOS JULIO ACOSTA CAMACHO | I53: 211.74 | L53: KR | M53: CARLOS JULIO ACOSTA CAMACHO | Q53: KR | R53: CARLOS JULIO ACOSTA CAMACHO | S53: 120 | V53: KR | W53: CARLOS ANDRES MANTILLA URREGO | AA53: KR | AB53: CARLOS JULIO ACOSTA CAMACHO | AF53: KR | AG53: CARLOS JULIO ACOSTA CAMACHO | AK53: KR | AL53: CARLOS JULIO ACOSTA CAMACHO | AM53: 15
B54: LM | C54: CARLOS JULIO CANON | G54: LM | H54: CARLOS JULIO CANON | I54: 218.798 | L54: LM | M54: CARLOS JULIO CANON | Q54: LM | R54: CARLOS JULIO CANON | V54: KR | W54: CARLOS JULIO ACOSTA CAMACHO | AA54: LM | AB54: CARLOS JULIO CANON | AF54: LM | AG54: CARLOS JULIO CANON | AK54: LM | AL54: CARLOS JULIO CANON | AM54: 15
B55: KR | C55: CARLOS MARIO JARAMILLO LOPEZ | G55: KR | H55: CARLOS MARIO JARAMILLO LOPEZ | I55: 0 | L55: KR | M55: CARLOS MARIO JARAMILLO LOPEZ | Q55: KR | R55: CARLOS MARIO JARAMILLO LOPEZ | V55: KR | W55: CARLOS MARIO JARAMILLO LOPEZ | AA55: KR | AB55: CARLOS MARIO JARAMILLO LOPEZ | AF55: KR | AG55: CARLOS MARIO JARAMILLO LOPEZ | AK55: KR | AL55: CARLOS MARIO JARAMILLO LOPEZ | AM55: 15
B56: LM | C56: CARLOS MARIO ROCHA ARIZ | G56: LM | H56: CARLOS MARIO ROCHA ARIZ | I56: 0 | L56: LM | M56: CARLOS MARIO ROCHA ARIZ | Q56: LM | R56: CARLOS MARIO ROCHA ARIZ | S56: 128.88889 | V56: KR | W56: EDU PANDURO RUIZ | AA56: LM | AB56: CARLOS MARIO ROCHA ARIZ | AF56: LM | AG56: CARLOS MARIO ROCHA ARIZ | AK56: LM | AL56: CARLOS MARIO ROCHA ARIZ | AM56: 15
B57: WS | C57: CARLOS MITCHELL SANTOS RODRIGUEZ | G57: WS | H57: CARLOS MITCHELL SANTOS RODRIGUEZ | I57: 218.798 | L57: WS | M57: CARLOS MITCHELL SANTOS RODRIGUEZ | Q57: WS | R57: CARLOS MITCHELL SANTOS RODRIGUEZ | S57: 66.666667 | V57: KR | W57: EDUARDO JOSE RUSSO LINERO | AA57: WS | AB57: CARLOS MITCHELL SANTOS RODRIGUEZ | AC57: 0 | AF57: WS | AG57: CARLOS MITCHELL SANTOS RODRIGUEZ | AH57: 21.74 | AK57: WS | AL57: CARLOS MITCHELL SANTOS RODRIGUEZ | AM57: 15
B58: WS | C58: CICERO LIMA BATISTA | G58: WS | H58: CICERO LIMA BATISTA | I58: 218.798 | L58: WS | M58: CICERO LIMA BATISTA | N58: 200 | Q58: WS | R58: CICERO LIMA BATISTA | V58: KR | W58: EDWIN FERNANDO LINARES MACA | AA58: WS | AB58: CICERO LIMA BATISTA | AF58: WS | AG58: CICERO LIMA BATISTA | AK58: WS | AL58: CICERO LIMA BATISTA | AM58: 16
B59: WS | C59: CRISTIAN ARIZA MARTINEZ | G59: WS | H59: CRISTIAN ARIZA MARTINEZ | I59: 0 | L59: WS | M59: CRISTIAN ARIZA MARTINEZ | Q59: WS | R59: CRISTIAN ARIZA MARTINEZ | S59: 74.666667 | V59: KR | W59: EISON SALAS AHUMEDO | AA59: WS | AB59: CRISTIAN ARIZA MARTINEZ | AF59: WS | AG59: CRISTIAN ARIZA MARTINEZ | AK59: WS | AL59: CRISTIAN ARIZA MARTINEZ | AM59: 14
B60: LM | C60: CRISTIAN CAMILO BORRE SILVA | G60: LM | H60: CRISTIAN CAMILO BORRE SILVA | I60: 0 | L60: LM | M60: CRISTIAN CAMILO BORRE SILVA | Q60: LM | R60: CRISTIAN CAMILO BORRE SILVA | V60: KR | W60: FABIAN LLERAR ROA MATEUS | AA60: LM | AB60: CRISTIAN CAMILO BORRE SILVA | AF60: LM | AG60: CRISTIAN CAMILO BORRE SILVA | AK60: LM | AL60: CRISTIAN CAMILO BORRE SILVA | AM60: 15
B61: LM | C61: CRISTIAN CAMILO CABALLERO CORREDOR | G61: LM | H61: CRISTIAN CAMILO CABALLERO CORREDOR | I61: 91.754 | L61: LM | M61: CRISTIAN CAMILO CABALLERO CORREDOR | Q61: LM | R61: CRISTIAN CAMILO CABALLERO CORREDOR | V61: KR | W61: FRANCISCO JAVIER MERCADO MELENDEZ | AA61: LM | AB61: CRISTIAN CAMILO CABALLERO CORREDOR | AC61: 0 | AF61: LM | AG61: CRISTIAN CAMILO CABALLERO CORREDOR | AH61: 21.74 | AK61: LM | AL61: CRISTIAN CAMILO CABALLERO CORREDOR | AM61: 15
B62: KI | C62: DAMIAN ZAMBRANO TULANDE | G62: KI | H62: DAMIAN ZAMBRANO TULANDE | I62: 211.74 | L62: KI | M62: DAMIAN ZAMBRANO TULANDE | Q62: KI | R62: DAMIAN ZAMBRANO TULANDE | S62: 66.666667 | V62: KR | W62: FREDY MANCERA URIBE | AA62: KI | AB62: DAMIAN ZAMBRANO TULANDE | AF62: KI | AG62: DAMIAN ZAMBRANO TULANDE | AK62: KI | AL62: DAMIAN ZAMBRANO TULANDE | AM62: 15
B63: WS | C63: DANIER CALDERON SALAS | D63: 110 | G63: WS | H63: DANIER CALDERON SALAS | I63: 0 | L63: WS | M63: DANIER CALDERON SALAS | Q63: WS | R63: DANIER CALDERON SALAS | S63: 120 | V63: KR | W63: GILBER MORA DIAZ | AA63: WS | AB63: DANIER CALDERON SALAS | AC63: 185 | AF63: WS | AG63: DANIER CALDERON SALAS | AH63: 0 | AK63: WS | AL63: DANIER CALDERON SALAS | AM63: 15
B64: LM | C64: DANILO PINEDA RIVAS | G64: LM | H64: DANILO PINEDA RIVAS | I64: 0 | L64: LM | M64: DANILO PINEDA RIVAS | Q64: LM | R64: DANILO PINEDA RIVAS | V64: KR | W64: HECTOR JAIME ROA CONTRERAS | AA64: LM | AB64: DANILO PINEDA RIVAS | AF64: LM | AG64: DANILO PINEDA RIVAS | AK64: LM | AL64: DANILO PINEDA RIVAS | AM64: 15
B65: WS | C65: DARIO CARLOS MANUEL PEREIRA | G65: WS | H65: DARIO CARLOS MANUEL PEREIRA | I65: 218.798 | L65: WS | M65: DARIO CARLOS MANUEL PEREIRA | Q65: WS | R65: DARIO CARLOS MANUEL PEREIRA | V65: KR | W65: HECTOR MANUEL BUELVAS ZAMBRANO | AA65: WS | AB65: DARIO CARLOS MANUEL PEREIRA | AF65: WS | AG65: DARIO CARLOS MANUEL PEREIRA | AK65: WS | AL65: DARIO CARLOS MANUEL PEREIRA | AM65: 15
B66: KI | C66: DARWIN JOSE VASQUEZ ORTEGA | D66: 300 | G66: KI | H66: DARWIN JOSE VASQUEZ ORTEGA | I66: 0 | L66: KI | M66: DARWIN JOSE VASQUEZ ORTEGA | Q66: KI | R66: DARWIN JOSE VASQUEZ ORTEGA | V66: KR | W66: HENRRY CASTRO COLLACHAGUA | AA66: KI | AB66: DARWIN JOSE VASQUEZ ORTEGA | AF66: KI | AG66: DARWIN JOSE VASQUEZ ORTEGA | AK66: KI | AL66: DARWIN JOSE VASQUEZ ORTEGA | AM66: 15
B67: LM | C67: DAVID RICARDO SANCHEZ ZAPATA | G67: LM | H67: DAVID RICARDO SANCHEZ ZAPATA | I67: 0 | L67: LM | M67: DAVID RICARDO SANCHEZ ZAPATA | Q67: LM | R67: DAVID RICARDO SANCHEZ ZAPATA | V67: KR | W67: JAHIR SURLEY DELGADO AGREDO | AA67: LM | AB67: DAVID RICARDO SANCHEZ ZAPATA | AF67: LM | AG67: DAVID RICARDO SANCHEZ ZAPATA | AK67: LM | AL67: DAVID RICARDO SANCHEZ ZAPATA | AM67: 15
B68: WS | C68: DEWIN DE JESUS DE LEON BARRERA | G68: WS | H68: DEWIN DE JESUS DE LEON BARRERA | I68: 0 | L68: WS | M68: DEWIN DE JESUS DE LEON BARRERA | Q68: WS | R68: DEWIN DE JESUS DE LEON BARRERA | S68: 115 | V68: KR | W68: JAIRO ALFONSO MUNOZ VALLE | X68: 0 | AA68: WS | AB68: DEWIN DE JESUS DE LEON BARRERA | AC68: 0 | AF68: WS | AG68: DEWIN DE JESUS DE LEON BARRERA | AH68: 0 | AK68: WS | AL68: DEWIN DE JESUS DE LEON BARRERA | AM68: 15
B69: WS | C69: DIEGO ROBERTO SOUZA SCAVACINI | G69: WS | H69: DIEGO ROBERTO SOUZA SCAVACINI | I69: 218.798 | L69: WS | M69: DIEGO ROBERTO SOUZA SCAVACINI | Q69: WS | R69: DIEGO ROBERTO SOUZA SCAVACINI | V69: KR | W69: JAVIER FRANCISCO BALDOVINO ORTEGA | AA69: WS | AB69: DIEGO ROBERTO SOUZA SCAVACINI | AF69: WS | AG69: DIEGO ROBERTO SOUZA SCAVACINI | AK69: WS | AL69: DIEGO ROBERTO SOUZA SCAVACINI | AM69: 17
B70: WS | C70: DOMINGO RAMON VEGA HUMANEZ | G70: WS | H70: DOMINGO RAMON VEGA HUMANEZ | I70: 0 | L70: WS | M70: DOMINGO RAMON VEGA HUMANEZ | Q70: WS | R70: DOMINGO RAMON VEGA HUMANEZ | V70: KR | W70: JEFFERSON ANDRES OROZCO RODRIGUEZ | AA70: WS | AB70: DOMINGO RAMON VEGA HUMANEZ | AF70: WS | AG70: DOMINGO RAMON VEGA HUMANEZ | AK70: WS | AL70: DOMINGO RAMON VEGA HUMANEZ | AM70: 15
B71: WS | C71: DUAN ANTONIO AVILA NORIEGA | G71: WS | H71: DUAN ANTONIO AVILA NORIEGA | I71: 0 | L71: WS | M71: DUAN ANTONIO AVILA NORIEGA | Q71: WS | R71: DUAN ANTONIO AVILA NORIEGA | S71: 50 | V71: KR | W71: JEFFERSON ANDRES VALIENTE PEREZ | X71: 0 | AA71: WS | AB71: DUAN ANTONIO AVILA NORIEGA | AF71: WS | AG71: DUAN ANTONIO AVILA NORIEGA | AK71: WS | AL71: DUAN ANTONIO AVILA NORIEGA | AM71: 15
B72: LM | C72: DUBERNEY POSCUE FAJARDO | G72: LM | H72: DUBERNEY POSCUE FAJARDO | I72: 0 | L72: LM | M72: DUBERNEY POSCUE FAJARDO | Q72: LM | R72: DUBERNEY POSCUE FAJARDO | S72: 84.444444 | V72: KR | W72: JHON ADAIMER MORALES MORALES | AA72: LM | AB72: DUBERNEY POSCUE FAJARDO | AF72: LM | AG72: DUBERNEY POSCUE FAJARDO | AK72: LM | AL72: DUBERNEY POSCUE FAJARDO | AM72: 15
B73: WS | C73: EDDIE DE JESUS ZARATE IGUARAN | G73: WS | H73: EDDIE DE JESUS ZARATE IGUARAN | I73: 91.754 | L73: WS | M73: EDDIE DE JESUS ZARATE IGUARAN | Q73: WS | R73: EDDIE DE JESUS ZARATE IGUARAN | S73: 40 | V73: KR | W73: JOHN FREDDY PEREZ RUIZ | AA73: WS | AB73: EDDIE DE JESUS ZARATE IGUARAN | AC73: 0 | AF73: WS | AG73: EDDIE DE JESUS ZARATE IGUARAN | AH73: 112.93 | AK73: WS | AL73: EDDIE DE JESUS ZARATE IGUARAN | AM73: 15
B74: LM | C74: EDGAR CORRALES HOYOS | G74: LM | H74: EDGAR CORRALES HOYOS | I74: 0 | L74: LM | M74: EDGAR CORRALES HOYOS | Q74: LM | R74: EDGAR CORRALES HOYOS | V74: KR | W74: JOHN FREDY CASTRO JIMENEZ | AA74: LM | AB74: EDGAR CORRALES HOYOS | AF74: LM | AG74: EDGAR CORRALES HOYOS | AK74: LM | AL74: EDGAR CORRALES HOYOS | AM74: 15
B75: WS | C75: EDGAR ENRIQUE TORRES RAMIREZ | G75: WS | H75: EDGAR ENRIQUE TORRES RAMIREZ | I75: 0 | L75: WS | M75: EDGAR ENRIQUE TORRES RAMIREZ | Q75: WS | R75: EDGAR ENRIQUE TORRES RAMIREZ | V75: KR | W75: JOSE ELMES PASTES DOMINGUEZ | AA75: WS | AB75: EDGAR ENRIQUE TORRES RAMIREZ | AF75: WS | AG75: EDGAR ENRIQUE TORRES RAMIREZ | AK75: WS | AL75: EDGAR ENRIQUE TORRES RAMIREZ | AM75: 14
B76: KI | C76: EDGAR STEVEN PENAGOS CESPEDES | G76: KI | H76: EDGAR STEVEN PENAGOS CESPEDES | I76: 211.74 | L76: KI | M76: EDGAR STEVEN PENAGOS CESPEDES | Q76: KI | R76: EDGAR STEVEN PENAGOS CESPEDES | V76: KR | W76: JUAN CARLOS BENAVIDES RODRIGUEZ | AA76: KI | AB76: EDGAR STEVEN PENAGOS CESPEDES | AF76: KI | AG76: EDGAR STEVEN PENAGOS CESPEDES | AK76: KI | AL76: EDGAR STEVEN PENAGOS CESPEDES | AM76: 16
B77: KI | C77: EDILBERTO DOMINGUEZ PEREIRA | G77: KI | H77: EDILBERTO DOMINGUEZ PEREIRA | I77: 218.798 | L77: KI | M77: EDILBERTO DOMINGUEZ PEREIRA | Q77: KI | R77: EDILBERTO DOMINGUEZ PEREIRA | V77: KR | W77: JUAN CARLOS VILLANUEVA DE LA HOZ | AA77: KI | AB77: EDILBERTO DOMINGUEZ PEREIRA | AF77: KI | AG77: EDILBERTO DOMINGUEZ PEREIRA | AK77: KI | AL77: EDILBERTO DOMINGUEZ PEREIRA | AM77: 18
B78: KI | C78: EDILSON FIERRO DAGUA | G78: KI | H78: EDILSON FIERRO DAGUA | I78: 0 | L78: KI | M78: EDILSON FIERRO DAGUA | Q78: KI | R78: EDILSON FIERRO DAGUA | S78: 74.666667 | V78: KR | W78: JUAN CARLOS VILLANUEVA GALVIS | AA78: KI | AB78: EDILSON FIERRO DAGUA | AF78: KI | AG78: EDILSON FIERRO DAGUA | AK78: KI | AL78: EDILSON FIERRO DAGUA | AM78: 15
B79: WS | C79: EDILSON TORRES SALCEDO | G79: WS | H79: EDILSON TORRES SALCEDO | I79: 0 | L79: WS | M79: EDILSON TORRES SALCEDO | Q79: WS | R79: EDILSON TORRES SALCEDO | V79: KR | W79: JULIO CESAR MANJARRES | X79: 0 | AA79: WS | AB79: EDILSON TORRES SALCEDO | AC79: 0 | AF79: WS | AG79: EDILSON TORRES SALCEDO | AH79: 0 | AK79: WS | AL79: EDILSON TORRES SALCEDO | AM79: 15
B80: KR | C80: EDU PANDURO RUIZ | G80: KR | H80: EDU PANDURO RUIZ | I80: 0 | L80: KR | M80: EDU PANDURO RUIZ | Q80: KR | R80: EDU PANDURO RUIZ | S80: 89.52381 | V80: KR | W80: LENNIN JESUS CANON CARDENAS | AA80: KR | AB80: EDU PANDURO RUIZ | AF80: KR | AG80: EDU PANDURO RUIZ | AK80: KR | AL80: EDU PANDURO RUIZ | AM80: 13
B81: LM | C81: EDUAR MANUEL DAVILA CERON | G81: LM | H81: EDUAR MANUEL DAVILA CERON | I81: 91.754 | L81: LM | M81: EDUAR MANUEL DAVILA CERON | Q81: LM | R81: EDUAR MANUEL DAVILA CERON | V81: KR | W81: MARIO ANDRES SUAREZ ACOSTA | AA81: LM | AB81: EDUAR MANUEL DAVILA CERON | AF81: LM | AG81: EDUAR MANUEL DAVILA CERON | AK81: LM | AL81: EDUAR MANUEL DAVILA CERON | AM81: 15
B82: WS | C82: EDUARD YOVANNY LOZANO OSORIO | G82: WS | H82: EDUARD YOVANNY LOZANO OSORIO | I82: 218.798 | L82: WS | M82: EDUARD YOVANNY LOZANO OSORIO | Q82: WS | R82: EDUARD YOVANNY LOZANO OSORIO | V82: KR | W82: MILTON DAVID SOSA PALLAS | AA82: WS | AB82: EDUARD YOVANNY LOZANO OSORIO | AC82: 50 | AF82: WS | AG82: EDUARD YOVANNY LOZANO OSORIO | AH82: 0 | AK82: WS | AL82: EDUARD YOVANNY LOZANO OSORIO | AM82: 15
B83: KR | C83: EDUARDO JOSE RUSSO LINERO | G83: KR | H83: EDUARDO JOSE RUSSO LINERO | I83: 0 | L83: KR | M83: EDUARDO JOSE RUSSO LINERO | Q83: KR | R83: EDUARDO JOSE RUSSO LINERO | S83: 89.52381 | V83: KR | W83: NEIRON ENRIQUE CARCAMO REALES | AA83: KR | AB83: EDUARDO JOSE RUSSO LINERO | AF83: KR | AG83: EDUARDO JOSE RUSSO LINERO | AK83: KR | AL83: EDUARDO JOSE RUSSO LINERO | AM83: 12
B84: LM | C84: EDWAR ANDRES BENACHI ARCE | G84: LM | H84: EDWAR ANDRES BENACHI ARCE | I84: 91.754 | L84: LM | M84: EDWAR ANDRES BENACHI ARCE | Q84: LM | R84: EDWAR ANDRES BENACHI ARCE | V84: KR | W84: NICOLAS RAUL MACIAS MEJIA | AA84: LM | AB84: EDWAR ANDRES BENACHI ARCE | AF84: LM | AG84: EDWAR ANDRES BENACHI ARCE | AK84: LM | AL84: EDWAR ANDRES BENACHI ARCE | AM84: 15
B85: WS | C85: EDWAR ARIEL VELEZ POSADA | G85: WS | H85: EDWAR ARIEL VELEZ POSADA | I85: 0 | L85: WS | M85: EDWAR ARIEL VELEZ POSADA | Q85: WS | R85: EDWAR ARIEL VELEZ POSADA | S85: 50 | V85: KR | W85: NORBEY BALLESTEROS CRUZ | AA85: WS | AB85: EDWAR ARIEL VELEZ POSADA | AF85: WS | AG85: EDWAR ARIEL VELEZ POSADA | AK85: WS | AL85: EDWAR ARIEL VELEZ POSADA | AM85: 15
B86: WS | C86: EDWARD IGNACIO DIAZ AVILA | G86: WS | H86: EDWARD IGNACIO DIAZ AVILA | I86: 218.798 | L86: WS | M86: EDWARD IGNACIO DIAZ AVILA | Q86: WS | R86: EDWARD IGNACIO DIAZ AVILA | S86: 67 | V86: KR | W86: NORBEY VARON ESQUIVEL | AA86: WS | AB86: EDWARD IGNACIO DIAZ AVILA | AF86: WS | AG86: EDWARD IGNACIO DIAZ AVILA | AK86: WS | AL86: EDWARD IGNACIO DIAZ AVILA | AM86: 15
B87: WS | C87: EDWIN ALBERTO HINESTROZA | G87: WS | H87: EDWIN ALBERTO HINESTROZA | I87: 0 | L87: WS | M87: EDWIN ALBERTO HINESTROZA | Q87: WS | R87: EDWIN ALBERTO HINESTROZA | S87: 121.66667 | V87: KR | W87: ORLANDO JANNCARLO ACEVEDO GUZMAN | AA87: WS | AB87: EDWIN ALBERTO HINESTROZA | AF87: WS | AG87: EDWIN ALBERTO HINESTROZA | AK87: WS | AL87: EDWIN ALBERTO HINESTROZA | AM87: 15
B88: WS | C88: EDWIN ALEXANDER DIAZ PITRE | G88: WS | H88: EDWIN ALEXANDER DIAZ PITRE | I88: 134.102 | L88: WS | M88: EDWIN ALEXANDER DIAZ PITRE | Q88: WS | R88: EDWIN ALEXANDER DIAZ PITRE | S88: 13.333333 | V88: KR | W88: PEDRO DE JESUS DE LA HOZ SALCEDO | AA88: WS | AB88: EDWIN ALEXANDER DIAZ PITRE | AF88: WS | AG88: EDWIN ALEXANDER DIAZ PITRE | AK88: WS | AL88: EDWIN ALEXANDER DIAZ PITRE | AM88: 14
B89: WS | C89: EDWIN ALFONSO ORTIZ DELGADO | G89: WS | H89: EDWIN ALFONSO ORTIZ DELGADO | I89: 0 | L89: WS | M89: EDWIN ALFONSO ORTIZ DELGADO | Q89: WS | R89: EDWIN ALFONSO ORTIZ DELGADO | S89: 64 | V89: KR | W89: RIGOBERTO ROMERO REINA | AA89: WS | AB89: EDWIN ALFONSO ORTIZ DELGADO | AF89: WS | AG89: EDWIN ALFONSO ORTIZ DELGADO | AK89: WS | AL89: EDWIN ALFONSO ORTIZ DELGADO | AM89: 15
B90: WS | C90: EDWIN CASTANEDA HENAO | D90: 140 | G90: WS | H90: EDWIN CASTANEDA HENAO | I90: 0 | L90: WS | M90: EDWIN CASTANEDA HENAO | Q90: WS | R90: EDWIN CASTANEDA HENAO | V90: KR | W90: SERGIO ALONSO ANDRADE CASTRILLON | AA90: WS | AB90: EDWIN CASTANEDA HENAO | AF90: WS | AG90: EDWIN CASTANEDA HENAO | AK90: WS | AL90: EDWIN CASTANEDA HENAO | AM90: 15
B91: WS | C91: EDWIN DIAZ MARULANDA | G91: WS | H91: EDWIN DIAZ MARULANDA | I91: 218.798 | L91: WS | M91: EDWIN DIAZ MARULANDA | Q91: WS | R91: EDWIN DIAZ MARULANDA | V91: KR | W91: SERGIO ANDRES LANDINES BARRIOS | AA91: WS | AB91: EDWIN DIAZ MARULANDA | AF91: WS | AG91: EDWIN DIAZ MARULANDA | AK91: WS | AL91: EDWIN DIAZ MARULANDA | AM91: 15
B92: KR | C92: EDWIN FERNANDO LINARES MACA | G92: KR | H92: EDWIN FERNANDO LINARES MACA | I92: 211.74 | L92: KR | M92: EDWIN FERNANDO LINARES MACA | Q92: KR | R92: EDWIN FERNANDO LINARES MACA | S92: 104.44444 | V92: KR | W92: SERGIO DAVID CORDOBA TUTA | AA92: KR | AB92: EDWIN FERNANDO LINARES MACA | AF92: KR | AG92: EDWIN FERNANDO LINARES MACA | AK92: KR | AL92: EDWIN FERNANDO LINARES MACA | AM92: 15
B93: WS | C93: EDWIN RODRIGO AVILA PENA | G93: WS | H93: EDWIN RODRIGO AVILA PENA | I93: 119.986 | L93: WS | M93: EDWIN RODRIGO AVILA PENA | Q93: WS | R93: EDWIN RODRIGO AVILA PENA | V93: KR | W93: VICTOR BLANCO BRAVO | AA93: WS | AB93: EDWIN RODRIGO AVILA PENA | AF93: WS | AG93: EDWIN RODRIGO AVILA PENA | AK93: WS | AL93: EDWIN RODRIGO AVILA PENA | AM93: 15
B94: KR | C94: EISON SALAS AHUMEDO | G94: KR | H94: EISON SALAS AHUMEDO | I94: 211.74 | L94: KR | M94: EISON SALAS AHUMEDO | Q94: KR | R94: EISON SALAS AHUMEDO | V94: KR | W94: VICTOR RAMON TUANAMA GARCIA | AA94: KR | AB94: EISON SALAS AHUMEDO | AF94: KR | AG94: EISON SALAS AHUMEDO | AK94: KR | AL94: EISON SALAS AHUMEDO | AM94: 14
B95: WS | C95: ELICEO FUENTES PARRA | G95: WS | H95: ELICEO FUENTES PARRA | I95: 0 | L95: WS | M95: ELICEO FUENTES PARRA | Q95: WS | R95: ELICEO FUENTES PARRA | V95: KR | W95: WILMAN DE AVILA MARRIAGA | AA95: WS | AB95: ELICEO FUENTES PARRA | AF95: WS | AG95: ELICEO FUENTES PARRA | AK95: WS | AL95: ELICEO FUENTES PARRA | AM95: 16
B96: KI | C96: ELKIN ARMANDO GARZON LOPEZ | G96: KI | H96: ELKIN ARMANDO GARZON LOPEZ | I96: 0 | J96: OK | L96: KI | M96: ELKIN ARMANDO GARZON LOPEZ | O96: OK | Q96: KI | R96: ELKIN ARMANDO GARZON LOPEZ | S96: 128.88889 | V96: KR | W96: XEMIR SOLER ROMERO | AA96: KI | AB96: ELKIN ARMANDO GARZON LOPEZ | AD96: OK | AF96: KI | AG96: ELKIN ARMANDO GARZON LOPEZ | AI96: OK | AK96: KI | AL96: ELKIN ARMANDO GARZON LOPEZ | AM96: 15 | AN96: OK
B97: LM | C97: ELKIN ARMANDO GARZON LOPEZ | G97: LM | H97: ELKIN ARMANDO GARZON LOPEZ | I97: 218.798 | L97: LM | M97: ELKIN ARMANDO GARZON LOPEZ | Q97: LM | R97: ELKIN ARMANDO GARZON LOPEZ | S97: 128.88889 | V97: KR | W97: YEFFERSON ZULUAGA BUITRAGO | AA97: LM | AB97: ELKIN ARMANDO GARZON LOPEZ | AF97: LM | AG97: ELKIN ARMANDO GARZON LOPEZ | AK97: LM | AL97: ELKIN ARMANDO GARZON LOPEZ | AM97: 15
B98: LM | C98: ENRI JAIME CALDAS BERMUDES | G98: LM | H98: ENRI JAIME CALDAS BERMUDES | I98: 21.174 | L98: LM | M98: ENRI JAIME CALDAS BERMUDES | Q98: LM | R98: ENRI JAIME CALDAS BERMUDES | V98: LM | W98: ALAN GERSON RAMIREZ ACARO | AA98: LM | AB98: ENRI JAIME CALDAS BERMUDES | AF98: LM | AG98: ENRI JAIME CALDAS BERMUDES | AK98: LM | AL98: ENRI JAIME CALDAS BERMUDES | AM98: 15
B99: LM | C99: ERIK RUBEN RAMIREZ SIMANCAS | G99: LM | H99: ERIK RUBEN RAMIREZ SIMANCAS | I99: 183.508 | L99: LM | M99: ERIK RUBEN RAMIREZ SIMANCAS | Q99: LM | R99: ERIK RUBEN RAMIREZ SIMANCAS | V99: LM | W99: ALEXANDER GUZMAN | AA99: LM | AB99: ERIK RUBEN RAMIREZ SIMANCAS | AC99: 0 | AF99: LM | AG99: ERIK RUBEN RAMIREZ SIMANCAS | AH99: 21.74 | AK99: LM | AL99: ERIK RUBEN RAMIREZ SIMANCAS | AM99: 15
B100: WS | C100: ERNESTO GERMAN HERRERA | D100: 300 | G100: WS | H100: ERNESTO GERMAN HERRERA | I100: 211.74 | L100: WS | M100: ERNESTO GERMAN HERRERA | Q100: WS | R100: ERNESTO GERMAN HERRERA | V100: LM | W100: ALEXIS ENRIQUE MORENO ARRIETA | AA100: WS | AB100: ERNESTO GERMAN HERRERA | AF100: WS | AG100: ERNESTO GERMAN HERRERA | AK100: WS | AL100: ERNESTO GERMAN HERRERA | AM100: 15
B101: KI | C101: EVELIO ANGULO ANGULO | G101: KI | H101: EVELIO ANGULO ANGULO | I101: 211.74 | L101: KI | M101: EVELIO ANGULO ANGULO | Q101: KI | R101: EVELIO ANGULO ANGULO | S101: 66.666667 | V101: LM | W101: ALIRIO ORTIZ MOLINA | AA101: KI | AB101: EVELIO ANGULO ANGULO | AF101: KI | AG101: EVELIO ANGULO ANGULO | AK101: KI | AL101: EVELIO ANGULO ANGULO | AM101: 15
B102: WS | C102: FABIAN ARTURO RUIZ GARCIA | D102: 300 | G102: WS | H102: FABIAN ARTURO RUIZ GARCIA | I102: 218.798 | L102: WS | M102: FABIAN ARTURO RUIZ GARCIA | Q102: WS | R102: FABIAN ARTURO RUIZ GARCIA | V102: LM | W102: ALVARO SEGOVIA TORRES | AA102: WS | AB102: FABIAN ARTURO RUIZ GARCIA | AF102: WS | AG102: FABIAN ARTURO RUIZ GARCIA | AK102: WS | AL102: FABIAN ARTURO RUIZ GARCIA | AM102: 15
...

Sheet Hoja1
A3: Etiquetas de fila | B3: Suma de Liquido total | C3: Cuenta de Status SS
A4: Ativo | B4: 59508.195 | C4: 26
A5: Não ativo | B5: 54285.071 | C5: 24
A6: Total general | B6: 113793.27 | C6: 50

Sheet Kotrik Industrial
AD1: =SUM(AR:AR) -> 116695.93
N2: CLIENTE | U2: CLIENTE 2
B3: Cod trabalhador | C3: Status SS | D3: KI | E3: KR | F3: WS | G3: LN | H3: Data admissão | I3: Data cessação | J3: Dias de alta | K3: PUXADO | L3: Colaborador | M3: Columna6 | N3: Nome cliente 1 | O3: Tarifa cliente 1 | P3: Hora por Previsão | Q3: Horas confirmadas cliente 1 | R3: Status confirmação cliente 13 | S3: Status revisão | T3: Columna3 | U3: Nome cliente 2 | V3: Tarifa cliente 2 | W3: Horas confirmadas cliente 2 | X3: Status confirmação cliente 2 | Y3: Status revisão 2 | Z3: Columna32 | AA3: Auxilio alojamento | AB3: Outros acréscimos | AC3: Columna4 | AD3: Imposto ss | AE3: Adiantamento | AF3: Desconto Carro | AG3: MULTA TRANSITO | AH3: COMBUSTIBLE | AI3: PEAJES | AJ3: SUMINISTROS | AK3: MULTA ALOJAMIENTO | AL3: LIMPIEZA O DAÑOS | AM3: EPIS | AN3: Outros descontos | AO3: Taxa bancária | AP3: Columna2 | AQ3: Valor previsão de folha | AR3: Liquido total | AS3: Columna5 | AT3: IBAN pagamento | AU3: Observações | AV3: Status pagamento cliente | AW3: Responsável pagamento | AX3: Status pagamento
B4: E0166 | C4: =IF(ISNUMBER(MATCH(Tabla57[[#This Row],[Cod trabalhador]],'Altas Industrial'!B:B, 0)), "Ativo", "Não ativo") -> Ativo | D4: =IFERROR(IF(VLOOKUP(Tabla57[[#This Row],[Cod trabalhador]],'Altas Industrial'!B:E,1,0)<>"","KI",""),"") -> KI | E4: =IFERROR(IF(VLOOKUP(Tabla57[[#This Row],[Cod trabalhador]],'Altas Rosas'!B:F,1,0)<>"","KR",""),"") | F4: =IFERROR(IF(VLOOKUP(Tabla57[[#This Row],[Cod trabalhador]],'Altas Wiseowe'!B:E,1,0)<>"","WS",""),"") | G4: =IFERROR(IF(VLOOKUP(Tabla57[[#This Row],[Cod trabalhador]],'Altas Luminous'!B:E,1,0)<>"","LM",""),"") | H4: =IFERROR(VLOOKUP(Tabla57[[#This Row],[Cod trabalhador]],'Altas Industrial'!B:E,3,FALSE),"") -> 45762 | I4: =IF(OR(Tabla57[[#This Row],[Cod trabalhador]]="",ISBLANK(Tabla57[[#This Row],[Cod trabalhador]])),"",IFERROR(IF(VLOOKUP(Tabla57[[#This Row],[Cod trabalhador]],'Altas Industrial'!B:E,4,FALSE)=0,"",VLOOKUP(Tabla57[[#This Row],[Cod trabalhador]],'Altas Industrial'!B:E,4,FALSE)),"")) -> 46053 | J4: =IF(C4="ativo", IF(ISBLANK(H4),"",MAX(0,MIN(IF(ISBLANK(I4),EOMONTH(DATE(2026,1,1),0),I4),EOMONTH(DATE(2026,1,1),0)) - MAX(H4,DATE(2026,1,1))))+1, 0 ) -> 31 | K4: ALVARO ROJAS | L4: =IFERROR(IF(Tabla57[[#This Row],[Cod trabalhador]]="",Tabla57[[#This Row],[Cod trabalhador]], INDEX(Colaborador_ID[Nombre], MATCH(Tabla57[[#This Row],[Cod trabalhador]],Colaborador_ID[Cod_colab], 0))), "") -> ALVARO ENRIQUE ROJAS DE LA OSSA | N4: 43-CAM IMPIANTI INDUSTRIALI SRL | O4: =IFERROR(VLOOKUP(Tabla57[[#This Row],[Cod trabalhador]],Tabla15[],4,FALSE),"") -> 17 | P4: =IFERROR(VLOOKUP(Tabla57[[#This Row],[Cod trabalhador]],'TotalHorasAjustadas (2)'!D:L,8,FALSE),"") -> 144 | Q4: 144 | R4: Confirmada | AA4: =IFERROR(VLOOKUP(Tabla57[[#This Row],[Cod trabalhador]],Alojamentos!B:P,11,FALSE),"") | AD4: =Tabla57[[#This Row],[Dias de alta]]*7.058 -> 218.798 | AE4: =IFERROR(VLOOKUP(Tabla57[[#This Row],[Cod trabalhador]],Adiantamentos!B:S,7,FALSE),"") | AF4: =IFERROR(VLOOKUP(Tabla57[[#This Row],[Cod trabalhador]],Carro!B:D,3,FALSE),"") | AG4: =IFERROR(VLOOKUP(Tabla57[[#This Row],[Cod trabalhador]],'Outros descontos'!B:M,7,FALSE),"") | AH4: =IFERROR(VLOOKUP(Tabla57[[#This Row],[Cod trabalhador]],'Outros descontos'!B:M,8,FALSE),"") | AI4: =IFERROR(VLOOKUP(Tabla57[[#This Row],[Cod trabalhador]],'Outros descontos'!B:M,9,FALSE),"") | AJ4: =IFERROR(VLOOKUP(Tabla57[[#This Row],[Cod trabalhador]],'Outros descontos'!B:M,10,FALSE),"") | AK4: =IFERROR(VLOOKUP(Tabla57[[#This Row],[Cod trabalhador]],'Outros descontos'!B:M,11,FALSE),"") | AL4: =IFERROR(VLOOKUP(Tabla57[[#This Row],[Cod trabalhador]],'Outros descontos'!B:M,12,FALSE),"") | AM4: =IFERROR(VLOOKUP(Tabla57[[#This Row],[Cod trabalhador]],'Outros descontos'!B:M,13,FALSE),"") | AO4: 4.08 | AQ4: =IFERROR(IF(ISNUMBER(Tabla57[[#This Row],[Hora por Previsão]])*ISNUMBER(Tabla57[[#This Row],[Tarifa cliente 1]]), Tabla57[[#This Row],[Hora por Previsão]]*Tabla57[[#This Row],[Tarifa cliente 1]], 0), 0) + IFERROR(IF(ISNUMBER(Tabla57[[#This Row],[Horas confirmadas cliente 2]])*ISNUMBER(Tabla57[[#This Row],[Tarifa cliente 2]]), Tabla57[[#This Row],[Horas confirmadas cliente 2]]*Tabla57[[#This Row],[Tarifa cliente 2]], 0), 0) + IFERROR(IF(ISNUMBER(Tabla57[[#This Row],[Auxilio alojamento]]), Tabla57[[#This Row],[Auxilio alojamento]], 0), 0)+ IFERROR(IF(ISNUMBER(Tabla57[[#This Row],[Outros acréscimos]]), Tabla57[[#This Row],[Outros acréscimos]], 0), 0) - IFERROR(IF(ISNUMBER(Tabla57[[#This Row],[Imposto ss]]), Tabla57[[#This Row],[Imposto ss]], 0), 0) - IFERROR(IF(ISNUMBER(Tabla57[[#This Row],[Adiantamento]]), Tabla57[[#This Row],[Adiantamento]], 0), 0) - IFERROR(IF(ISNUMBER(Tabla57[[#This Row],[Desconto Carro]]), Tabla57[[#This Row],[Desconto Carro]], 0), 0) - IFERROR(IF(ISNUMBER(Tabla57[[#This Row],[MULTA TRANSITO]]), Tabla57[[#This Row],[MULTA TRANSITO]], 0), 0) - IFERROR(IF(ISNUMBER(Tabla57[[#This Row],[COMBUSTIBLE]]), Tabla57[[#This Row],[COMBUSTIBLE]], 0), 0) - IFERROR(IF(ISNUMBER(Tabla57[[#This Row],[PEAJES]]), Tabla57[[#This Row],[PEAJES]], 0), 0) - IFERROR(IF(ISNUMBER(Tabla57[[#This Row],[SUMINISTROS]]), Tabla57[[#This Row],[SUMINISTROS]], 0), 0) - IFERROR(IF(ISNUMBER(Tabla57[[#This Row],[MULTA ALOJAMIENTO]]), Tabla57[[#This Row],[MULTA ALOJAMIENTO]], 0), 0) - IFERROR(IF(ISNUMBER(Tabla57[[#This Row],[LIMPIEZA O DAÑOS]]), Tabla57[[#This Row],[LIMPIEZA O DAÑOS]], 0), 0) - IFERROR(IF(ISNUMBER(Tabla57[[#This Row],[Outros descontos]]), Tabla57[[#This Row],[Outros descontos]], 0), 0) - IFERROR(IF(ISNUMBER(Tabla57[[#This Row],[Taxa bancária]]), Tabla57[[#This Row],[Taxa bancária]], 0), 0) - IFERROR(IF(ISNUMBER(Tabla57[[#This Row],[EPIS]]), Tabla57[[#This Row],[EPIS]], 0), 0) -> 2225.122 | AR4: =IFERROR(IF(ISNUMBER(Tabla57[[#This Row],[Horas confirmadas cliente 1]])*ISNUMBER(Tabla57[[#This Row],[Tarifa cliente 1]]),Tabla57[[#This Row],[Horas confirmadas cliente 1]]* Tabla57[[#This Row],[Tarifa cliente 1]], 0), 0) + IFERROR(IF(ISNUMBER(Tabla57[[#This Row],[Horas confirmadas cliente 2]])*ISNUMBER(Tabla57[[#This Row],[Tarifa cliente 2]]), Tabla57[[#This Row],[Horas confirmadas cliente 2]]*Tabla57[[#This Row],[Tarifa cliente 2]], 0), 0) + IFERROR(IF(ISNUMBER(Tabla57[[#This Row],[Auxilio alojamento]]), Tabla57[[#This Row],[Auxilio alojamento]], 0), 0)+ IFERROR(IF(ISNUMBER(Tabla57[[#This Row],[Outros acréscimos]]), Tabla57[[#This Row],[Outros acréscimos]], 0), 0) - IFERROR(IF(ISNUMBER(Tabla57[[#This Row],[Imposto ss]]), Tabla57[[#This Row],[Imposto ss]], 0), 0) - IFERROR(IF(ISNUMBER(Tabla57[[#This Row],[Adiantamento]]), Tabla57[[#This Row],[Adiantamento]], 0), 0) - IFERROR(IF(ISNUMBER(Tabla57[[#This Row],[Desconto Carro]]), Tabla57[[#This Row],[Desconto Carro]], 0), 0) - IFERROR(IF(ISNUMBER(Tabla57[[#This Row],[MULTA TRANSITO]]), Tabla57[[#This Row],[MULTA TRANSITO]], 0), 0) - IFERROR(IF(ISNUMBER(Tabla57[[#This Row],[COMBUSTIBLE]]), Tabla57[[#This Row],[COMBUSTIBLE]], 0), 0) - IFERROR(IF(ISNUMBER(Tabla57[[#This Row],[PEAJES]]), Tabla57[[#This Row],[PEAJES]], 0), 0) - IFERROR(IF(ISNUMBER(Tabla57[[#This Row],[SUMINISTROS]]), Tabla57[[#This Row],[SUMINISTROS]], 0), 0) - IFERROR(IF(ISNUMBER(Tabla57[[#This Row],[MULTA ALOJAMIENTO]]), Tabla57[[#This Row],[MULTA ALOJAMIENTO]], 0), 0) - IFERROR(IF(ISNUMBER(Tabla57[[#This Row],[LIMPIEZA O DAÑOS]]), Tabla57[[#This Row],[LIMPIEZA O DAÑOS]], 0), 0) - IFERROR(IF(ISNUMBER(Tabla57[[#This Row],[Outros descontos]]), Tabla57[[#This Row],[Outros descontos]], 0), 0) - IFERROR(IF(ISNUMBER(Tabla57[[#This Row],[Taxa bancária]]), Tabla57[[#This Row],[Taxa bancária]], 0), 0) - IFERROR(IF(ISNUMBER(Tabla57[[#This Row],[EPIS]]), Tabla57[[#This Row],[EPIS]], 0), 0) -> 2225.122 | AT4: =IF(Tabla57[[#This Row],[Cod trabalhador]]="", "", INDEX(Iban!C:C, MATCH(Tabla57[[#This Row],[Cod trabalhador]],Iban!A:A, 0))) -> NL02 BUNQ 2185 0437 57 | AW4: Fernando 16-02 | AX4: Pago
B5: E1590 | C5: =IF(ISNUMBER(MATCH(Tabla57[[#This Row],[Cod trabalhador]],'Altas Industrial'!B:B, 0)), "Ativo", "Não ativo") -> Não ativo | D5: =IFERROR(IF(VLOOKUP(Tabla57[[#This Row],[Cod trabalhador]],'Altas Industrial'!B:E,1,0)<>"","KI",""),"") | E5: =IFERROR(IF(VLOOKUP(Tabla57[[#This Row],[Cod trabalhador]],'Altas Rosas'!B:F,1,0)<>"","KR",""),"") | F5: =IFERROR(IF(VLOOKUP(Tabla57[[#This Row],[Cod trabalhador]],'Altas Wiseowe'!B:E,1,0)<>"","WS",""),"") | G5: =IFERROR(IF(VLOOKUP(Tabla57[[#This Row],[Cod trabalhador]],'Altas Luminous'!B:E,1,0)<>"","LM",""),"") | H5: =IFERROR(VLOOKUP(Tabla57[[#This Row],[Cod trabalhador]],'Altas Industrial'!B:E,3,FALSE),"") | I5: =IF(OR(Tabla57[[#This Row],[Cod trabalhador]]="",ISBLANK(Tabla57[[#This Row],[Cod trabalhador]])),"",IFERROR(IF(VLOOKUP(Tabla57[[#This Row],[Cod trabalhador]],'Altas Industrial'!B:E,4,FALSE)=0,"",VLOOKUP(Tabla57[[#This Row],[Cod trabalhador]],'Altas Industrial'!B:E,4,FALSE)),"")) | J5: =IF(C5="ativo", IF(ISBLANK(H5),"",MAX(0,MIN(IF(ISBLANK(I5),EOMONTH(DATE(2026,1,1),0),I5),EOMONTH(DATE(2026,1,1),0)) - MAX(H5,DATE(2026,1,1))))+1, 0 ) -> 0 | K5: BAIRON BURBANO | L5: =IFERROR(IF(Tabla57[[#This Row],[Cod trabalhador]]="",Tabla57[[#This Row],[Cod trabalhador]], INDEX(Colaborador_ID[Nombre], MATCH(Tabla57[[#This Row],[Cod trabalhador]],Colaborador_ID[Cod_colab], 0))), "") -> BAIRON RENE BURBANO MORALES | N5: 225-CARVISA CONTAINER SLU | O5: =IFERROR(VLOOKUP(Tabla57[[#This Row],[Cod trabalhador]],Tabla15[],4,FALSE),"") -> 15 | P5: =IFERROR(VLOOKUP(Tabla57[[#This Row],[Cod trabalhador]],'TotalHorasAjustadas (2)'!D:L,8,FALSE),"") -> 36 | Q5: 142 | R5: Pendente | AD5: =Tabla57[[#This Row],[Dias de alta]]*7.058 -> 0 | AE5: =IFERROR(VLOOKUP(Tabla57[[#This Row],[Cod trabalhador]],Adiantamentos!B:S,7,FALSE),"") -> 200 | AG5: =IFERROR(VLOOKUP(Tabla57[[#This Row],[Cod trabalhador]],'Outros descontos'!B:M,7,FALSE),"") | AH5: =IFERROR(VLOOKUP(Tabla57[[#This Row],[Cod trabalhador]],'Outros descontos'!B:M,8,FALSE),"") | AI5: =IFERROR(VLOOKUP(Tabla57[[#This Row],[Cod trabalhador]],'Outros descontos'!B:M,9,FALSE),"") | AJ5: =IFERROR(VLOOKUP(Tabla57[[#This Row],[Cod trabalhador]],'Outros descontos'!B:M,10,FALSE),"") | AK5: =IFERROR(VLOOKUP(Tabla57[[#This Row],[Cod trabalhador]],'Outros descontos'!B:M,11,FALSE),"") | AL5: =IFERROR(VLOOKUP(Tabla57[[#This Row],[Cod trabalhador]],'Outros descontos'!B:M,12,FALSE),"") | AM5: =IFERROR(VLOOKUP(Tabla57[[#This Row],[Cod trabalhador]],'Outros descontos'!B:M,13,FALSE),"") | AO5: 4.08 | AQ5: =IFERROR(IF(ISNUMBER(Tabla57[[#This Row],[Hora por Previsão]])*ISNUMBER(Tabla57[[#This Row],[Tarifa cliente 1]]), Tabla57[[#This Row],[Hora por Previsão]]*Tabla57[[#This Row],[Tarifa cliente 1]], 0), 0) + IFERROR(IF(ISNUMBER(Tabla57[[#This Row],[Horas confirmadas cliente 2]])*ISNUMBER(Tabla57[[#This Row],[Tarifa cliente 2]]), Tabla57[[#This Row],[Horas confirmadas cliente 2]]*Tabla57[[#This Row],[Tarifa cliente 2]], 0), 0) + IFERROR(IF(ISNUMBER(Tabla57[[#This Row],[Auxilio alojamento]]), Tabla57[[#This Row],[Auxilio alojamento]], 0), 0)+ IFERROR(IF(ISNUMBER(Tabla57[[#This Row],[Outros acréscimos]]), Tabla57[[#This Row],[Outros acréscimos]], 0), 0) - IFERROR(IF(ISNUMBER(Tabla57[[#This Row],[Imposto ss]]), Tabla57[[#This Row],[Imposto ss]], 0), 0) - IFERROR(IF(ISNUMBER(Tabla57[[#This Row],[Adiantamento]]), Tabla57[[#This Row],[Adiantamento]], 0), 0) - IFERROR(IF(ISNUMBER(Tabla57[[#This Row],[Desconto Carro]]), Tabla57[[#This Row],[Desconto Carro]], 0), 0) - IFERROR(IF(ISNUMBER(Tabla57[[#This Row],[MULTA TRANSITO]]), Tabla57[[#This Row],[MULTA TRANSITO]], 0), 0) - IFERROR(IF(ISNUMBER(Tabla57[[#This Row],[COMBUSTIBLE]]), Tabla57[[#This Row],[COMBUSTIBLE]], 0), 0) - IFERROR(IF(ISNUMBER(Tabla57[[#This Row],[PEAJES]]), Tabla57[[#This Row],[PEAJES]], 0), 0) - IFERROR(IF(ISNUMBER(Tabla57[[#This Row],[SUMINISTROS]]), Tabla57[[#This Row],[SUMINISTROS]], 0), 0) - IFERROR(IF(ISNUMBER(Tabla57[[#This Row],[MULTA ALOJAMIENTO]]), Tabla57[[#This Row],[MULTA ALOJAMIENTO]], 0), 0) - IFERROR(IF(ISNUMBER(Tabla57[[#This Row],[LIMPIEZA O DAÑOS]]), Tabla57[[#This Row],[LIMPIEZA O DAÑOS]], 0), 0) - IFERROR(IF(ISNUMBER(Tabla57[[#This Row],[Outros descontos]]), Tabla57[[#This Row],[Outros descontos]], 0), 0) - IFERROR(IF(ISNUMBER(Tabla57[[#This Row],[Taxa bancária]]), Tabla57[[#This Row],[Taxa bancária]], 0), 0) - IFERROR(IF(ISNUMBER(Tabla57[[#This Row],[EPIS]]), Tabla57[[#This Row],[EPIS]], 0), 0) -> 335.92 | AR5: =IFERROR(IF(ISNUMBER(Tabla57[[#This Row],[Horas confirmadas cliente 1]])*ISNUMBER(Tabla57[[#This Row],[Tarifa cliente 1]]),Tabla57[[#This Row],[Horas confirmadas cliente 1]]* Tabla57[[#This Row],[Tarifa cliente 1]], 0), 0) + IFERROR(IF(ISNUMBER(Tabla57[[#This Row],[Horas confirmadas cliente 2]])*ISNUMBER(Tabla57[[#This Row],[Tarifa cliente 2]]), Tabla57[[#This Row],[Horas confirmadas cliente 2]]*Tabla57[[#This Row],[Tarifa cliente 2]], 0), 0) + IFERROR(IF(ISNUMBER(Tabla57[[#This Row],[Auxilio alojamento]]), Tabla57[[#This Row],[Auxilio alojamento]], 0), 0)+ IFERROR(IF(ISNUMBER(Tabla57[[#This Row],[Outros acréscimos]]), Tabla57[[#This Row],[Outros acréscimos]], 0), 0) - IFERROR(IF(ISNUMBER(Tabla57[[#This Row],[Imposto ss]]), Tabla57[[#This Row],[Imposto ss]], 0), 0) - IFERROR(IF(ISNUMBER(Tabla57[[#This Row],[Adiantamento]]), Tabla57[[#This Row],[Adiantamento]], 0), 0) - IFERROR(IF(ISNUMBER(Tabla57[[#This Row],[Desconto Carro]]), Tabla57[[#This Row],[Desconto Carro]], 0), 0) - IFERROR(IF(ISNUMBER(Tabla57[[#This Row],[MULTA TRANSITO]]), Tabla57[[#This Row],[MULTA TRANSITO]], 0), 0) - IFERROR(IF(ISNUMBER(Tabla57[[#This Row],[COMBUSTIBLE]]), Tabla57[[#This Row],[COMBUSTIBLE]], 0), 0) - IFERROR(IF(ISNUMBER(Tabla57[[#This Row],[PEAJES]]), Tabla57[[#This Row],[PEAJES]], 0), 0) - IFERROR(IF(ISNUMBER(Tabla57[[#This Row],[SUMINISTROS]]), Tabla57[[#This Row],[SUMINISTROS]], 0), 0) - IFERROR(IF(ISNUMBER(Tabla57[[#This Row],[MULTA ALOJAMIENTO]]), Tabla57[[#This Row],[MULTA ALOJAMIENTO]], 0), 0) - IFERROR(IF(ISNUMBER(Tabla57[[#This Row],[LIMPIEZA O DAÑOS]]), Tabla57[[#This Row],[LIMPIEZA O DAÑOS]], 0), 0) - IFERROR(IF(ISNUMBER(Tabla57[[#This Row],[Outros descontos]]), Tabla57[[#This Row],[Outros descontos]], 0), 0) - IFERROR(IF(ISNUMBER(Tabla57[[#This Row],[Taxa bancária]]), Tabla57[[#This Row],[Taxa bancária]], 0), 0) - IFERROR(IF(ISNUMBER(Tabla57[[#This Row],[EPIS]]), Tabla57[[#This Row],[EPIS]], 0), 0) -> 1925.92 | AT5: =IF(Tabla57[[#This Row],[Cod trabalhador]]="", "", INDEX(Iban!C:C, MATCH(Tabla57[[#This Row],[Cod trabalhador]],Iban!A:A, 0))) -> ES54 0182 2270 0102 0248 1802 | AW5: Fernando 16-02 | AX5: Pago
B6: E0277 | C6: =IF(ISNUMBER(MATCH(Tabla57[[#This Row],[Cod trabalhador]],'Altas Industrial'!B:B, 0)), "Ativo", "Não ativo") -> Ativo | D6: =IFERROR(IF(VLOOKUP(Tabla57[[#This Row],[Cod trabalhador]],'Altas Industrial'!B:E,1,0)<>"","KI",""),"") -> KI | E6: =IFERROR(IF(VLOOKUP(Tabla57[[#This Row],[Cod trabalhador]],'Altas Rosas'!B:F,1,0)<>"","KR",""),"") | F6: =IFERROR(IF(VLOOKUP(Tabla57[[#This Row],[Cod trabalhador]],'Altas Wiseowe'!B:E,1,0)<>"","WS",""),"") | G6: =IFERROR(IF(VLOOKUP(Tabla57[[#This Row],[Cod trabalhador]],'Altas Luminous'!B:E,1,0)<>"","LM",""),"") | H6: =IFERROR(VLOOKUP(Tabla57[[#This Row],[Cod trabalhador]],'Altas Industrial'!B:E,3,FALSE),"") -> 45762 | I6: =IF(OR(Tabla57[[#This Row],[Cod trabalhador]]="",ISBLANK(Tabla57[[#This Row],[Cod trabalhador]])),"",IFERROR(IF(VLOOKUP(Tabla57[[#This Row],[Cod trabalhador]],'Altas Industrial'!B:E,4,FALSE)=0,"",VLOOKUP(Tabla57[[#This Row],[Cod trabalhador]],'Altas Industrial'!B:E,4,FALSE)),"")) -> 46053 | J6: =IF(C6="ativo", IF(ISBLANK(H6),"",MAX(0,MIN(IF(ISBLANK(I6),EOMONTH(DATE(2026,1,1),0),I6),EOMONTH(DATE(2026,1,1),0)) - MAX(H6,DATE(2026,1,1))))+1, 0 ) -> 31 | K6: CAMILO ANDRES VALERO PEREZ | L6: =IFERROR(IF(Tabla57[[#This Row],[Cod trabalhador]]="",Tabla57[[#This Row],[Cod trabalhador]], INDEX(Colaborador_ID[Nombre], MATCH(Tabla57[[#This Row],[Cod trabalhador]],Colaborador_ID[Cod_colab], 0))), "") -> CAMILO ANDRES VALERO PEREZ | N6: 84-GRUPO LOAFA | O6: =IFERROR(VLOOKUP(Tabla57[[#This Row],[Cod trabalhador]],Tabla15[],4,FALSE),"") -> 15 | P6: =IFERROR(VLOOKUP(Tabla57[[#This Row],[Cod trabalhador]],'TotalHorasAjustadas (2)'!D:L,8,FALSE),"") -> 201 | Q6: 201 | R6: Confirmada | AA6: =IFERROR(VLOOKUP(Tabla57[[#This Row],[Cod trabalhador]],Alojamentos!B:P,11,FALSE),"") | AD6: =Tabla57[[#This Row],[Dias de alta]]*7.058 -> 218.798 | AE6: =IFERROR(VLOOKUP(Tabla57[[#This Row],[Cod trabalhador]],Adiantamentos!B:S,7,FALSE),"") | AF6: =IFERROR(VLOOKUP(Tabla57[[#This Row],[Cod trabalhador]],Carro!B:D,3,FALSE),"") -> 145 | AG6: =IFERROR(VLOOKUP(Tabla57[[#This Row],[Cod trabalhador]],'Outros descontos'!B:M,7,FALSE),"") | AH6: =IFERROR(VLOOKUP(Tabla57[[#This Row],[Cod trabalhador]],'Outros descontos'!B:M,8,FALSE),"") | AI6: =IFERROR(VLOOKUP(Tabla57[[#This Row],[Cod trabalhador]],'Outros descontos'!B:M,9,FALSE),"") | AJ6: =IFERROR(VLOOKUP(Tabla57[[#This Row],[Cod trabalhador]],'Outros descontos'!B:M,10,FALSE),"") | AK6: =IFERROR(VLOOKUP(Tabla57[[#This Row],[Cod trabalhador]],'Outros descontos'!B:M,11,FALSE),"") | AL6: =IFERROR(VLOOKUP(Tabla57[[#This Row],[Cod trabalhador]],'Outros descontos'!B:M,12,FALSE),"") | AM6: =IFERROR(VLOOKUP(Tabla57[[#This Row],[Cod trabalhador]],'Outros descontos'!B:M,13,FALSE),"") | AO6: 4.08 | AQ6: =IFERROR(IF(ISNUMBER(Tabla57[[#This Row],[Hora por Previsão]])*ISNUMBER(Tabla57[[#This Row],[Tarifa cliente 1]]), Tabla57[[#This Row],[Hora por Previsão]]*Tabla57[[#This Row],[Tarifa cliente 1]], 0), 0) + IFERROR(IF(ISNUMBER(Tabla57[[#This Row],[Horas confirmadas cliente 2]])*ISNUMBER(Tabla57[[#This Row],[Tarifa cliente 2]]), Tabla57[[#This Row],[Horas confirmadas cliente 2]]*Tabla57[[#This Row],[Tarifa cliente 2]], 0), 0) + IFERROR(IF(ISNUMBER(Tabla57[[#This Row],[Auxilio alojamento]]), Tabla57[[#This Row],[Auxilio alojamento]], 0), 0)+ IFERROR(IF(ISNUMBER(Tabla57[[#This Row],[Outros acréscimos]]), Tabla57[[#This Row],[Outros acréscimos]], 0), 0) - IFERROR(IF(ISNUMBER(Tabla57[[#This Row],[Imposto ss]]), Tabla57[[#This Row],[Imposto ss]], 0), 0) - IFERROR(IF(ISNUMBER(Tabla57[[#This Row],[Adiantamento]]), Tabla57[[#This Row],[Adiantamento]], 0), 0) - IFERROR(IF(ISNUMBER(Tabla57[[#This Row],[Desconto Carro]]), Tabla57[[#This Row],[Desconto Carro]], 0), 0) - IFERROR(IF(ISNUMBER(Tabla57[[#This Row],[MULTA TRANSITO]]), Tabla57[[#This Row],[MULTA TRANSITO]], 0), 0) - IFERROR(IF(ISNUMBER(Tabla57[[#This Row],[COMBUSTIBLE]]), Tabla57[[#This Row],[COMBUSTIBLE]], 0), 0) - IFERROR(IF(ISNUMBER(Tabla57[[#This Row],[PEAJES]]), Tabla57[[#This Row],[PEAJES]], 0), 0) - IFERROR(IF(ISNUMBER(Tabla57[[#This Row],[SUMINISTROS]]), Tabla57[[#This Row],[SUMINISTROS]], 0), 0) - IFERROR(IF(ISNUMBER(Tabla57[[#This Row],[MULTA ALOJAMIENTO]]), Tabla57[[#This Row],[MULTA ALOJAMIENTO]], 0), 0) - IFERROR(IF(ISNUMBER(Tabla57[[#This Row],[LIMPIEZA O DAÑOS]]), Tabla57[[#This Row],[LIMPIEZA O DAÑOS]], 0), 0) - IFERROR(IF(ISNUMBER(Tabla57[[#This Row],[Outros descontos]]), Tabla57[[#This Row],[Outros descontos]], 0), 0) - IFERROR(IF(ISNUMBER(Tabla57[[#This Row],[Taxa bancária]]), Tabla57[[#This Row],[Taxa bancária]], 0), 0) - IFERROR(IF(ISNUMBER(Tabla57[[#This Row],[EPIS]]), Tabla57[[#This Row],[EPIS]], 0), 0) -> 2647.122 | AR6: =IFERROR(IF(ISNUMBER(Tabla57[[#This Row],[Horas confirmadas cliente 1]])*ISNUMBER(Tabla57[[#This Row],[Tarifa cliente 1]]),Tabla57[[#This Row],[Horas confirmadas cliente 1]]* Tabla57[[#This Row],[Tarifa cliente 1]], 0), 0) + IFERROR(IF(ISNUMBER(Tabla57[[#This Row],[Horas confirmadas cliente 2]])*ISNUMBER(Tabla57[[#This Row],[Tarifa cliente 2]]), Tabla57[[#This Row],[Horas confirmadas cliente 2]]*Tabla57[[#This Row],[Tarifa cliente 2]], 0), 0) + IFERROR(IF(ISNUMBER(Tabla57[[#This Row],[Auxilio alojamento]]), Tabla57[[#This Row],[Auxilio alojamento]], 0), 0)+ IFERROR(IF(ISNUMBER(Tabla57[[#This Row],[Outros acréscimos]]), Tabla57[[#This Row],[Outros acréscimos]], 0), 0) - IFERROR(IF(ISNUMBER(Tabla57[[#This Row],[Imposto ss]]), Tabla57[[#This Row],[Imposto ss]], 0), 0) - IFERROR(IF(ISNUMBER(Tabla57[[#This Row],[Adiantamento]]), Tabla57[[#This Row],[Adiantamento]], 0), 0) - IFERROR(IF(ISNUMBER(Tabla57[[#This Row],[Desconto Carro]]), Tabla57[[#This Row],[Desconto Carro]], 0), 0) - IFERROR(IF(ISNUMBER(Tabla57[[#This Row],[MULTA TRANSITO]]), Tabla57[[#This Row],[MULTA TRANSITO]], 0), 0) - IFERROR(IF(ISNUMBER(Tabla57[[#This Row],[COMBUSTIBLE]]), Tabla57[[#This Row],[COMBUSTIBLE]], 0), 0) - IFERROR(IF(ISNUMBER(Tabla57[[#This Row],[PEAJES]]), Tabla57[[#This Row],[PEAJES]], 0), 0) - IFERROR(IF(ISNUMBER(Tabla57[[#This Row],[SUMINISTROS]]), Tabla57[[#This Row],[SUMINISTROS]], 0), 0) - IFERROR(IF(ISNUMBER(Tabla57[[#This Row],[MULTA ALOJAMIENTO]]), Tabla57[[#This Row],[MULTA ALOJAMIENTO]], 0), 0) - IFERROR(IF(ISNUMBER(Tabla57[[#This Row],[LIMPIEZA O DAÑOS]]), Tabla57[[#This Row],[LIMPIEZA O DAÑOS]], 0), 0) - IFERROR(IF(ISNUMBER(Tabla57[[#This Row],[Outros descontos]]), Tabla57[[#This Row],[Outros descontos]], 0), 0) - IFERROR(IF(ISNUMBER(Tabla57[[#This Row],[Taxa bancária]]), Tabla57[[#This Row],[Taxa bancária]], 0), 0) - IFERROR(IF(ISNUMBER(Tabla57[[#This Row],[EPIS]]), Tabla57[[#This Row],[EPIS]], 0), 0) -> 2647.122 | AT6: =IF(Tabla57[[#This Row],[Cod trabalhador]]="", "", INDEX(Iban!C:C, MATCH(Tabla57[[#This Row],[Cod trabalhador]],Iban!A:A, 0))) -> ES44 0182 4388 1902 0186 5368 | AW6: Fernando 16-02 | AX6: Pago
